Workbook

Sheet DIA_Danh Mục Đầu Tư
A1: DIA+ - DANH MỤC ĐẦU TƯ
A3: STT | B3: Danh mục | C3: Số lượng | D3: Đơn giá | E3: Thành tiền | F3: Thời gian sử dụng | G3: Khấu hao / phân bổ | H3: Ghi chú
A4: 1 | B4: Laptop Lenovo LOQ | C4: ='DIA_Giả Định'!$N$129 -> 5 | D4: ='DIA_Giả Định'!$N$130 -> 24700000 | E4: =C4*D4 -> 123500000 | F4: ='DIA_Giả Định'!$N$65 -> 4 | G4: Có | H4: Mua 5 Laptop cho công ty (Chi 1 lần)
A5: 2 | B5: Điện thoại Iphone/demo test | C5: ='DIA_Giả Định'!$N$131 -> 1 | D5: ='DIA_Giả Định'!$N$132 -> 16300000 | E5: =C5*D5 -> 16300000 | F5: ='DIA_Giả Định'!$N$65 -> 4 | G5: Có | H5: Giá ngày 20/07/2026 tham khảo tại CellphoneS
A6: 3 | B6: Lương đội ngũ công nghệ | C6: 1 | D6: ='DIA_Giả Định'!$N$75*12 -> 300000000 | E6: ='DIA_Giả Định'!$N$75*12 -> 300000000 | F6: 1 | H6: 30.000.000đ/tháng
A7: 4 | B7: Thuê mặt bằng văn phòng co - working | C7: 1 | D7: 0 | E7: 0 | F7: 0 | H7: Năm đầu chưa thuê mặt bằng
A8: 5 | B8: Bảo mật và lưu trữ thông tin | C8: =SUM(C9:C13) -> 5 | D8: =SUM(D9:D13) -> 96000000 | E8: =SUM(E9:E13) -> 96000000 | F8: 1 | G8: Có
B9: - Bảo mật Đám mây (Cloudflare Pro/WAF) | C9: ='DIA_Giả Định'!$N$133 -> 1 | D9: ='DIA_Giả Định'!$N$134 -> 6400000 | E9: =C9*D9 -> 6400000 | F9: 1,0 năm | G9: Có | H9: Giá được tham khảo tại trang web cloudflare.com với gói Pro $240/năm tương đương $20/tháng và tỷ giá được xác định theo ngày 20/07/2026 với 1 USD = 26.940 VND | J9: Note: - Do thuê mặt bằng là Co - working nó sẽ bao hàm hết, không cần trả phí điện nước hay mạng.
B10: - Vercel Pro | C10: 1 | D10: 6500000 | E10: =C10*D10 -> 6500000 | F10: 1,0 năm | G10: Có | H10: Hosting cho Frontend (React/PWA)
B11: - Render / AWS EC2 | C11: 1 | D11: 2000000 | E11: =C11*D11 -> 2000000 | F11: 1,0 năm | G11: Có | H11: Hosting cho Backend (Node.js)
B12: - Supabase (Pro) | C12: 1 | D12: 8100000 | E12: =C12*D12 -> 8100000 | F12: 1,0 năm | G12: Có | H12: Database PostgreSQL lưu bệnh án bảo mật
B13: - AWS S3 | C13: 1 | D13: 73000000 | E13: =C13*D13 -> 73000000 | F13: 1,0 năm | G13: Có | H13: lưu trữ ảnh đơn thuốc
A14: 6 | B14: Bản quyền Microsoft 365 Family chính hãng (có AI Copilot) | C14: ='DIA_Giả Định'!$N$135 -> 1 | D14: ='DIA_Giả Định'!$N$136 -> 2600000 | E14: =C14*D14 -> 2600000 | F14: ='DIA_Giả Định'!$N$64 -> 1 | G14: Có
A15: 7 | B15: Tích hợp AI | C15: ='DIA_Giả Định'!$N$139 -> 2 | D15: =SUM(D16+D17) -> 11300000 | E15: =SUM(E16+E17) -> 11300000 | F15: ='DIA_Giả Định'!$N$64 -> 1 | G15: Có
B16: - AI của Google Pro (đã bao gồm VAT) | C16: 1 | D16: 4100000 | E16: =C16*D16 -> 4100000 | F16: 1,0 năm | G16: Có | H16: Giá được giảm khi sử dụng năm đầu, giá sau đó là 5.555.55 6 ₫/năm
B17: - Claude Team (Standard seat) (đã bao gồm VAT) | C17: 1 | D17: 7200000 | E17: =C17*D17 -> 7200000 | F17: 1,0 năm | G17: Có | H17: Giá được tham khảo tại trang webclaude.com với gói Team $240/năm tương đương $20/tháng và tỷ giá được xác định theo ngày 20/07/2026 với 1 USD = 26.940 VND
A18: 8 | B18: Tư vấn pháp lý và đăng ký kinh doanh | C18: ='DIA_Giả Định'!$N$141 -> 6 | D18: =SUM(D19:D24) -> 41000000 | E18: =SUM(E19:E24) -> 41000000 | F18: 0 | G18: Không
B19: - Thuê đơn vị hỗ trợ đăng ký thành lập doanh nghiệp đầy đủ (đã bao gồm ký quỹ ngân hàng) | C19: 1 | D19: 6000000 | E19: 6000000 | F19: 0,0 năm | G19: Không | H19: Đã bao trọn gói, ký quỹ và thuê địa chỉ
B20: - Kế toán dịch vụ (phí 1 tháng) | C20: 1 | D20: 5000000 | E20: 5000000 | F20: 0,0 năm | G20: Không | H20: Báo cáo hàng tháng
B21: - Đăng ký sở hữu trí tuệ (nhãn hiệu) | C21: 1 | D21: ='DIA_Giả Định'!$N$103 -> 5000000 | E21: ='DIA_Giả Định'!$N$103 -> 5000000 | F21: 0,0 năm | G21: Không | H21: Đã bao gồm phí đăng ký và thuê Đại lý sở hữu công nghiệp
B22: - Tư vấn pháp lý y tế | C22: 1 | D22: 20000000 | E22: 20000000 | F22: 0,0 năm | G22: Không | H22: Chính sách dữ liệu y tế (HIPAA/VN)
B23: - Đăng ký bản quyền phần mềm app | C23: 1 | D23: 3000000 | E23: 3000000 | F23: 0,0 năm | G23: Không | H23: Thuê dịch vụ, giá tham khảo tại Luật Trí Nam
B24: - Giấy phép Thương mại điện tử (Bộ Công Thương) | C24: 1 | D24: 2000000 | E24: 2000000 | F24: 0,0 năm | G24: Không | H24: Thuê dịch vụ soạn hồ sơ
A25: 9 | B25: Hạ tầng công nghệ | C25: =SUM(C26:C33) -> 12 | D25: =SUM(D26:D33) -> 259850000 | E25: =SUM(E26:E33) -> 264650000 | F25: 1 | G25: có
B26: - SendGrid / Resend Gói Essentials (50K email/tháng) | C26: 1 | D26: 6500000 | E26: 6500000 | F26: 1 | G26: có | H26: Hệ thống gửi Email OTP tự động
B27: - Zalo ZNS / SMS | C27: 1 | D27: 151200000 | E27: 151200000 | F27: 1 | G27: có | H27: 1. Phí đăng ký thương hiệu chính thống bảo mật y tế: ~ 600.000đ/năm 2. Ước tính giá tin nhắn 1 năm: 50.000 tin / tháng ~150.600.000đ/năm
B28: - Apple Developer | C28: 1 | D28: 2700000 | E28: 2700000 | F28: 1 | G28: có | H28: Tài khoản App Store (Thanh toán năm)
B29: - Google Play Console | C29: 1 | D29: 700000 | E29: 700000 | F29: 1 | G29: có | H29: Tài khoản CH Play (Đóng 1 lần vĩnh viễn)
B30: - Tên miền (domain) | C30: 1 | D30: 700000 | E30: 700000 | F30: 1 | G30: có | H30: diaplus.vn / diaplus.app
B31: - Email workspace | C31: 1 | D31: 850000 | E31: 850000 | F31: 1 | G31: có | H31: Email doanh nghiệp (vd: contact@diaplus.vn)
B32: - GitHub Team/Pro | C32: 5 | D32: 1200000 | E32: =C32*D32 -> 6000000 | F32: 1 | G32: có | H32: Quản lý mã nguồn nhóm
B33: - Thiết kế UI/UX - Loveable | C33: ='DIA_Giả Định'!$N$92 -> 1 | D33: ='DIA_Giả Định'!$N$93 -> 96000000 | E33: =C33*D33 -> 96000000 | F33: 1 | G33: có | H33: Thiết kế UI/UX
A34: 10 | B34: Dự phòng ban đầu - dự trù chi phí phát sinh | C34: ='DIA_Giả Định'!$N$137 -> 2 | D34: ='DIA_Giả Định'!$N$138 -> 320000000 | E34: ='DIA_Giả Định'!$N$138 -> 320000000 | F34: ='DIA_Giả Định'!$N$64 -> 1 | G34: kHÔNG
B35: - Phát triển MVP | C35: 1 | D35: 220000000 | E35: 220000000 | F35: ='DIA_Giả Định'!$N$64 -> 1 | G35: kHÔNG | H35: Sản phẩm khả dụng tối thiểu)
B36: - Backend và cơ sở dữ liệu | C36: 1 | D36: 180000000 | E36: 180000000 | F36: ='DIA_Giả Định'!$N$64 -> 1 | G36: kHÔNG | H36: Bảo vệ thông tin bệnh nhân và Tối ưu chi phí & Hiệu năng
A37: TỔNG DANH MỤC ĐẦU TƯ CHI TIẾT | E37: =SUM(E4:E8,E14:E15,E18,E25,E34) -> 1175350000
H40: .

Sheet DIA_Giả Định
A1: DIA+ - GIẢ ĐỊNH ĐẦU VÀO & KỊCH BẢN 3 NĂM
B2: Cơ sở | D2: Note: - Thận trọng: Nếu mọi thứ diễn ra không thuận lợi lắm. - Cơ sở: Kịch bản có khả năng xảy ra nhất - Tích cực: Nếu mọi thứ diễn ra thuận lợi hơn dự kiến
A3: Nhóm | B3: Mã biến | C3: Biến số | D3: Đơn vị | E3: Thận trọng Năm 1 | F3: Thận trọng Năm 2 | G3: Thận trọng Năm 3 | H3: Cơ sở Năm 1 | I3: Cơ sở Năm 2 | J3: Cơ sở Năm 3 | K3: Tích cực Năm 1 | L3: Tích cực Năm 2 | M3: Tích cực Năm 3 | N3: Kịch bản chọn Năm 1 | O3: Kịch bản chọn Năm 2 | P3: Kịch bản chọn Năm 3 | Q3: Nguồn / căn cứ | R3: Trạng thái
A4: A. NGƯỜI DÙNG
A5: Người dùng | B5: months_year | C5: Số tháng trong năm | D5: tháng | E5: 12 | F5: 12 | G5: 12 | H5: 12 | I5: 12 | J5: 12 | K5: 12 | L5: 12 | M5: 12 | N5: =IF($B$2="Thận trọng",E5,IF($B$2="Cơ sở",H5,K5)) -> 12 | O5: =IF($B$2="Thận trọng",F5,IF($B$2="Cơ sở",I5,L5)) -> 12 | P5: =IF($B$2="Thận trọng",G5,IF($B$2="Cơ sở",J5,M5)) -> 12 | Q5: Quy ước mô hình | R5: Quy ước
A6: Người dùng | B6: users_total | C6: Tổng người dùng đăng ký | D6: người | E6: 20000 | F6: 30000 | G6: =(G25*G31 + G26*G32)*0.5 + 20000 -> 37500 | H6: =(H25*H31 + H26*H32)*0.5 + 40000 -> 70000 | I6: =(I25*I31 + I26*I32)*0.5 + 70000 -> 190000 | J6: 70000 | K6: 50000 | L6: 70000 | M6: 100000 | N6: =IF($B$2="Thận trọng",E6,IF($B$2="Cơ sở",H6,K6)) -> 70000 | O6: =IF($B$2="Thận trọng",F6,IF($B$2="Cơ sở",I6,L6)) -> 190000 | P6: =IF($B$2="Thận trọng",G6,IF($B$2="Cơ sở",J6,M6)) -> 70000 | Q6: Giả định với mục tiêu tăng trưởng theo 3 giai đoạn: thử nghiệm – tăng trưởng – mở rộng. | R6: Đã xác nhận
A7: Người dùng | B7: mau_rate | C7: Tỷ lệ người dùng hoạt động MAU | D7: % | E7: 0.3 | F7: 0.4 | G7: 0.5 | H7: 0.35 | I7: 0.45 | J7: 0.55 | K7: 0.4 | L7: 0.5 | M7: 0.6 | N7: =IF($B$2="Thận trọng",E7,IF($B$2="Cơ sở",H7,K7)) -> 0.35 | O7: =IF($B$2="Thận trọng",F7,IF($B$2="Cơ sở",I7,L7)) -> 0.45 | P7: =IF($B$2="Thận trọng",G7,IF($B$2="Cơ sở",J7,M7)) -> 0.55 | Q7: Giả định ban đầu | R7: Đã xác nhận
A8: Người dùng | B8: pro_conv | C8: Tỷ lệ chuyển đổi Free → Pro | D8: % | E8: 0.03 | F8: 0.04 | G8: 0.05 | H8: 0.04 | I8: 0.05 | J8: 0.06 | K8: 0.05 | L8: 0.06 | M8: 0.07 | N8: =IF($B$2="Thận trọng",E8,IF($B$2="Cơ sở",H8,K8)) -> 0.04 | O8: =IF($B$2="Thận trọng",F8,IF($B$2="Cơ sở",I8,L8)) -> 0.05 | P8: =IF($B$2="Thận trọng",G8,IF($B$2="Cơ sở",J8,M8)) -> 0.06 | Q8: Giả định | R8: Đã xác nhận
A9: Người dùng | B9: pro_monthly_share | C9: Tỷ lệ Pro trả theo tháng | D9: % | E9: 0.75 | F9: 0.7 | G9: 0.65 | H9: 0.7 | I9: 0.65 | J9: 0.6 | K9: 0.65 | L9: 0.6 | M9: 0.55 | N9: =IF($B$2="Thận trọng",E9,IF($B$2="Cơ sở",H9,K9)) -> 0.7 | O9: =IF($B$2="Thận trọng",F9,IF($B$2="Cơ sở",I9,L9)) -> 0.65 | P9: =IF($B$2="Thận trọng",G9,IF($B$2="Cơ sở",J9,M9)) -> 0.6 | Q9: Giả định ban đầu | R9: Đã xác nhận
A10: Người dùng | B10: pro_annual_share | C10: Tỷ lệ Pro trả theo năm | D10: % | E10: 0.25 | F10: 0.3 | G10: 0.35 | H10: 0.3 | I10: 0.35 | J10: 0.4 | K10: 0.35 | L10: 0.4 | M10: 0.45 | N10: =IF($B$2="Thận trọng",E10,IF($B$2="Cơ sở",H10,K10)) -> 0.3 | O10: =IF($B$2="Thận trọng",F10,IF($B$2="Cơ sở",I10,L10)) -> 0.35 | P10: =IF($B$2="Thận trọng",G10,IF($B$2="Cơ sở",J10,M10)) -> 0.4 | Q10: Giả định ban đầu | R10: Đã xác nhận
A11: Người dùng | B11: clinic_monthly_share | C11: Tỷ lệ Clinic trả theo tháng | D11: % | E11: 0.8 | F11: 0.7 | G11: 0.6 | H11: 0.6 | I11: 0.45 | J11: 0.35 | K11: 0.4 | L11: 0.25 | M11: 0.15 | N11: =IF($B$2="Thận trọng",E11,IF($B$2="Cơ sở",H11,K11)) -> 0.6 | O11: =IF($B$2="Thận trọng",F11,IF($B$2="Cơ sở",I11,L11)) -> 0.45 | P11: =IF($B$2="Thận trọng",G11,IF($B$2="Cơ sở",J11,M11)) -> 0.35 | Q11: Giả định ban đầu | R11: Đã xác nhận
A12: Người dùng | B12: clinic_annual_share | C12: Tỷ lệ Clinc trả theo năm | D12: % | E12: 0.2 | F12: 0.3 | G12: 0.4 | H12: 0.4 | I12: 0.55 | J12: 0.65 | K12: 0.6 | L12: 0.75 | M12: 0.85 | N12: =IF($B$2="Thận trọng",E12,IF($B$2="Cơ sở",H12,K12)) -> 0.4 | O12: =IF($B$2="Thận trọng",F12,IF($B$2="Cơ sở",I12,L12)) -> 0.55 | P12: =IF($B$2="Thận trọng",G12,IF($B$2="Cơ sở",J12,M12)) -> 0.65 | Q12: Giả định ban đầu | R12: Đã xác nhận
A13: Người dùng | B13: mau | C13: Số người thật sự dùng (MAU) | D13: người | E13: =E6*E7 -> 6000 | F13: =F6*F7 -> 12000 | G13: =G6*G7 -> 18750 | H13: =H6*H7 -> 24500 | I13: =I6*I7 -> 85500 | J13: =J6*J7 -> 38500 | K13: =K6*K7 -> 20000 | L13: =L6*L7 -> 35000 | M13: =M6*M7 -> 60000 | N13: =IF($B$2="Thận trọng",E13,IF($B$2="Cơ sở",H13,K13)) -> 24500 | O13: =IF($B$2="Thận trọng",F13,IF($B$2="Cơ sở",I13,L13)) -> 85500 | P13: =IF($B$2="Thận trọng",G13,IF($B$2="Cơ sở",J13,M13)) -> 38500 | Q13: Giả định ban đầu | R13: Đã xác nhận
A14: Người dùng | B14: b2c_mau | C14: Số người thật sự dùng phân khúc bệnh nhân | D14: người | E14: 5950 | F14: 11900 | G14: 22300 | H14: 13900 | I14: 22350 | J14: 38250 | K14: 19850 | L14: 34800 | M14: 59650 | N14: =IF($B$2="Thận trọng",E14,IF($B$2="Cơ sở",H14,K14)) -> 13900 | O14: =IF($B$2="Thận trọng",F14,IF($B$2="Cơ sở",I14,L14)) -> 22350 | P14: =IF($B$2="Thận trọng",G14,IF($B$2="Cơ sở",J14,M14)) -> 38250 | Q14: Giả định ban đầu | R14: Đã xác nhận
A15: Người dùng | B15: b2c_clinic_mau | C15: Số người thật sự dùng phân khúc phòng khám | D15: người | E15: =E13-E14 -> 50 | F15: =F13-F14 -> 100 | G15: =G13-G14 -> -3550 | H15: =H13-H14 -> 10600 | I15: =I13-I14 -> 63150 | J15: =J13-J14 -> 250 | K15: =K13-K14 -> 150 | L15: =L13-L14 -> 200 | M15: =M13-M14 -> 350 | N15: =IF($B$2="Thận trọng",E15,IF($B$2="Cơ sở",H15,K15)) -> 10600 | O15: =IF($B$2="Thận trọng",F15,IF($B$2="Cơ sở",I15,L15)) -> 63150 | P15: =IF($B$2="Thận trọng",G15,IF($B$2="Cơ sở",J15,M15)) -> 250 | Q15: Giả định ban đầu | R15: Đã xác nhận
A16: Người dùng | B16: b2c_retention_monthly | C16: Tỷ lệ giữ chân hằng tháng phân khúc bệnh nhân | D16: % | E16: 0.915 | F16: 0.92 | G16: 0.925 | H16: 0.935 | I16: 0.942 | J16: 0.95 | K16: 0.952 | L16: 0.958 | M16: 0.965 | N16: =IF($B$2="Thận trọng",E16,IF($B$2="Cơ sở",H16,K16)) -> 0.935 | O16: =IF($B$2="Thận trọng",F16,IF($B$2="Cơ sở",I16,L16)) -> 0.942 | P16: =IF($B$2="Thận trọng",G16,IF($B$2="Cơ sở",J16,M16)) -> 0.95 | Q16: Giả định ban đầu | R16: Đã xác nhận
A17: Người dùng | B17: b2c_churn_monthly | C17: Tỷ lệ rời bỏ hằng tháng phân khúc bệnh nhân | D17: % | E17: =100% - E16 -> 0.085 | F17: =100% - F16 -> 0.08 | G17: =100% - G16 -> 0.075 | H17: =100% - H16 -> 0.065 | I17: =100% - I16 -> 0.058 | J17: =100% - J16 -> 0.05 | K17: =100% - K16 -> 0.048 | L17: =100% - L16 -> 0.042 | M17: =100% - M16 -> 0.035 | N17: =IF($B$2="Thận trọng",E17,IF($B$2="Cơ sở",H17,K17)) -> 0.065 | O17: =IF($B$2="Thận trọng",F17,IF($B$2="Cơ sở",I17,L17)) -> 0.058 | P17: =IF($B$2="Thận trọng",G17,IF($B$2="Cơ sở",J17,M17)) -> 0.05 | Q17: Giả định ban đầu | R17: Đã xác nhận
A18: Người dùng | B18: b2b_retention_monthly | C18: Tỷ lệ giữ chân hằng tháng phân khúc phòng khám | D18: % | E18: 0.965 | F18: 0.97 | G18: 0.975 | H18: 0.982 | I18: 0.986 | J18: 0.99 | K18: 0.991 | L18: 0.993 | M18: 0.995 | N18: =IF($B$2="Thận trọng",E18,IF($B$2="Cơ sở",H18,K18)) -> 0.982 | O18: =IF($B$2="Thận trọng",F18,IF($B$2="Cơ sở",I18,L18)) -> 0.986 | P18: =IF($B$2="Thận trọng",G18,IF($B$2="Cơ sở",J18,M18)) -> 0.99 | Q18: Giả định ban đầu | R18: Đã xác nhận
A19: Người dùng | B19: b2b_churn_monthly | C19: Tỷ lệ rời bỏ hằng tháng phân khúc phòng khám | D19: % | E19: =100% - E18 -> 0.035 | F19: =100% - F18 -> 0.03 | G19: =100% - G18 -> 0.025 | H19: =100% - H18 -> 0.018 | I19: =100% - I18 -> 0.014 | J19: =100% - J18 -> 0.01 | K19: =100% - K18 -> 0.009 | L19: =100% - L18 -> 0.007 | M19: =100% - M18 -> 0.005 | N19: =IF($B$2="Thận trọng",E19,IF($B$2="Cơ sở",H19,K19)) -> 0.018 | O19: =IF($B$2="Thận trọng",F19,IF($B$2="Cơ sở",I19,L19)) -> 0.014 | P19: =IF($B$2="Thận trọng",G19,IF($B$2="Cơ sở",J19,M19)) -> 0.01 | Q19: Giả định ban đầu | R19: Đã xác nhận
A20: Người dùng | B20: new_users | C20: Tổng số người dùng mới trong năm | D20: người | E20: =E21+E22 -> 6000 | F20: =F21+F22 -> 6507.5 | G20: =G21+G22 -> 7705 | H20: =H21+H22 -> 24500 | I20: =I21+I22 -> 62094.3 | J20: =J21+J22 -> -44819.6 | K20: =K21+K22 -> 20000 | L20: =L21+L22 -> 15954.15 | M20: =M21+M22 -> 26463 | N20: =IF($B$2="Thận trọng",E20,IF($B$2="Cơ sở",H20,K20)) -> 24500 | O20: =IF($B$2="Thận trọng",F20,IF($B$2="Cơ sở",I20,L20)) -> 62094.3 | P20: =IF($B$2="Thận trọng",G20,IF($B$2="Cơ sở",J20,M20)) -> -44819.6 | Q20: Giả định, chênh lệch mục tiêu người dùng cuối năm | R20: Đã xác nhận
A21: Người dùng | B21: b2c_new_users_annual | C21: Tổng số người dùng mới là bệnh nhân trong năm | D21: người | E21: =E14 -> 5950 | F21: =F14-E14*E16 -> 6455.75 | G21: =G14-F14*F16 -> 11352 | H21: =H14 -> 13900 | I21: =I14-H14*H16 -> 9353.5 | J21: =J14-I14*I16 -> 17196.3 | K21: =K14 -> 19850 | L21: =L14-K14*K16 -> 15902.8 | M21: =M14-L14*L16 -> 26311.6 | N21: =IF($B$2="Thận trọng",E21,IF($B$2="Cơ sở",H21,K21)) -> 13900 | O21: =IF($B$2="Thận trọng",F21,IF($B$2="Cơ sở",I21,L21)) -> 9353.5 | P21: =IF($B$2="Thận trọng",G21,IF($B$2="Cơ sở",J21,M21)) -> 17196.3 | Q21: Giả định ban đầu | R21: Đã xác nhận
A22: Người dùng | B22: b2b_new_clinics_annual | C22: Tổng số người dùng mới là phòng khám trong năm | D22: người | E22: =E15 -> 50 | F22: =F15-E15*E18 -> 51.75 | G22: =G15-F15*F18 -> -3647 | H22: =H15 -> 10600 | I22: =I15-H15*H18 -> 52740.8 | J22: =J15-I15*I18 -> -62015.9 | K22: =K15 -> 150 | L22: =L15-K15*K18 -> 51.35 | M22: =M15-L15*L18 -> 151.4 | N22: =IF($B$2="Thận trọng",E22,IF($B$2="Cơ sở",H22,K22)) -> 10600 | O22: =IF($B$2="Thận trọng",F22,IF($B$2="Cơ sở",I22,L22)) -> 52740.8 | P22: =IF($B$2="Thận trọng",G22,IF($B$2="Cơ sở",J22,M22)) -> -62015.9 | Q22: Giả định ban đầu | R22: Đã xác nhận
A23: Người dùng | B23: scans_per_mau | C23: Lượt quét đơn thuốc / MAU / tháng | D23: lượt | E23: 0.8 | F23: 1 | G23: 1.2 | H23: 1 | I23: 1.2 | J23: 1.5 | K23: 1.2 | L23: 1.5 | M23: 1.8 | N23: =IF($B$2="Thận trọng",E23,IF($B$2="Cơ sở",H23,K23)) -> 1 | O23: =IF($B$2="Thận trọng",F23,IF($B$2="Cơ sở",I23,L23)) -> 1.2 | P23: =IF($B$2="Thận trọng",G23,IF($B$2="Cơ sở",J23,M23)) -> 1.5 | Q23: Giả định theo mức sử dụng AI/OCR | R23: Đã xác nhận
A24: B. KHÁCH HÀNG TỔ CHỨC
A25: Tổ chức | B25: hospitals_end | C25: Số bệnh viện cuối năm | D25: cơ sở | E25: 1 | F25: 3 | G25: 5 | H25: 10 | I25: 30 | J25: 10 | K25: 3 | L25: 8 | M25: 15 | N25: =IF($B$2="Thận trọng",E25,IF($B$2="Cơ sở",H25,K25)) -> 10 | O25: =IF($B$2="Thận trọng",F25,IF($B$2="Cơ sở",I25,L25)) -> 30 | P25: =IF($B$2="Thận trọng",G25,IF($B$2="Cơ sở",J25,M25)) -> 10 | Q25: Năm 1 ưu tiên pilot; năm 2–3 mở rộng qua đối tác y tế. | R25: Đã xác nhận
A26: Tổ chức | B26: clinics_end | C26: Số phòng khám cuối năm | D26: cơ sở | E26: 3 | F26: 10 | G26: 20 | H26: 50 | I26: 150 | J26: 30 | K26: 8 | L26: 22 | M26: 40 | N26: =IF($B$2="Thận trọng",E26,IF($B$2="Cơ sở",H26,K26)) -> 50 | O26: =IF($B$2="Thận trọng",F26,IF($B$2="Cơ sở",I26,L26)) -> 150 | P26: =IF($B$2="Thận trọng",G26,IF($B$2="Cơ sở",J26,M26)) -> 30 | Q26: Giả định theo chiến lược B2B2C | R26: Đã xác nhận
A27: Tổ chức | B27: new_hospitals | C27: Bệnh viện ký mới trong năm | D27: cơ sở | E27: 1 | F27: 2 | G27: 3 | H27: 2 | I27: 3 | J27: 5 | K27: 3 | L27: 5 | M27: 7 | N27: =IF($B$2="Thận trọng",E27,IF($B$2="Cơ sở",H27,K27)) -> 2 | O27: =IF($B$2="Thận trọng",F27,IF($B$2="Cơ sở",I27,L27)) -> 3 | P27: =IF($B$2="Thận trọng",G27,IF($B$2="Cơ sở",J27,M27)) -> 5 | Q27: Giả định pipeline bán hàng | R27: Đã xác nhận
A28: Tổ chức | B28: new_clinics | C28: Phòng khám ký mới trong năm | D28: cơ sở | E28: 3 | F28: 7 | G28: 12 | H28: 5 | I28: 10 | J28: 20 | K28: 8 | L28: 14 | M28: 28 | N28: =IF($B$2="Thận trọng",E28,IF($B$2="Cơ sở",H28,K28)) -> 5 | O28: =IF($B$2="Thận trọng",F28,IF($B$2="Cơ sở",I28,L28)) -> 10 | P28: =IF($B$2="Thận trọng",G28,IF($B$2="Cơ sở",J28,M28)) -> 20 | Q28: Giả định pipeline bán hàng | R28: Đã xác nhận
A29: Tổ chức | B29: new_facilities | C29: Tổng cơ sở ký mới trong năm | D29: cơ sở | E29: =SUM(E27+E28) -> 4 | F29: =SUM(F27+F28) -> 9 | G29: =SUM(G27+G28) -> 15 | H29: =SUM(H27+H28) -> 7 | I29: =SUM(I27+I28) -> 13 | J29: =SUM(J27+J28) -> 25 | K29: =SUM(K27+K28) -> 11 | L29: =SUM(L27+L28) -> 19 | M29: =SUM(M27+M28) -> 35 | N29: =IF($B$2="Thận trọng",E29,IF($B$2="Cơ sở",H29,K29)) -> 7 | O29: =IF($B$2="Thận trọng",F29,IF($B$2="Cơ sở",I29,L29)) -> 13 | P29: =IF($B$2="Thận trọng",G29,IF($B$2="Cơ sở",J29,M29)) -> 25 | Q29: Tổng cơ sở ký mới | R29: Đã xác nhận
A30: Tổ chức | B30: avg_active_new_factor | C30: Tỷ lệ hoạt động bình quân của cơ sở ký mới | D30: % | E30: 0.5 | F30: 0.5 | G30: 0.5 | H30: 0.5 | I30: 0.5 | J30: 0.5 | K30: 0.5 | L30: 0.5 | M30: 0.5 | N30: =IF($B$2="Thận trọng",E30,IF($B$2="Cơ sở",H30,K30)) -> 0.5 | O30: =IF($B$2="Thận trọng",F30,IF($B$2="Cơ sở",I30,L30)) -> 0.5 | P30: =IF($B$2="Thận trọng",G30,IF($B$2="Cơ sở",J30,M30)) -> 0.5 | Q30: Giả định ký hợp đồng đều trong năm | R30: Đã xác nhận
A31: Tổ chức | B31: patients_hospital | C31: Bệnh nhân trung bình / bệnh viện | D31: người | E31: 3000 | F31: 4000 | G31: 5000 | H31: 4000 | I31: 5000 | J31: 6000 | K31: 5000 | L31: 6500 | M31: 8000 | N31: =IF($B$2="Thận trọng",E31,IF($B$2="Cơ sở",H31,K31)) -> 4000 | O31: =IF($B$2="Thận trọng",F31,IF($B$2="Cơ sở",I31,L31)) -> 5000 | P31: =IF($B$2="Thận trọng",G31,IF($B$2="Cơ sở",J31,M31)) -> 6000 | Q31: DIAPLUS.docx: 5.000–10.000 bệnh nhân/bệnh viện | R31: Tham chiếu DIA+
A32: Tổ chức | B32: patients_clinic | C32: Bệnh nhân trung bình / phòng khám | D32: người | E32: 300 | F32: 400 | G32: 500 | H32: 400 | I32: 600 | J32: 800 | K32: 500 | L32: 800 | M32: 1000 | N32: =IF($B$2="Thận trọng",E32,IF($B$2="Cơ sở",H32,K32)) -> 400 | O32: =IF($B$2="Thận trọng",F32,IF($B$2="Cơ sở",I32,L32)) -> 600 | P32: =IF($B$2="Thận trọng",G32,IF($B$2="Cơ sở",J32,M32)) -> 800 | Q32: Giả định ban đầu | R32: Đã xác nhận
A33: Tổ chức | B33: b2b_renewal | C33: Tỷ lệ gia hạn hợp đồng B2B | D33: % | E33: 0.8 | F33: 0.85 | G33: 0.88 | H33: 0.85 | I33: 0.88 | J33: 0.9 | K33: 0.88 | L33: 0.92 | M33: 0.94 | N33: =IF($B$2="Thận trọng",E33,IF($B$2="Cơ sở",H33,K33)) -> 0.85 | O33: =IF($B$2="Thận trọng",F33,IF($B$2="Cơ sở",I33,L33)) -> 0.88 | P33: =IF($B$2="Thận trọng",G33,IF($B$2="Cơ sở",J33,M33)) -> 0.9 | Q33: Giả định ban đầu | R33: Đã xác nhận
A34: C. GIÁ BÁN | C34: (r = 10%/năm, rf tháng = 10,47%)
A35: Giá bán | B35: premium_month | C35: Giá DIA+ Pro/ tháng | D35: VNĐ/tháng | E35: 29000 | F35: =E35*(1+10.47%) -> 32036.3 | G35: =E35*(1+10.47%) -> 32036.3 | H35: 39000 | I35: =H35*(1+10.47%) -> 43083.3 | J35: =H35*(1+10.47%)^2 -> 47594.122 | K35: 49000 | L35: =K35*(1+10.47%) -> 54130.3 | M35: =K35*(1+10.47%)^2 -> 59797.742 | N35: =IF($B$2="Thận trọng",E35,IF($B$2="Cơ sở",H35,K35)) -> 39000 | O35: =IF($B$2="Thận trọng",F35,IF($B$2="Cơ sở",I35,L35)) -> 43083.3 | P35: =IF($B$2="Thận trọng",G35,IF($B$2="Cơ sở",J35,M35)) -> 47594.122 | Q35: Giá khởi điểm phục vụ kiểm chứng willingness-to-pay. | R35: Đã kiểm chứng và báo giá
A36: Giá bán | B36: premium_year | C36: Giá DIA+ Pro / năm | D36: VNĐ/năm | E36: 299000 | F36: =E36*(1+10%) -> 328900 | G36: =E36*(1+10%)^2 -> 361790 | H36: 399000 | I36: =H36*(1+10%) -> 438900 | J36: =H36*(1+10%)^2 -> 482790 | K36: 499000 | L36: =K36*(1+10%) -> 548900 | M36: =K36*(1+10%)^2 -> 603790 | N36: =IF($B$2="Thận trọng",E36,IF($B$2="Cơ sở",H36,K36)) -> 399000 | O36: =IF($B$2="Thận trọng",F36,IF($B$2="Cơ sở",I36,L36)) -> 438900 | P36: =IF($B$2="Thận trọng",G36,IF($B$2="Cơ sở",J36,M36)) -> 482790 | Q36: Giả định giá khởi tạo – cần xác nhận | R36: Đã xác nhận
A37: Giá bán | B37: clinic_month | C37: Giá DIA+ Clinic / tháng | D37: VNĐ/tháng | E37: 799000 | F37: =E37*(1+10.47%)^12 -> 2639240.9 | G37: =E37*(1+10.47%)^24 -> 8717887.8 | H37: 899000 | I37: =H37*(1+10.47%) -> 993125.3 | J37: =H37*(1+10.47%)^2 -> 1097105.5 | K37: 999000 | L37: =K37*(1+10.47%) -> 1103595.3 | M37: =K37*(1+10.47%)^2 -> 1219141.7 | N37: =IF($B$2="Thận trọng",E37,IF($B$2="Cơ sở",H37,K37)) -> 899000 | O37: =IF($B$2="Thận trọng",F37,IF($B$2="Cơ sở",I37,L37)) -> 993125.3 | P37: =IF($B$2="Thận trọng",G37,IF($B$2="Cơ sở",J37,M37)) -> 1097105.5 | Q37: Giả định giá khởi tạo – cần xác nhận | R37: Đã xác nhận
A38: Giá bán | B38: clinic_month | C38: Giá DIA+ Clinic/năm | D38: VNĐ/tháng | E38: 7900000 | F38: =E38*(1+10%) -> 8690000 | G38: =E38*(1+10%)^2 -> 9559000 | H38: 8900000 | I38: =H38*(1+10%) -> 9790000 | J38: =H38*(1+10%)^2 -> 10769000 | K38: 9900000 | L38: =K38*(1+10%) -> 10890000 | M38: =K38*(1+10%)^2 -> 11979000 | N38: =IF($B$2="Thận trọng",E38,IF($B$2="Cơ sở",H38,K38)) -> 8900000 | O38: =IF($B$2="Thận trọng",F38,IF($B$2="Cơ sở",I38,L38)) -> 9790000 | P38: =IF($B$2="Thận trọng",G38,IF($B$2="Cơ sở",J38,M38)) -> 10769000 | Q38: Giả định giá khởi tạo – cần xác nhận | R38: Đã xác nhận
A39: Giá bán | B39: deploy_hospital_fee | C39: Phí triển khai / bệnh viện (Doanh thu) | D39: VNĐ/cơ sở | E39: 27000000 | F39: 27000000 | G39: 27000000 | H39: 30000000 | I39: 30000000 | J39: 30000000 | K39: 33000000 | L39: 33000000 | M39: 33000000 | N39: =IF($B$2="Thận trọng",E39,IF($B$2="Cơ sở",H39,K39)) -> 30000000 | O39: =IF($B$2="Thận trọng",F39,IF($B$2="Cơ sở",I39,L39)) -> 30000000 | P39: =IF($B$2="Thận trọng",G39,IF($B$2="Cơ sở",J39,M39)) -> 30000000 | Q39: Giả định giá khởi tạo – cần xác nhận | R39: Đã xác nhận
A40: Giá bán | B40: deploy_clinic_fee | C40: Phí triển khai / phòng khám (Doanh thu) | D40: VNĐ/cơ sở | E40: 9000000 | F40: 9000000 | G40: 9000000 | H40: 10000000 | I40: 10000000 | J40: 10000000 | K40: 11000000 | L40: 11000000 | M40: 11000000 | N40: =IF($B$2="Thận trọng",E40,IF($B$2="Cơ sở",H40,K40)) -> 10000000 | O40: =IF($B$2="Thận trọng",F40,IF($B$2="Cơ sở",I40,L40)) -> 10000000 | P40: =IF($B$2="Thận trọng",G40,IF($B$2="Cơ sở",J40,M40)) -> 10000000 | Q40: Giả định giá khởi tạo – cần xác nhận | R40: Đã xác nhận
A41: Giá bán | B41: training_fee | C41: Phí đào tạo / cơ sở | D41: VNĐ/cơ sở | E41: 1800000 | F41: 1800000 | G41: 1800000 | H41: 2000000 | I41: 2000000 | J41: 2000000 | K41: 2200000 | L41: 2200000 | M41: 2200000 | N41: =IF($B$2="Thận trọng",E41,IF($B$2="Cơ sở",H41,K41)) -> 2000000 | O41: =IF($B$2="Thận trọng",F41,IF($B$2="Cơ sở",I41,L41)) -> 2000000 | P41: =IF($B$2="Thận trọng",G41,IF($B$2="Cơ sở",J41,M41)) -> 2000000 | Q41: Giả định giá khởi tạo – cần xác nhận | R41: Đã xác nhận
A42: Giá bán | B42: api_fee | C42: 60000000 | D42: VNĐ/cơ sở | E42: 13500000 | F42: 13500000 | G42: 13500000 | H42: 15000000 | I42: 15000000 | J42: 15000000 | K42: 18000000 | L42: 18000000 | M42: 18000000 | N42: =IF($B$2="Thận trọng",E42,IF($B$2="Cơ sở",H42,K42)) -> 15000000 | O42: =IF($B$2="Thận trọng",F42,IF($B$2="Cơ sở",I42,L42)) -> 15000000 | P42: =IF($B$2="Thận trọng",G42,IF($B$2="Cơ sở",J42,M42)) -> 15000000 | Q42: Giả định giá khởi tạo – cần xác nhận | R42: Đã xác nhận
A43: Giá bán | B43: api_adoption | C43: Tỷ lệ cơ sở ký mới mua tích hợp API | D43: % | E43: 0.15 | F43: 0.2 | G43: 0.25 | H43: 0.2 | I43: 0.25 | J43: 0.3 | K43: 0.25 | L43: 0.35 | M43: 0.45 | N43: =IF($B$2="Thận trọng",E43,IF($B$2="Cơ sở",H43,K43)) -> 0.2 | O43: =IF($B$2="Thận trọng",F43,IF($B$2="Cơ sở",I43,L43)) -> 0.25 | P43: =IF($B$2="Thận trọng",G43,IF($B$2="Cơ sở",J43,M43)) -> 0.3 | Q43: Giả định ban đầu | R43: Đã xác nhận
A44: D. CHI PHÍ BIẾN ĐỔI
A45: Biến phí | B45: ai_cost_scan | C45: Chi phí AI/OCR / lượt | D45: VNĐ/lượt | E45: 200 | F45: 180 | G45: 160 | H45: 180 | I45: 160 | J45: 140 | K45: 160 | L45: 140 | M45: 120 | N45: =IF($B$2="Thận trọng",E45,IF($B$2="Cơ sở",H45,K45)) -> 180 | O45: =IF($B$2="Thận trọng",F45,IF($B$2="Cơ sở",I45,L45)) -> 160 | P45: =IF($B$2="Thận trọng",G45,IF($B$2="Cơ sở",J45,M45)) -> 140 | Q45: Giả định | R45: Đã xác nhận
A46: Biến phí | B46: cloud_cost_mau | C46: Chi phí cloud / MAU / tháng | D46: VNĐ/người/tháng | E46: 1000 | F46: 1100 | G46: 1200 | H46: 900 | I46: 1000 | J46: 1100 | K46: 800 | L46: 900 | M46: 1000 | N46: =IF($B$2="Thận trọng",E46,IF($B$2="Cơ sở",H46,K46)) -> 900 | O46: =IF($B$2="Thận trọng",F46,IF($B$2="Cơ sở",I46,L46)) -> 1000 | P46: =IF($B$2="Thận trọng",G46,IF($B$2="Cơ sở",J46,M46)) -> 1100 | Q46: Giả định hạ tầng cloud theo mô hình tối ưu chi phí startup. | R46: Đã xác nhận
A47: Biến phí | B47: storage_cost_mau | C47: Chi phí lưu trữ / MAU / tháng | D47: VNĐ/người/tháng | E47: 280 | F47: 330 | G47: 380 | H47: 250 | I47: 300 | J47: 350 | K47: 220 | L47: 270 | M47: 320 | N47: =IF($B$2="Thận trọng",E47,IF($B$2="Cơ sở",H47,K47)) -> 250 | O47: =IF($B$2="Thận trọng",F47,IF($B$2="Cơ sở",I47,L47)) -> 300 | P47: =IF($B$2="Thận trọng",G47,IF($B$2="Cơ sở",J47,M47)) -> 350 | Q47: Giả định | R47: Đã xác nhận
A48: Biến phí | B48: notify_cost_mau | C48: Chi phí SMS/email/push / MAU / tháng | D48: VNĐ/người/tháng | E48: 140 | F48: 170 | G48: 200 | H48: 120 | I48: 150 | J48: 180 | K48: 100 | L48: 130 | M48: 160 | N48: =IF($B$2="Thận trọng",E48,IF($B$2="Cơ sở",H48,K48)) -> 120 | O48: =IF($B$2="Thận trọng",F48,IF($B$2="Cơ sở",I48,L48)) -> 150 | P48: =IF($B$2="Thận trọng",G48,IF($B$2="Cơ sở",J48,M48)) -> 180 | Q48: Giả định | R48: Đã xác nhận
A49: Biến phí | B49: payment_fee | C49: Phí cổng thanh toán | D49: % doanh thu B2C | E49: 0.03 | F49: 0.03 | G49: 0.03 | H49: 0.025 | I49: 0.025 | J49: 0.025 | K49: 0.022 | L49: 0.022 | M49: 0.022 | N49: =IF($B$2="Thận trọng",E49,IF($B$2="Cơ sở",H49,K49)) -> 0.025 | O49: =IF($B$2="Thận trọng",F49,IF($B$2="Cơ sở",I49,L49)) -> 0.025 | P49: =IF($B$2="Thận trọng",G49,IF($B$2="Cơ sở",J49,M49)) -> 0.025 | Q49: Giả định | R49: Đã xác nhận
A50: Biến phí | B50: support_cost_premium | C50: Hỗ trợ / Pro / tháng | D50: VNĐ/người/tháng | E50: 8000 | F50: 8500 | G50: 9000 | H50: 7000 | I50: 7500 | J50: 8000 | K50: 6500 | L50: 7000 | M50: 7500 | N50: =IF($B$2="Thận trọng",E50,IF($B$2="Cơ sở",H50,K50)) -> 7000 | O50: =IF($B$2="Thận trọng",F50,IF($B$2="Cơ sở",I50,L50)) -> 7500 | P50: =IF($B$2="Thận trọng",G50,IF($B$2="Cơ sở",J50,M50)) -> 8000 | Q50: Giả định | R50: Đã xác nhận
A51: Biến phí | B51: deploy_cost_hospital | C51: Chi phí triển khai / bệnh viện | D51: VNĐ/cơ sở | E51: 13000000 | F51: 13000000 | G51: 13000000 | H51: 12000000 | I51: 12000000 | J51: 12000000 | K51: 11000000 | L51: 11000000 | M51: 11000000 | N51: =IF($B$2="Thận trọng",E51,IF($B$2="Cơ sở",H51,K51)) -> 12000000 | O51: =IF($B$2="Thận trọng",F51,IF($B$2="Cơ sở",I51,L51)) -> 12000000 | P51: =IF($B$2="Thận trọng",G51,IF($B$2="Cơ sở",J51,M51)) -> 12000000 | Q51: Giả định | R51: Đã xác nhận
A52: Biến phí | B52: deploy_cost_clinic | C52: Chi phí triển khai / phòng khám | D52: VNĐ/cơ sở | E52: 4500000 | F52: 4500000 | G52: 4500000 | H52: 4000000 | I52: 4000000 | J52: 4000000 | K52: 3500000 | L52: 3500000 | M52: 3500000 | N52: =IF($B$2="Thận trọng",E52,IF($B$2="Cơ sở",H52,K52)) -> 4000000 | O52: =IF($B$2="Thận trọng",F52,IF($B$2="Cơ sở",I52,L52)) -> 4000000 | P52: =IF($B$2="Thận trọng",G52,IF($B$2="Cơ sở",J52,M52)) -> 4000000 | Q52: Giả định | R52: Đã xác nhận
A53: Biến phí | B53: sales_commission | C53: Hoa hồng bán hàng B2B | D53: % doanh thu B2B | E53: 0.06 | F53: 0.06 | G53: 0.06 | H53: 0.05 | I53: 0.05 | J53: 0.05 | K53: 0.045 | L53: 0.045 | M53: 0.045 | N53: =IF($B$2="Thận trọng",E53,IF($B$2="Cơ sở",H53,K53)) -> 0.05 | O53: =IF($B$2="Thận trọng",F53,IF($B$2="Cơ sở",I53,L53)) -> 0.05 | P53: =IF($B$2="Thận trọng",G53,IF($B$2="Cơ sở",J53,M53)) -> 0.05 | Q53: Giả định | R53: Đã xác nhận
A54: Biến phí | B54: care_cost_facility | C54: CSKH / cơ sở / tháng | D54: VNĐ/cơ sở/tháng | E54: 250000 | F54: 300000 | G54: 350000 | H54: 220000 | I54: 260000 | J54: 300000 | K54: 200000 | L54: 240000 | M54: 280000 | N54: =IF($B$2="Thận trọng",E54,IF($B$2="Cơ sở",H54,K54)) -> 220000 | O54: =IF($B$2="Thận trọng",F54,IF($B$2="Cơ sở",I54,L54)) -> 260000 | P54: =IF($B$2="Thận trọng",G54,IF($B$2="Cơ sở",J54,M54)) -> 300000 | Q54: Giả định | R54: Đã xác nhận
A55: Biến phí | B55: partner_cost_rate | C55: Chi phí đối tác | D55: % tổng doanh thu | E55: 0.018 | F55: 0.018 | G55: 0.018 | H55: 0.015 | I55: 0.015 | J55: 0.015 | K55: 0.012 | L55: 0.012 | M55: 0.012 | N55: =IF($B$2="Thận trọng",E55,IF($B$2="Cơ sở",H55,K55)) -> 0.015 | O55: =IF($B$2="Thận trọng",F55,IF($B$2="Cơ sở",I55,L55)) -> 0.015 | P55: =IF($B$2="Thận trọng",G55,IF($B$2="Cơ sở",J55,M55)) -> 0.015 | Q55: Giả định | R55: Đã xác nhận
A56: Biến phí | B56: doctor_sessions | C56: Số phiên tư vấn bác sĩ / Pro / năm | D56: phiên | E56: 0.05 | F56: 0.08 | G56: 0.1 | H56: 0.05 | I56: 0.08 | J56: 0.1 | K56: 0.06 | L56: 0.1 | M56: 0.12 | N56: =IF($B$2="Thận trọng",E56,IF($B$2="Cơ sở",H56,K56)) -> 0.05 | O56: =IF($B$2="Thận trọng",F56,IF($B$2="Cơ sở",I56,L56)) -> 0.08 | P56: =IF($B$2="Thận trọng",G56,IF($B$2="Cơ sở",J56,M56)) -> 0.1 | Q56: Giả định | R56: Đã xác nhận
A57: Biến phí | B57: doctor_cost_session | C57: Chi phí bác sĩ / phiên | D57: VNĐ/phiên | E57: 300000 | F57: 300000 | G57: 300000 | H57: 200000 | I57: 200000 | J57: 200000 | K57: 100000 | L57: 100000 | M57: 100000 | N57: =IF($B$2="Thận trọng",E57,IF($B$2="Cơ sở",H57,K57)) -> 200000 | O57: =IF($B$2="Thận trọng",F57,IF($B$2="Cơ sở",I57,L57)) -> 200000 | P57: =IF($B$2="Thận trọng",G57,IF($B$2="Cơ sở",J57,M57)) -> 200000 | Q57: Giả định | R57: Đã xác nhận
A58: E. THÔNG SỐ TÀI CHÍNH
A59: Tài chính | B59: tax_rate | C59: Thuế TNDN | D59: % | E59: 0.2 | F59: 0.2 | G59: 0.2 | H59: 0.2 | I59: 0.2 | J59: 0.2 | K59: 0.2 | L59: 0.2 | M59: 0.2 | N59: =IF($B$2="Thận trọng",E59,IF($B$2="Cơ sở",H59,K59)) -> 0.2 | O59: =IF($B$2="Thận trọng",F59,IF($B$2="Cơ sở",I59,L59)) -> 0.2 | P59: =IF($B$2="Thận trọng",G59,IF($B$2="Cơ sở",J59,M59)) -> 0.2 | Q59: Giả định | R59: Đã xác nhận
A60: Tài chính | B60: discount_rate | C60: Tỷ lệ chiết khấu | D60: % | E60: 0.2 | F60: 0.2 | G60: 0.2 | H60: 0.18 | I60: 0.18 | J60: 0.18 | K60: 0.15 | L60: 0.15 | M60: 0.15 | N60: =IF($B$2="Thận trọng",E60,IF($B$2="Cơ sở",H60,K60)) -> 0.18 | O60: =IF($B$2="Thận trọng",F60,IF($B$2="Cơ sở",I60,L60)) -> 0.18 | P60: =IF($B$2="Thận trọng",G60,IF($B$2="Cơ sở",J60,M60)) -> 0.18 | Q60: Giả định | R60: Đã xác nhận
A61: Tài chính | B61: debt_ratio | C61: Tỷ lệ vốn vay | D61: % | E61: 0 | F61: 0 | G61: 0 | H61: 0 | I61: 0 | J61: 0 | K61: 0 | L61: 0 | M61: 0 | N61: =IF($B$2="Thận trọng",E61,IF($B$2="Cơ sở",H61,K61)) -> 0 | O61: =IF($B$2="Thận trọng",F61,IF($B$2="Cơ sở",I61,L61)) -> 0 | P61: =IF($B$2="Thận trọng",G61,IF($B$2="Cơ sở",J61,M61)) -> 0 | Q61: Giả định | R61: Đã xác nhận
A62: Tài chính | B62: interest_rate | C62: Lãi suất vay | D62: %/năm | E62: 0.1 | F62: 0.1 | G62: 0.1 | H62: 0.1 | I62: 0.1 | J62: 0.1 | K62: 0.09 | L62: 0.09 | M62: 0.09 | N62: =IF($B$2="Thận trọng",E62,IF($B$2="Cơ sở",H62,K62)) -> 0.1 | O62: =IF($B$2="Thận trọng",F62,IF($B$2="Cơ sở",I62,L62)) -> 0.1 | P62: =IF($B$2="Thận trọng",G62,IF($B$2="Cơ sở",J62,M62)) -> 0.1 | Q62: Giả định | R62: Đã xác nhận
A63: Tài chính | B63: equity_ratio | C63: Tỷ lệ vốn chủ sở hữu | D63: % | E63: 1 | F63: 1 | G63: 1 | H63: 1 | I63: 1 | J63: 1 | K63: 1 | L63: 1 | M63: 1 | N63: =IF($B$2="Thận trọng",E63,IF($B$2="Cơ sở",H63,K63)) -> 1 | O63: =IF($B$2="Thận trọng",F63,IF($B$2="Cơ sở",I63,L63)) -> 1 | P63: =IF($B$2="Thận trọng",G63,IF($B$2="Cơ sở",J63,M63)) -> 1 | Q63: Giả định | R63: Đã xác nhận
A64: Tài chính | B64: software_amort_years | C64: Phân bổ phần mềm bản quyền Microsoft 365 Family | D64: năm | E64: 1 | F64: 0 | G64: 0 | H64: 1 | I64: 0 | J64: 0 | K64: 1 | L64: 0 | M64: 0 | N64: =IF($B$2="Thận trọng",E64,IF($B$2="Cơ sở",H64,K64)) -> 1 | O64: =IF($B$2="Thận trọng",F64,IF($B$2="Cơ sở",I64,L64)) -> 0 | P64: =IF($B$2="Thận trọng",G64,IF($B$2="Cơ sở",J64,M64)) -> 0 | Q64: Giá tham khảo tại trang Microsoft chính hãng | R64: Đã xác nhận
A65: Tài chính | B65: equipment_dep_years | C65: Khấu hao thiết bị | D65: năm | E65: 3 | F65: 3 | G65: 3 | H65: 4 | I65: 4 | J65: 4 | K65: 5 | L65: 5 | M65: 5 | N65: =IF($B$2="Thận trọng",E65,IF($B$2="Cơ sở",H65,K65)) -> 4 | O65: =IF($B$2="Thận trọng",F65,IF($B$2="Cơ sở",I65,L65)) -> 4 | P65: =IF($B$2="Thận trọng",G65,IF($B$2="Cơ sở",J65,M65)) -> 4 | Q65: Giả định | R65: Đã xác nhận
A66: Tài chính | B66: project_life | C66: Vòng đời dự án | D66: năm | E66: 3 | F66: 3 | G66: 3 | H66: 3 | I66: 3 | J66: 3 | K66: 3 | L66: 3 | M66: 3 | N66: =IF($B$2="Thận trọng",E66,IF($B$2="Cơ sở",H66,K66)) -> 3 | O66: =IF($B$2="Thận trọng",F66,IF($B$2="Cơ sở",I66,L66)) -> 3 | P66: =IF($B$2="Thận trọng",G66,IF($B$2="Cơ sở",J66,M66)) -> 3 | Q66: Giả định | R66: Đã xác nhận
A67: Tài chính | B67: min_wc_months | C67: Vốn lưu động tối thiểu | D67: tháng định phí | E67: 2 | F67: 2 | G67: 2 | H67: 2 | I67: 2 | J67: 2 | K67: 2 | L67: 2 | M67: 2 | N67: =IF($B$2="Thận trọng",E67,IF($B$2="Cơ sở",H67,K67)) -> 2 | O67: =IF($B$2="Thận trọng",F67,IF($B$2="Cơ sở",I67,L67)) -> 2 | P67: =IF($B$2="Thận trọng",G67,IF($B$2="Cơ sở",J67,M67)) -> 2 | Q67: Giả định | R67: Đã xác nhận
A68: Tài chính | B68: salary_growth | C68: Tăng lương | D68: %/năm | E68: 0.08 | F68: 0.08 | G68: 0.08 | H68: 0.1 | I68: 0.1 | J68: 0.1 | K68: 0.12 | L68: 0.12 | M68: 0.12 | N68: =IF($B$2="Thận trọng",E68,IF($B$2="Cơ sở",H68,K68)) -> 0.1 | O68: =IF($B$2="Thận trọng",F68,IF($B$2="Cơ sở",I68,L68)) -> 0.1 | P68: =IF($B$2="Thận trọng",G68,IF($B$2="Cơ sở",J68,M68)) -> 0.1 | Q68: Giả định | R68: Đã xác nhận
A69: Tài chính | B69: cloud_growth | C69: Tăng chi phí cloud | D69: %/năm | E69: 0.1 | F69: 0.1 | G69: 0.1 | H69: 0.08 | I69: 0.08 | J69: 0.08 | K69: 0.06 | L69: 0.06 | M69: 0.06 | N69: =IF($B$2="Thận trọng",E69,IF($B$2="Cơ sở",H69,K69)) -> 0.08 | O69: =IF($B$2="Thận trọng",F69,IF($B$2="Cơ sở",I69,L69)) -> 0.08 | P69: =IF($B$2="Thận trọng",G69,IF($B$2="Cơ sở",J69,M69)) -> 0.08 | Q69: Giả định | R69: Đã xác nhận
A70: Tài chính | B70: marketing_growth | C70: Tăng chi phí marketing | D70: %/năm | E70: 0.1 | F70: 0.1 | G70: 0.1 | H70: 0.15 | I70: 0.15 | J70: 0.15 | K70: 0.2 | L70: 0.2 | M70: 0.2 | N70: =IF($B$2="Thận trọng",E70,IF($B$2="Cơ sở",H70,K70)) -> 0.15 | O70: =IF($B$2="Thận trọng",F70,IF($B$2="Cơ sở",I70,L70)) -> 0.15 | P70: =IF($B$2="Thận trọng",G70,IF($B$2="Cơ sở",J70,M70)) -> 0.15 | Q70: Giả định | R70: Đã xác nhận
... A73: Tài chính | B73: additional_capex | C73: Chi đầu tư bổ sung | D73: VNĐ/năm | E73: 0 | F73: 50000000 | G73: 80000000 | H73: 0 | I73: 100000000 | J73: 150000000 | K73: 0 | L73: 200000000 | M73: 300000000 | N73: =IF($B$2="Thận trọng",E73,IF($B$2="Cơ sở",H73,K73)) -> 0 | O73: =IF($B$2="Thận trọng",F73,IF($B$2="Cơ sở",I73,L73)) -> 100000000 | P73: =IF($B$2="Thận trọng",G73,IF($B$2="Cơ sở",J73,M73)) -> 150000000 | Q73: Giả định | R73: Đã xác nhận
A74: F. CHI PHÍ VẬN HÀNH CỐ ĐỊNH / THÁNG
A75: Định phí | B75: fix_tech | C75: Lương đội ngũ công nghệ | D75: VNĐ/tháng | E75: 20000000 | F75: 25000000 | G75: 30000000 | H75: 25000000 | I75: 30000000 | J75: 35000000 | K75: 30000000 | L75: 35000000 | M75: 40000000 | N75: =IF($B$2="Thận trọng",E75,IF($B$2="Cơ sở",H75,K75)) -> 25000000 | O75: =IF($B$2="Thận trọng",F75,IF($B$2="Cơ sở",I75,L75)) -> 30000000 | P75: =IF($B$2="Thận trọng",G75,IF($B$2="Cơ sở",J75,M75)) -> 35000000 | Q75: Đội ngũ tinh gọn; founder kiêm nhiệm, tuyển theo cột mốc doanh thu. | R75: Đã xác nhận
A76: Định phí | B76: fix_product | C76: Lương sản phẩm và UI/UX | D76: VNĐ/tháng | E76: 7000000 | F76: 8000000 | G76: 9000000 | H76: 8000000 | I76: 9000000 | J76: 10000000 | K76: 9000000 | L76: 10000000 | M76: 12000000 | N76: =IF($B$2="Thận trọng",E76,IF($B$2="Cơ sở",H76,K76)) -> 8000000 | O76: =IF($B$2="Thận trọng",F76,IF($B$2="Cơ sở",I76,L76)) -> 9000000 | P76: =IF($B$2="Thận trọng",G76,IF($B$2="Cơ sở",J76,M76)) -> 10000000 | Q76: Giả định | R76: Đã xác nhận
A77: Định phí | B77: fix_medical | C77: Lương chuyên môn y tế | D77: VNĐ/tháng | E77: 5000000 | F77: 7000000 | G77: 10000000 | H77: 6000000 | I77: 9000000 | J77: 12000000 | K77: 10000000 | L77: 12000000 | M77: 15000000 | N77: =IF($B$2="Thận trọng",E77,IF($B$2="Cơ sở",H77,K77)) -> 6000000 | O77: =IF($B$2="Thận trọng",F77,IF($B$2="Cơ sở",I77,L77)) -> 9000000 | P77: =IF($B$2="Thận trọng",G77,IF($B$2="Cơ sở",J77,M77)) -> 12000000 | Q77: Giả định | R77: Đã xác nhận
A78: Định phí | B78: fix_sales | C78: Nhân sự kinh doanh B2B | D78: VNĐ/tháng | E78: 7000000 | F78: 8500000 | G78: 10000000 | H78: 8000000 | I78: 9500000 | J78: 12000000 | K78: 10000000 | L78: 12500000 | M78: 15000000 | N78: =IF($B$2="Thận trọng",E78,IF($B$2="Cơ sở",H78,K78)) -> 8000000 | O78: =IF($B$2="Thận trọng",F78,IF($B$2="Cơ sở",I78,L78)) -> 9500000 | P78: =IF($B$2="Thận trọng",G78,IF($B$2="Cơ sở",J78,M78)) -> 12000000 | Q78: Giả định | R78: Đã xác nhận
A79: Định phí | B79: fix_marketing | C79: Marketing | D79: VNĐ/tháng | E79: 13000000 | F79: =15000000 -> 15000000 | G79: 20000000 | H79: 15000000 | I79: 20000000 | J79: 25000000 | K79: 20000000 | L79: =25000000 -> 25000000 | M79: 30000000 | N79: =IF($B$2="Thận trọng",E79,IF($B$2="Cơ sở",H79,K79)) -> 15000000 | O79: =IF($B$2="Thận trọng",F79,IF($B$2="Cơ sở",I79,L79)) -> 20000000 | P79: =IF($B$2="Thận trọng",G79,IF($B$2="Cơ sở",J79,M79)) -> 25000000 | Q79: Giả định | R79: Đã xác nhận
A80: Định phí | B80: fix_cs | C80: Chăm sóc khách hàng | D80: VNĐ/tháng | E80: 5000000 | F80: =7000000 -> 7000000 | G80: 10000000 | H80: 10000000 | I80: 12000000 | J80: 15000000 | K80: 12000000 | L80: =15000000 -> 15000000 | M80: 20000000 | N80: =IF($B$2="Thận trọng",E80,IF($B$2="Cơ sở",H80,K80)) -> 10000000 | O80: =IF($B$2="Thận trọng",F80,IF($B$2="Cơ sở",I80,L80)) -> 12000000 | P80: =IF($B$2="Thận trọng",G80,IF($B$2="Cơ sở",J80,M80)) -> 15000000 | Q80: Giả định | R80: Đã xác nhận
A81: Định phí | B81: fix_admin | C81: Kế toán và hành chính | D81: VNĐ/tháng | E81: 5000000 | F81: 7000000 | G81: 10000000 | H81: 7000000 | I81: 9000000 | J81: 12000000 | K81: 8000000 | L81: 10000000 | M81: 13000000 | N81: =IF($B$2="Thận trọng",E81,IF($B$2="Cơ sở",H81,K81)) -> 7000000 | O81: =IF($B$2="Thận trọng",F81,IF($B$2="Cơ sở",I81,L81)) -> 9000000 | P81: =IF($B$2="Thận trọng",G81,IF($B$2="Cơ sở",J81,M81)) -> 12000000 | Q81: Giả định | R81: Đã xác nhận
A82: Định phí | B82: fix_office | C82: Thuê mặt bằng văn phòng co - working | D82: VNĐ/tháng | E82: 0 | F82: 7000000 | G82: 10000000 | H82: 0 | I82: 10000000 | J82: 12000000 | K82: 0 | L82: 12000000 | M82: 15000000 | N82: =IF($B$2="Thận trọng",E82,IF($B$2="Cơ sở",H82,K82)) -> 0 | O82: =IF($B$2="Thận trọng",F82,IF($B$2="Cơ sở",I82,L82)) -> 10000000 | P82: =IF($B$2="Thận trọng",G82,IF($B$2="Cơ sở",J82,M82)) -> 12000000 | Q82: Giả định | R82: Đã kiểm chứng và báo giá
A83: Định phí | B83: fix_tools | C83: Phần mềm và công cụ làm việc | D83: VNĐ/tháng | E83: =(SUM('DIA_Danh Mục Đầu Tư'!$D$8,'DIA_Danh Mục Đầu Tư'!$D$14,'DIA_Danh Mục Đầu Tư'!D15,'DIA_Danh Mục Đầu Tư'!D25)-'DIA_Danh Mục Đầu Tư'!$D$33)/12 -> 22812500 | F83: =(SUM('DIA_Danh Mục Đầu Tư'!$D$8,'DIA_Danh Mục Đầu Tư'!$D$14,'DIA_Danh Mục Đầu Tư'!D15,'DIA_Danh Mục Đầu Tư'!D25)-'DIA_Danh Mục Đầu Tư'!$D$33)/12 -> 22812500 | G83: =(SUM('DIA_Danh Mục Đầu Tư'!$D$8,'DIA_Danh Mục Đầu Tư'!$D$14,'DIA_Danh Mục Đầu Tư'!D15,'DIA_Danh Mục Đầu Tư'!D25)-'DIA_Danh Mục Đầu Tư'!$D$33)/12 -> 22812500 | H83: =(SUM('DIA_Danh Mục Đầu Tư'!$D$8,'DIA_Danh Mục Đầu Tư'!$D$14,'DIA_Danh Mục Đầu Tư'!D15,'DIA_Danh Mục Đầu Tư'!D25)-'DIA_Danh Mục Đầu Tư'!$D$33)/12 -> 22812500 | I83: =(SUM('DIA_Danh Mục Đầu Tư'!$D$8,'DIA_Danh Mục Đầu Tư'!$D$14,'DIA_Danh Mục Đầu Tư'!D15,'DIA_Danh Mục Đầu Tư'!D25)-'DIA_Danh Mục Đầu Tư'!$D$33)/12 -> 22812500 | J83: =(SUM('DIA_Danh Mục Đầu Tư'!$D$8,'DIA_Danh Mục Đầu Tư'!$D$14,'DIA_Danh Mục Đầu Tư'!D15,'DIA_Danh Mục Đầu Tư'!D25)-'DIA_Danh Mục Đầu Tư'!$D$33)/12 -> 22812500 | K83: =(SUM('DIA_Danh Mục Đầu Tư'!$D$8,'DIA_Danh Mục Đầu Tư'!$D$14,'DIA_Danh Mục Đầu Tư'!D15,'DIA_Danh Mục Đầu Tư'!D25)-'DIA_Danh Mục Đầu Tư'!$D$33)/12 -> 22812500 | L83: =(SUM('DIA_Danh Mục Đầu Tư'!$D$8,'DIA_Danh Mục Đầu Tư'!$D$14,'DIA_Danh Mục Đầu Tư'!D15,'DIA_Danh Mục Đầu Tư'!D25)-'DIA_Danh Mục Đầu Tư'!$D$33)/12 -> 22812500 | M83: =(SUM('DIA_Danh Mục Đầu Tư'!$D$8,'DIA_Danh Mục Đầu Tư'!$D$14,'DIA_Danh Mục Đầu Tư'!D15,'DIA_Danh Mục Đầu Tư'!D25)-'DIA_Danh Mục Đầu Tư'!$D$33)/12 -> 22812500 | N83: =IF($B$2="Thận trọng",E83,IF($B$2="Cơ sở",H83,K83)) -> 22812500 | O83: =IF($B$2="Thận trọng",F83,IF($B$2="Cơ sở",I83,L83)) -> 22812500 | P83: =IF($B$2="Thận trọng",G83,IF($B$2="Cơ sở",J83,M83)) -> 22812500 | Q83: Giả định | R83: Đã xác nhận
A84: Định phí | B84: fix_security | C84: Kiểm tra bảo mật định kỳ | D84: VNĐ/tháng | E84: 1500000 | F84: 3500000 | G84: 6000000 | H84: 2000000 | I84: 4000000 | J84: 7000000 | K84: 2500000 | L84: 5000000 | M84: 8500000 | N84: =IF($B$2="Thận trọng",E84,IF($B$2="Cơ sở",H84,K84)) -> 2000000 | O84: =IF($B$2="Thận trọng",F84,IF($B$2="Cơ sở",I84,L84)) -> 4000000 | P84: =IF($B$2="Thận trọng",G84,IF($B$2="Cơ sở",J84,M84)) -> 7000000 | Q84: Giả định | R84: Đã xác nhận
A85: Định phí | B85: fix_legal | C85: Pháp lý và tuân thủ dữ liệu | D85: VNĐ/tháng | E85: 50000000 | F85: 70000000 | G85: 90000000 | H85: 70000000 | I85: 90000000 | J85: 100000000 | K85: 120000000 | L85: 168000000 | M85: 216000000 | N85: =IF($B$2="Thận trọng",E85,IF($B$2="Cơ sở",H85,K85)) -> 70000000 | O85: =IF($B$2="Thận trọng",F85,IF($B$2="Cơ sở",I85,L85)) -> 90000000 | P85: =IF($B$2="Thận trọng",G85,IF($B$2="Cơ sở",J85,M85)) -> 100000000 | Q85: Giả định | R85: Đã xác nhận
A86: Định phí | B86: fix_rd | C86: Nghiên cứu và phát triển | D86: VNĐ/tháng | E86: 3500000 | F86: 8500000 | G86: 15500000 | H86: 4000000 | I86: 10000000 | J86: 18000000 | K86: 5000000 | L86: 12000000 | M86: 21500000 | N86: =IF($B$2="Thận trọng",E86,IF($B$2="Cơ sở",H86,K86)) -> 4000000 | O86: =IF($B$2="Thận trọng",F86,IF($B$2="Cơ sở",I86,L86)) -> 10000000 | P86: =IF($B$2="Thận trọng",G86,IF($B$2="Cơ sở",J86,M86)) -> 18000000 | Q86: Giả định | R86: Đã xác nhận
A87: Định phí | B87: fix_travel | C87: Đi lại, demo, làm việc bệnh viện | D87: VNĐ/tháng | E87: 2500000 | F87: 5000000 | G87: 10000000 | H87: 3000000 | I87: 6000000 | J87: 12000000 | K87: 3500000 | L87: 7000000 | M87: 14500000 | N87: =IF($B$2="Thận trọng",E87,IF($B$2="Cơ sở",H87,K87)) -> 3000000 | O87: =IF($B$2="Thận trọng",F87,IF($B$2="Cơ sở",I87,L87)) -> 6000000 | P87: =IF($B$2="Thận trọng",G87,IF($B$2="Cơ sở",J87,M87)) -> 12000000 | Q87: Giả định | R87: Đã xác nhận
A88: Định phí | B88: fix_contingency | C88: Dự phòng vận hành | D88: VNĐ/tháng | E88: 5000000 | F88: 6000000 | G88: 7000000 | H88: 6000000 | I88: 7000000 | J88: 8000000 | K88: 7000000 | L88: 8000000 | M88: 9000000 | N88: =IF($B$2="Thận trọng",E88,IF($B$2="Cơ sở",H88,K88)) -> 6000000 | O88: =IF($B$2="Thận trọng",F88,IF($B$2="Cơ sở",I88,L88)) -> 7000000 | P88: =IF($B$2="Thận trọng",G88,IF($B$2="Cơ sở",J88,M88)) -> 8000000 | Q88: Giả định | R88: Đã xác nhận
A89: G. CHI PHÍ ĐẦU TƯ BAN ĐẦU
A90: Đầu tư | B90: init_research_qty | C90: Nghiên cứu thị trường – Số lượng | D90: đơn vị | E90: 1 | F90: 0 | G90: 0 | H90: 1 | I90: 0 | J90: 0 | K90: 1 | L90: 0 | M90: 0 | N90: =IF($B$2="Thận trọng",E90,IF($B$2="Cơ sở",H90,K90)) -> 1 | O90: =IF($B$2="Thận trọng",F90,IF($B$2="Cơ sở",I90,L90)) -> 0 | P90: =IF($B$2="Thận trọng",G90,IF($B$2="Cơ sở",J90,M90)) -> 0 | Q90: Giả định ban đầu | R90: Đã xác nhận
A91: Đầu tư | B91: init_research_price | C91: Nghiên cứu thị trường – Đơn giá | D91: VNĐ/đơn vị | E91: 135000000 | F91: 0 | G91: 0 | H91: 270000000 | I91: 0 | J91: 0 | K91: 405000000 | L91: 0 | M91: 0 | N91: =IF($B$2="Thận trọng",E91,IF($B$2="Cơ sở",H91,K91)) -> 270000000 | O91: =IF($B$2="Thận trọng",F91,IF($B$2="Cơ sở",I91,L91)) -> 0 | P91: =IF($B$2="Thận trọng",G91,IF($B$2="Cơ sở",J91,M91)) -> 0 | Q91: Giá nghiên cứu thị trường dao động từ $5000 - $15000 | R91: Đã xác nhận
A92: Đầu tư | B92: init_security_storage_qty | C92: Bảo mật và lưu trữ thông tin - Số lượng | D92: đơn vị | E92: 1 | F92: 0 | G92: 0 | H92: 1 | I92: 0 | J92: 0 | K92: 1 | L92: 0 | M92: 0 | N92: 1 | O92: =IF($B$2="Thận trọng",F92,IF($B$2="Cơ sở",I92,L92)) -> 0 | P92: =IF($B$2="Thận trọng",G92,IF($B$2="Cơ sở",J92,M92)) -> 0 | R92: Đã xác nhận
A93: Đầu tư | B93: init_security_storage_price | C93: Bảo mật và lưu trữ thông tin - Đơn giá | D93: VNĐ/đơn vị | E93: 96000000 | F93: 0 | G93: 0 | H93: 96000000 | I93: 0 | J93: 0 | K93: 96000000 | L93: 0 | M93: 0 | N93: =IF($B$2="Thận trọng",E93,IF($B$2="Cơ sở",H93,K93)) -> 96000000 | O93: =IF($B$2="Thận trọng",F93,IF($B$2="Cơ sở",I93,L93)) -> 0 | P93: =IF($B$2="Thận trọng",G93,IF($B$2="Cơ sở",J93,M93)) -> 0 | R93: Đã xác nhận
A94: Đầu tư | B94: init_infrastructure_qty | C94: Hạ tầng công nghệ - Số lượng | D94: đơn vị | E94: 1 | F94: 0 | G94: 0 | H94: 1 | I94: 0 | J94: 0 | K94: 1 | L94: 0 | M94: 0 | N94: =IF($B$2="Thận trọng",E94,IF($B$2="Cơ sở",H94,K94)) -> 1 | O94: =IF($B$2="Thận trọng",F94,IF($B$2="Cơ sở",I94,L94)) -> 0 | P94: =IF($B$2="Thận trọng",G94,IF($B$2="Cơ sở",J94,M94)) -> 0 | Q94: Giả định | R94: Đã xác nhận
A95: Đầu tư | B95: init_infrastructure_price | C95: Hạ tầng công nghệ - Đơn giá | D95: VNĐ/đơn vị | E95: 150000000 | F95: 0 | G95: 0 | H95: 160000000 | I95: 0 | J95: 0 | K95: 170850000 | L95: 0 | M95: 0 | N95: =IF($B$2="Thận trọng",E95,IF($B$2="Cơ sở",H95,K95)) -> 160000000 | O95: =IF($B$2="Thận trọng",F95,IF($B$2="Cơ sở",I95,L95)) -> 0 | P95: =IF($B$2="Thận trọng",G95,IF($B$2="Cơ sở",J95,M95)) -> 0 | Q95: Giả định | R95: Đã xác nhận
A96: Đầu tư | B96: init_ai_qty | C96: Tích hợp AI – Số lượng | D96: đơn vị | E96: 2 | F96: 0 | G96: 0 | H96: 2 | I96: 0 | J96: 0 | K96: 2 | L96: 0 | M96: 0 | N96: =IF($B$2="Thận trọng",E96,IF($B$2="Cơ sở",H96,K96)) -> 2 | O96: =IF($B$2="Thận trọng",F96,IF($B$2="Cơ sở",I96,L96)) -> 0 | P96: =IF($B$2="Thận trọng",G96,IF($B$2="Cơ sở",J96,M96)) -> 0 | Q96: Giả định | R96: Đã xác nhận
A97: Đầu tư | B97: init_ai_price | C97: Tích hợp AI – Đơn giá | D97: VNĐ/đơn vị | E97: 7000000 | F97: 0 | G97: 0 | H97: 8000000 | I97: 0 | J97: 0 | K97: ='DIA_Danh Mục Đầu Tư'!$E$15 -> 11300000 | L97: 0 | M97: 0 | N97: =IF($B$2="Thận trọng",E97,IF($B$2="Cơ sở",H97,K97)) -> 8000000 | O97: =IF($B$2="Thận trọng",F97,IF($B$2="Cơ sở",I97,L97)) -> 0 | P97: =IF($B$2="Thận trọng",G97,IF($B$2="Cơ sở",J97,M97)) -> 0 | Q97: Giả định | R97: Đã kiểm chứng và báo giá
A98: Đầu tư | B98: init_testing_qty | C98: Kiểm thử phần mềm – Số lượng | D98: đơn vị | E98: 1 | F98: 0 | G98: 0 | H98: 1 | I98: 0 | J98: 0 | K98: 1 | L98: 0 | M98: 0 | N98: =IF($B$2="Thận trọng",E98,IF($B$2="Cơ sở",H98,K98)) -> 1 | O98: =IF($B$2="Thận trọng",F98,IF($B$2="Cơ sở",I98,L98)) -> 0 | P98: =IF($B$2="Thận trọng",G98,IF($B$2="Cơ sở",J98,M98)) -> 0 | Q98: Giả định | R98: Đã xác nhận
A99: Đầu tư | B99: init_testing_price | C99: Kiểm thử phần mềm – Đơn giá | D99: VNĐ/đơn vị | E99: 30000000 | F99: 0 | G99: 0 | H99: 40000000 | I99: 0 | J99: 0 | K99: 50000000 | L99: 0 | M99: 0 | N99: =IF($B$2="Thận trọng",E99,IF($B$2="Cơ sở",H99,K99)) -> 40000000 | O99: =IF($B$2="Thận trọng",F99,IF($B$2="Cơ sở",I99,L99)) -> 0 | P99: =IF($B$2="Thận trọng",G99,IF($B$2="Cơ sở",J99,M99)) -> 0 | Q99: Giả định | R99: Đã xác nhận
A100: Đầu tư | B100: init_security_qty | C100: Kiểm thử bảo mật – Số lượng | D100: đơn vị | E100: 1 | F100: 0 | G100: 0 | H100: 1 | I100: 0 | J100: 0 | K100: 1 | L100: 0 | M100: 0 | N100: =IF($B$2="Thận trọng",E100,IF($B$2="Cơ sở",H100,K100)) -> 1 | O100: =IF($B$2="Thận trọng",F100,IF($B$2="Cơ sở",I100,L100)) -> 0 | P100: =IF($B$2="Thận trọng",G100,IF($B$2="Cơ sở",J100,M100)) -> 0 | Q100: Giả định | R100: Đã xác nhận
A101: Đầu tư | B101: init_security_price | C101: Kiểm thử bảo mật – Đơn giá | D101: VNĐ/đơn vị | E101: 30000000 | F101: 0 | G101: 0 | H101: 40000000 | I101: 0 | J101: 0 | K101: 50000000 | L101: 0 | M101: 0 | N101: =IF($B$2="Thận trọng",E101,IF($B$2="Cơ sở",H101,K101)) -> 40000000 | O101: =IF($B$2="Thận trọng",F101,IF($B$2="Cơ sở",I101,L101)) -> 0 | P101: =IF($B$2="Thận trọng",G101,IF($B$2="Cơ sở",J101,M101)) -> 0 | Q101: Giả định | R101: Đã xác nhận
A102: Đầu tư | B102: init_trademark_qty | C102: Đăng ký thương hiệu – Số lượng | D102: đơn vị | E102: 1 | F102: 0 | G102: 0 | H102: 1 | I102: 0 | J102: 0 | K102: 1 | L102: 0 | M102: 0 | N102: =IF($B$2="Thận trọng",E102,IF($B$2="Cơ sở",H102,K102)) -> 1 | O102: =IF($B$2="Thận trọng",F102,IF($B$2="Cơ sở",I102,L102)) -> 0 | P102: =IF($B$2="Thận trọng",G102,IF($B$2="Cơ sở",J102,M102)) -> 0 | Q102: Giả định | R102: Đã xác nhận
...

Sheet DIA_Chi Phí
A1: DIA+ - KẾ HOẠCH CHI PHÍ
A4: A. CHI PHÍ ĐẦU TƯ BAN ĐẦU
A5: Khoản mục | B5: Số lượng | C5: Đơn giá | D5: Thành tiền | E5: Khấu hao / phân bổ? | F5: Thời gian phân bổ | G5: Ghi chú | H5: Nguồn / căn cứ | I5: Phân loại | K5: GHI CHÚ
A6: Nghiên cứu thị trường | B6: ='DIA_Giả Định'!$N$90 -> 1 | C6: ='DIA_Giả Định'!$N$91 -> 270000000 | D6: =B6*C6 -> 270000000 | E6: Không | F6: 0 | G6: Chi phí trước vận hành | H6: Giả định | I6: Chi phí trước vận hành | K6: 1. Năm 1 chưa thuê mặt bằng nên chưa định phí vào khoản này
A7: Hạ tầng công nghệ | B7: ='DIA_Giả Định'!$N$92 -> 1 | C7: ='DIA_Danh Mục Đầu Tư'!$D$25 -> 259850000 | D7: =B7*C7 -> 259850000 | E7: Có | F7: ='DIA_Giả Định'!$N$64 -> 1 | G7: Tài sản phần mềm | H7: Giả định | I7: Phần mềm
A8: Tích hợp AI | B8: ='DIA_Giả Định'!$N$96 -> 2 | C8: ='DIA_Giả Định'!$N$97 -> 8000000 | D8: =B8*C8 -> 16000000 | E8: Có | F8: ='DIA_Giả Định'!$N$64 -> 1 | G8: Tài sản phần mềm | H8: Giả định | I8: Phần mềm
A9: Bản quyền Microsoft 365 Family chính hãng (có AI Copilot) | B9: 1 | C9: ='DIA_Danh Mục Đầu Tư'!$D$14 -> 2600000 | D9: ='DIA_Danh Mục Đầu Tư'!$D$14 -> 2600000 | E9: Có | F9: ='DIA_Giả Định'!$N$64 -> 1 | G9: Tài sản phần mềm | H9: Giả định | I9: Phần mềm
A10: Bảo mật và lưu trữ thông tin | B10: 1 | C10: ='DIA_Danh Mục Đầu Tư'!$D$8 -> 96000000 | D10: ='DIA_Danh Mục Đầu Tư'!$E$8 -> 96000000 | F10: ='DIA_Giả Định'!$N$64 -> 1 | G10: Tài sản phần mềm | H10: Giả định | I10: Phần mềm
A11: Kiểm thử phần mềm | B11: ='DIA_Giả Định'!$N$98 -> 1 | C11: ='DIA_Giả Định'!$N$99 -> 40000000 | D11: =B11*C11 -> 40000000 | E11: Có | F11: ='DIA_Giả Định'!$N$64 -> 1 | G11: Đưa phần mềm vào trạng thái sẵn sàng | H11: Giả định | I11: Phần mềm
A12: Kiểm thử bảo mật | B12: ='DIA_Giả Định'!$N$100 -> 1 | C12: ='DIA_Giả Định'!$N$101 -> 40000000 | D12: =B12*C12 -> 40000000 | E12: Có | F12: ='DIA_Giả Định'!$N$64 -> 1 | G12: Đưa phần mềm vào trạng thái sẵn sàng | H12: Giả định | I12: Phần mềm
A13: Tư vấn pháp lý và đăng ký kinh doanh | B13: ='DIA_Giả Định'!$N$141 -> 6 | C13: ='DIA_Danh Mục Đầu Tư'!$D$18 -> 41000000 | D13: ='DIA_Danh Mục Đầu Tư'!$E$18 -> 41000000 | E13: Không | F13: 0 | G13: Chi phí trước vận hành | H13: Giả định | I13: Chi phí trước vận hành
A14: Thiết bị làm việc (laptop) | B14: ='DIA_Giả Định'!$N$114 -> 5 | C14: ='DIA_Giả Định'!$N$115 -> 24700000 | D14: =B14*C14 -> 123500000 | E14: Có | F14: ='DIA_Giả Định'!$N$65 -> 4 | G14: Thiết bị mạng, bảo mật, lưu trữ | H14: Giả định | I14: Tài sản hữu hình
A15: Điện thoại Iphone kiểm thử | B15: ='DIA_Giả Định'!$N$116 -> 1 | C15: ='DIA_Giả Định'!$N$117 -> 16300000 | D15: =B15*C15 -> 16300000 | E15: Có | F15: ='DIA_Giả Định'!$N$65 -> 4 | G15: Laptop, điện thoại, thiết bị demo | H15: Giả định | I15: Tài sản hữu hình
A16: Thí điểm tại bệnh viện | B16: ='DIA_Giả Định'!$N$118 -> 1 | C16: ='DIA_Giả Định'!$N$119 -> 80000000 | D16: =B16*C16 -> 80000000 | E16: Không | F16: 0 | G16: Chi phí thí điểm | H16: Giả định | I16: Chi phí trước vận hành
A17: Marketing ra mắt | B17: ='DIA_Giả Định'!$N$120 -> 1 | C17: ='DIA_Giả Định'!$N$121 -> 150000000 | D17: =B17*C17 -> 150000000 | E17: Không | F17: 0 | G17: Chi phí ra mắt | H17: Giả định | I17: Chi phí trước vận hành
A18: Đào tạo nhân sự | B18: ='DIA_Giả Định'!$N$122 -> 1 | C18: ='DIA_Giả Định'!$N$123 -> 20000000 | D18: =B18*C18 -> 20000000 | E18: Không | F18: 0 | G18: Chi phí trước vận hành | H18: Giả định | I18: Chi phí trước vận hành
A19: Vốn lưu động ban đầu | B19: ='DIA_Giả Định'!$N$124 -> 1 | C19: ='DIA_Giả Định'!$N$125 -> 300000000 | D19: =B19*C19 -> 300000000 | E19: Không | F19: 0 | G19: Dự trữ tiền mặt | H19: Giả định | I19: Vốn lưu động
A20: Dự phòng ban đầu - dự trù chi phí phát sinh | B20: ='DIA_Giả Định'!$N$126 -> 1 | C20: ='DIA_Giả Định'!$N$127 -> 300000000 | D20: =B20*C20 -> 300000000 | E20: Không | F20: 0 | G20: Dự phòng đầu tư | H20: Giả định | I20: Chi phí trước vận hành
A21: TỔNG ĐẦU TƯ BAN ĐẦU | D21: =SUM(D6:D20) -> 1755250000
A24: B. CHI PHÍ VẬN HÀNH CỐ ĐỊNH
A25: Khoản mục | B25: Tháng Năm 1 | C25: Năm 1 | D25: Tháng Năm 2 | E25: Năm 2 | F25: Tháng Năm 3 | G25: Năm 3 | H25: Nguồn / căn cứ | I25: Nhóm P&L
A26: Lương đội ngũ công nghệ | B26: ='DIA_Giả Định'!$N$75 -> 25000000 | C26: =B26*'DIA_Giả Định'!$N$5 -> 300000000 | D26: ='DIA_Giả Định'!$O$75 -> 30000000 | E26: =D26*'DIA_Giả Định'!$O$5 -> 360000000 | F26: ='DIA_Giả Định'!$P$75 -> 35000000 | G26: =F26*'DIA_Giả Định'!$P$5 -> 420000000 | H26: Giả định | I26: Nhân sự
A27: Lương sản phẩm và UI/UX | B27: ='DIA_Giả Định'!$N$76 -> 8000000 | C27: =B27*'DIA_Giả Định'!$N$5 -> 96000000 | D27: ='DIA_Giả Định'!$O$76 -> 9000000 | E27: =D27*'DIA_Giả Định'!$O$5 -> 108000000 | F27: ='DIA_Giả Định'!$P$76 -> 10000000 | G27: =F27*'DIA_Giả Định'!$P$5 -> 120000000 | H27: Giả định | I27: Nhân sự
A28: Lương chuyên môn y tế | B28: ='DIA_Giả Định'!$N$77 -> 6000000 | C28: =B28*'DIA_Giả Định'!$N$5 -> 72000000 | D28: ='DIA_Giả Định'!$O$77 -> 9000000 | E28: =D28*'DIA_Giả Định'!$O$5 -> 108000000 | F28: ='DIA_Giả Định'!$P$77 -> 12000000 | G28: =F28*'DIA_Giả Định'!$P$5 -> 144000000 | H28: Giả định | I28: Nhân sự
A29: Nhân sự kinh doanh B2B | B29: ='DIA_Giả Định'!$N$78 -> 8000000 | C29: =B29*'DIA_Giả Định'!$N$5 -> 96000000 | D29: ='DIA_Giả Định'!$O$78 -> 9500000 | E29: =D29*'DIA_Giả Định'!$O$5 -> 114000000 | F29: ='DIA_Giả Định'!$P$78 -> 12000000 | G29: =F29*'DIA_Giả Định'!$P$5 -> 144000000 | H29: Giả định | I29: Bán hàng & QLDN
A30: Marketing | B30: ='DIA_Giả Định'!$N$79 -> 15000000 | C30: =B30*'DIA_Giả Định'!$N$5 -> 180000000 | D30: ='DIA_Giả Định'!$O$79 -> 20000000 | E30: =D30*'DIA_Giả Định'!$O$5 -> 240000000 | F30: ='DIA_Giả Định'!$P$79 -> 25000000 | G30: =F30*'DIA_Giả Định'!$P$5 -> 300000000 | H30: Giả định | I30: Marketing
A31: Chăm sóc khách hàng | B31: ='DIA_Giả Định'!$N$80 -> 10000000 | C31: =B31*'DIA_Giả Định'!$N$5 -> 120000000 | D31: ='DIA_Giả Định'!$O$80 -> 12000000 | E31: =D31*'DIA_Giả Định'!$O$5 -> 144000000 | F31: ='DIA_Giả Định'!$P$80 -> 15000000 | G31: =F31*'DIA_Giả Định'!$P$5 -> 180000000 | H31: Giả định | I31: Nhân sự
A32: Kế toán và hành chính | B32: ='DIA_Giả Định'!$N$81 -> 7000000 | C32: =B32*'DIA_Giả Định'!$N$5 -> 84000000 | D32: ='DIA_Giả Định'!$O$81 -> 9000000 | E32: =D32*'DIA_Giả Định'!$O$5 -> 108000000 | F32: ='DIA_Giả Định'!$P$81 -> 12000000 | G32: =F32*'DIA_Giả Định'!$P$5 -> 144000000 | H32: Giả định | I32: Bán hàng & QLDN
A33: Thuê văn phòng văn phòng co - working | B33: - | C33: - | D33: ='DIA_Giả Định'!$O$82 -> 10000000 | E33: =D33*'DIA_Giả Định'!$N$5 -> 120000000 | F33: ='DIA_Giả Định'!$P$82 -> 12000000 | G33: =F33*'DIA_Giả Định'!$P$5 -> 144000000 | H33: Giả định | I33: Bán hàng & QLDN
A34: Phần mềm và công cụ làm việc | B34: ='DIA_Giả Định'!$N$83 -> 22812500 | C34: =B34*'DIA_Giả Định'!$N$5 -> 273750000 | D34: ='DIA_Giả Định'!$O$83 -> 22812500 | E34: =D34*'DIA_Giả Định'!$O$5 -> 273750000 | F34: ='DIA_Giả Định'!$P$83 -> 22812500 | G34: =F34*'DIA_Giả Định'!$P$5 -> 273750000 | H34: Giả định | I34: Công nghệ
A35: Kiểm tra bảo mật định kỳ | B35: ='DIA_Giả Định'!$N$84 -> 2000000 | C35: =B35*'DIA_Giả Định'!$N$5 -> 24000000 | D35: ='DIA_Giả Định'!$O$84 -> 4000000 | E35: =D35*'DIA_Giả Định'!$O$5 -> 48000000 | F35: ='DIA_Giả Định'!$P$84 -> 7000000 | G35: =F35*'DIA_Giả Định'!$P$5 -> 84000000 | H35: Giả định | I35: Công nghệ
A36: Pháp lý và tuân thủ dữ liệu | B36: =SUM(B37,B38) -> 10000000 | C36: =SUM(C37,C38) -> 120000000 | D36: =SUM(D37,D38) -> 14000000 | E36: =SUM(E37,E38) -> 168000000 | F36: =SUM(F37,F38) -> 18000000 | G36: =SUM(G37,G38) -> 216000000 | H36: Giả định | I36: Bán hàng & QLDN
A37: - Thuê tư vấn pháp lý / Kiểm toán tuân thủ định kỳ (Retainer Fee) | B37: 5000000 | C37: =B37*'DIA_Giả Định'!$N$5 -> 60000000 | D37: 7000000 | E37: =D37*'DIA_Giả Định'!$O$5 -> 84000000 | F37: 9000000 | G37: =F37*'DIA_Giả Định'!$P$5 -> 108000000 | H37: Giả định | I37: Bán hàng & QLDN
A38: - Nhân sự phụ trách bảo vệ dữ liệu (DPO - Data Protection Officer) | B38: 5000000 | C38: =B38*'DIA_Giả Định'!$N$5 -> 60000000 | D38: 7000000 | E38: =D38*'DIA_Giả Định'!$O$5 -> 84000000 | F38: 9000000 | G38: =F38*'DIA_Giả Định'!$P$5 -> 108000000 | H38: Giả định | I38: Bán hàng & QLDN
A39: Nghiên cứu và phát triển | B39: ='DIA_Giả Định'!$N$86 -> 4000000 | C39: =B39*'DIA_Giả Định'!$N$5 -> 48000000 | D39: ='DIA_Giả Định'!$O$86 -> 10000000 | E39: =D39*'DIA_Giả Định'!$O$5 -> 120000000 | F39: ='DIA_Giả Định'!$P$86 -> 18000000 | G39: =F39*'DIA_Giả Định'!$P$5 -> 216000000 | H39: Giả định | I39: Công nghệ
A40: Đi lại, demo, làm việc bệnh viện | B40: ='DIA_Giả Định'!$N$87 -> 3000000 | C40: =B40*'DIA_Giả Định'!$N$5 -> 36000000 | D40: ='DIA_Giả Định'!$O$87 -> 6000000 | E40: =D40*'DIA_Giả Định'!$O$5 -> 72000000 | F40: ='DIA_Giả Định'!$P$87 -> 12000000 | G40: =F40*'DIA_Giả Định'!$P$5 -> 144000000 | H40: Giả định | I40: Bán hàng & QLDN
A41: Dự phòng vận hành | B41: ='DIA_Giả Định'!$N$88 -> 6000000 | C41: =B41*'DIA_Giả Định'!$N$5 -> 72000000 | D41: ='DIA_Giả Định'!$O$88 -> 7000000 | E41: =D41*'DIA_Giả Định'!$O$5 -> 84000000 | F41: ='DIA_Giả Định'!$P$88 -> 8000000 | G41: =F41*'DIA_Giả Định'!$P$5 -> 96000000 | H41: Giả định | I41: Bán hàng & QLDN
A42: TỔNG ĐỊNH PHÍ | B42: =SUM(B26:B41) -> 136812500 | C42: =SUM(C26:C41) -> 1641750000 | D42: =SUM(D26:D41) -> 186312500 | E42: =SUM(E26:E41) -> 2235750000 | F42: =SUM(F26:F41) -> 236812500 | G42: =SUM(G26:G41) -> 2841750000
A45: C. CHI PHÍ BIẾN ĐỔI
A46: Khoản mục | B46: Cơ sở tính | C46: Đơn vị | D46: Năm 1 | E46: Năm 2 | F46: Năm 3 | G46: Nguồn | H46: Ghi chú | I46: Nhóm
A47: AI/OCR | B47: MAU × lượt quét × giá/lượt | C47: VNĐ | D47: =('DIA_Giả Định'!$N$6*'DIA_Giả Định'!$N$7)*'DIA_Giả Định'!$N$23*'DIA_Giả Định'!$N$45*'DIA_Giả Định'!$N$5 -> 52920000 | E47: =('DIA_Giả Định'!$O$6*'DIA_Giả Định'!$O$7)*'DIA_Giả Định'!$O$23*'DIA_Giả Định'!$O$45*'DIA_Giả Định'!$O$5 -> 196992000 | F47: =('DIA_Giả Định'!$P$6*'DIA_Giả Định'!$P$7)*'DIA_Giả Định'!$P$23*'DIA_Giả Định'!$P$45*'DIA_Giả Định'!$P$5 -> 97020000 | G47: Liên kết DIA_Giả Định / DIA_Giá và Doanh Thu | I47: B2C nền tảng
A48: Cloud theo người dùng | B48: MAU × chi phí cloud/tháng | C48: VNĐ | D48: =('DIA_Giả Định'!$N$6*'DIA_Giả Định'!$N$7)*'DIA_Giả Định'!$N$46*'DIA_Giả Định'!$N$5 -> 264600000 | E48: =('DIA_Giả Định'!$O$6*'DIA_Giả Định'!$O$7)*'DIA_Giả Định'!$O$46*'DIA_Giả Định'!$O$5 -> 1026000000 | F48: =('DIA_Giả Định'!$P$6*'DIA_Giả Định'!$P$7)*'DIA_Giả Định'!$P$46*'DIA_Giả Định'!$P$5 -> 508200000 | G48: Liên kết DIA_Giả Định / DIA_Giá và Doanh Thu | I48: B2C nền tảng
A49: Lưu trữ dữ liệu | B49: MAU × chi phí lưu trữ/tháng | C49: VNĐ | D49: =('DIA_Giả Định'!$N$6*'DIA_Giả Định'!$N$7)*'DIA_Giả Định'!$N$47*'DIA_Giả Định'!$N$5 -> 73500000 | E49: =('DIA_Giả Định'!$O$6*'DIA_Giả Định'!$O$7)*'DIA_Giả Định'!$O$47*'DIA_Giả Định'!$O$5 -> 307800000 | F49: =('DIA_Giả Định'!$P$6*'DIA_Giả Định'!$P$7)*'DIA_Giả Định'!$P$47*'DIA_Giả Định'!$P$5 -> 161700000 | G49: Liên kết DIA_Giả Định / DIA_Giá và Doanh Thu | I49: B2C nền tảng
A50: Phí thanh toán | B50: Doanh thu B2C × tỷ lệ phí | C50: VNĐ | D50: ='DIA_Giá và Doanh Thu'!$F$15*'DIA_Giả Định'!$N$49 -> 31311000 | E50: ='DIA_Giá và Doanh Thu'!$G$15*'DIA_Giả Định'!$O$49 -> 1.1629538e+08 | F50: ='DIA_Giá và Doanh Thu'!$H$15*'DIA_Giả Định'!$P$49 -> 56258336 | G50: Liên kết DIA_Giả Định / DIA_Giá và Doanh Thu | I50: B2C
A51: SMS/email/thông báo | B51: MAU × chi phí/tháng | C51: VNĐ | D51: =('DIA_Giả Định'!$N$6*'DIA_Giả Định'!$N$7)*'DIA_Giả Định'!$N$48*'DIA_Giả Định'!$N$5 -> 35280000 | E51: =('DIA_Giả Định'!$O$6*'DIA_Giả Định'!$O$7)*'DIA_Giả Định'!$O$48*'DIA_Giả Định'!$O$5 -> 153900000 | F51: =('DIA_Giả Định'!$P$6*'DIA_Giả Định'!$P$7)*'DIA_Giả Định'!$P$48*'DIA_Giả Định'!$P$5 -> 83160000 | G51: Liên kết DIA_Giả Định / DIA_Giá và Doanh Thu | I51: B2C nền tảng
A52: Hỗ trợ Pro | B52: Premium × phí hỗ trợ/tháng | C52: VNĐ | D52: =('DIA_Giả Định'!$N$6*'DIA_Giả Định'!$N$8)*'DIA_Giả Định'!$N$50*'DIA_Giả Định'!$N$5 -> 235200000 | E52: =('DIA_Giả Định'!$O$6*'DIA_Giả Định'!$O$8)*'DIA_Giả Định'!$O$50*'DIA_Giả Định'!$O$5 -> 855000000 | F52: =('DIA_Giả Định'!$P$6*'DIA_Giả Định'!$P$8)*'DIA_Giả Định'!$P$50*'DIA_Giả Định'!$P$5 -> 403200000 | G52: Liên kết DIA_Giả Định / DIA_Giá và Doanh Thu | I52: B2C
A53: Triển khai cơ sở | B53: Cơ sở ký mới × chi phí theo loại | C53: VNĐ | D53: ='DIA_Giả Định'!$N$27*'DIA_Giả Định'!$N$39+'DIA_Giả Định'!$N$28*'DIA_Giả Định'!$N$40 -> 110000000 | E53: ='DIA_Giả Định'!$O$27*'DIA_Giả Định'!$O$39+'DIA_Giả Định'!$O$28*'DIA_Giả Định'!$O$40 -> 190000000 | F53: ='DIA_Giả Định'!$P$27*'DIA_Giả Định'!$P$39+'DIA_Giả Định'!$P$28*'DIA_Giả Định'!$P$40 -> 350000000 | G53: Liên kết DIA_Giả Định / DIA_Giá và Doanh Thu | I53: B2B
A54: Hoa hồng bán hàng | B54: Doanh thu B2B × tỷ lệ | C54: VNĐ | D54: =('DIA_Giá và Doanh Thu'!$F$16+'DIA_Giá và Doanh Thu'!$F$18+'DIA_Giá và Doanh Thu'!$F$19)*'DIA_Giả Định'!$N$53 -> 44435000 | E54: =('DIA_Giá và Doanh Thu'!$G$16+'DIA_Giá và Doanh Thu'!$G$18+'DIA_Giá và Doanh Thu'!$G$19)*'DIA_Giả Định'!$O$53 -> 1.0906163e+08 | F54: =('DIA_Giá và Doanh Thu'!$H$16+'DIA_Giá và Doanh Thu'!$H$18+'DIA_Giá và Doanh Thu'!$H$19)*'DIA_Giả Định'!$P$53 -> 3.3344263e+08 | G54: Liên kết DIA_Giả Định / DIA_Giá và Doanh Thu | I54: B2B
A55: Chi phí đối tác | B55: Tổng doanh thu × tỷ lệ | C55: VNĐ | D55: ='DIA_Giá và Doanh Thu'!$F$20*'DIA_Giả Định'!$N$55 -> 33017100 | E55: ='DIA_Giá và Doanh Thu'!$G$20*'DIA_Giả Định'!$O$55 -> 1.0384572e+08 | F55: ='DIA_Giá và Doanh Thu'!$H$20*'DIA_Giả Định'!$P$55 -> 1.3603779e+08 | G55: Liên kết DIA_Giả Định / DIA_Giá và Doanh Thu | I55: Chung
A56: Chăm sóc B2B | B56: Cơ sở bình quân × phí/tháng | C56: VNĐ | D56: =('DIA_Giá và Doanh Thu'!$G$7)*'DIA_Giả Định'!$N$54*'DIA_Giả Định'!$N$5 -> 66000000 | E56: =('DIA_Giá và Doanh Thu'!$H$7)*'DIA_Giả Định'!$O$54*'DIA_Giả Định'!$O$5 -> 171600000 | F56: =('DIA_Giá và Doanh Thu'!$I$7)*'DIA_Giả Định'!$P$54*'DIA_Giả Định'!$P$5 -> 576000000 | G56: Liên kết DIA_Giả Định / DIA_Giá và Doanh Thu | I56: B2B
A57: Tư vấn bác sĩ | B57: Premium × phiên × giá/phiên | C57: VNĐ | D57: =('DIA_Giả Định'!$N$6*'DIA_Giả Định'!$N$8)*'DIA_Giả Định'!$N$56*'DIA_Giả Định'!$N$57 -> 28000000 | E57: =('DIA_Giả Định'!$O$6*'DIA_Giả Định'!$O$8)*'DIA_Giả Định'!$O$56*'DIA_Giả Định'!$O$57 -> 152000000 | F57: =('DIA_Giả Định'!$P$6*'DIA_Giả Định'!$P$8)*'DIA_Giả Định'!$P$56*'DIA_Giả Định'!$P$57 -> 84000000 | G57: Liên kết DIA_Giả Định / DIA_Giá và Doanh Thu | I57: B2C
A58: TỔNG BIẾN PHÍ | D58: =SUM(D47:D57) -> 974263100 | E58: =SUM(E47:E57) -> 3.3824947e+09 | F58: =SUM(F47:F57) -> 2.7890188e+09
A61: TỔNG HỢP CHI PHÍ
A62: Tổng đầu tư ban đầu | D62: =D21 -> 1755250000
A63: Tổng định phí vận hành | D63: =C42 -> 1641750000 | E63: =E42 -> 2235750000 | F63: =G42 -> 2841750000
A64: Tổng biến phí | D64: =D58 -> 974263100 | E64: =E58 -> 3.3824947e+09 | F64: =F58 -> 2.7890188e+09
A65: Tổng chi phí vận hành | D65: =D63+D64 -> 2616013100 | E65: =E63+E64 -> 5.6182447e+09 | F65: =F63+F64 -> 5.6307688e+09

Sheet DIA_Kịch Bản & Độ Nhạy
A1: DIA+ - PHÂN TÍCH KỊCH BẢN & ĐỘ NHẠY
A2: Ba kịch bản và bốn bảng độ nhạy được giữ nguyên; màu sắc và phân cấp tiêu đề được đồng bộ với mẫu YAMNUTRI.
A3: (giả định tỷ lệ giá vốn là 40%)
A4: SO SÁNH 3 KỊCH BẢN
A5: Chỉ tiêu | B5: Đơn vị | C5: Thận trọng | D5: Cơ sở | E5: Tích cực
A6: Tổng người dùng Năm 3 | B6: người | C6: =D23 -> 37500 | D6: =G23 -> 70000 | E6: =J23 -> 100000
A7: Tỷ lệ chuyển đổi Premium Năm 3 | B7: % | C7: ='DIA_Giả Định'!$G$8 -> 0.05 | D7: ='DIA_Giả Định'!$J$8 -> 0.06 | E7: ='DIA_Giả Định'!$M$8 -> 0.07
A8: Số cơ sở B2B Năm 3 | B8: cơ sở | C8: =D26 -> 25 | D8: =G26 -> 40 | E8: =J26 -> 55
A9: Doanh thu 3 năm | B9: VNĐ | C9: =SUM(B32:D32) -> 3.3748804e+09 | D9: =SUM(E32:G32) -> 1.0736359e+10 | E9: =SUM(H32:J32) -> 1.0923369e+10
A10: EBITDA 3 năm | B10: VNĐ | C10: =SUM(B35:D35) -> -4.3840161e+09 | D10: =SUM(E35:G35) -> -6.8348922e+08 | E10: =SUM(H35:J35) -> -4.4588506e+09
A11: Lợi nhuận sau thuế 3 năm | B11: VNĐ | C11: =SUM(B39:D39) -> -5.4828161e+09 | D11: =SUM(E39:G39) -> -2.0814175e+09 | E11: =SUM(H39:J39) -> -5.7268006e+09
A12: NPV | B12: VNĐ | C12: =B46 -> -3.2945406e+09 | D12: =E46 -> -1.4594359e+09 | E12: =H46 -> -4.4411218e+09
A13: IRR | B13: % | C13: =B47 -> 0 | D13: =E47 -> 0 | E13: =H47 -> 0
A14: Thời gian hoàn vốn | B14: năm | C14: =B48 -> >3 năm | D14: =E48 -> >3 năm | E14: =H48 -> >3 năm
A15: Nhu cầu vốn | B15: VNĐ | C15: =B49 -> 4.3676778e+09 | D15: =E49 -> 1.7450864e+09 | E15: =H49 -> 5.4441655e+09
B20: KHỐI TÍNH - THẬN TRỌNG | E20: KHỐI TÍNH - CƠ SỞ | H20: KHỐI TÍNH - TÍCH CỰC
A21: Chỉ tiêu | B21: Năm 1 | C21: Năm 2 | D21: Năm 3 | E21: Năm 1 | F21: Năm 2 | G21: Năm 3 | H21: Năm 1 | I21: Năm 2 | J21: Năm 3
A22: Đầu tư ban đầu | B22: ='DIA_Giả Định'!$E$90*'DIA_Giả Định'!$E$91+'DIA_Giả Định'!$E$92*'DIA_Giả Định'!$E$93+'DIA_Giả Định'!$E$94*'DIA_Giả Định'!$E$95+'DIA_Giả Định'!$E$96*'DIA_Giả Định'!$E$97+'DIA_Giả Định'!$E$98*'DIA_Giả Định'!$E$99+'DIA_Giả Định'!$E$100*'DIA_Giả Định'!$E$101+'DIA_Giả Định'!$E$102*'DIA_Giả Định'!$E$103+'DIA_Giả Định'!$E$104*'DIA_Giả Định'!$E$105+'DIA_Giả Định'!$E$106*'DIA_Giả Định'!$E$107+'DIA_Giả Định'!$E$108*'DIA_Giả Định'!$E$109+'DIA_Giả Định'!$E$110*'DIA_Giả Định'!$E$111+'DIA_Giả Định'!$E$112*'DIA_Giả Định'!$E$113+'DIA_Giả Định'!$E$114*'DIA_Giả Định'!$E$115+'DIA_Giả Định'!$E$116*'DIA_Giả Định'!$E$117+'DIA_Giả Định'!$E$118*'DIA_Giả Định'!$E$119 -> 684600000 | C22: 0 | D22: 0 | E22: ='DIA_Giả Định'!$H$90*'DIA_Giả Định'!$H$91+'DIA_Giả Định'!$H$92*'DIA_Giả Định'!$H$93+'DIA_Giả Định'!$H$94*'DIA_Giả Định'!$H$95+'DIA_Giả Định'!$H$96*'DIA_Giả Định'!$H$97+'DIA_Giả Định'!$H$98*'DIA_Giả Định'!$H$99+'DIA_Giả Định'!$H$100*'DIA_Giả Định'!$H$101+'DIA_Giả Định'!$H$102*'DIA_Giả Định'!$H$103+'DIA_Giả Định'!$H$104*'DIA_Giả Định'!$H$105+'DIA_Giả Định'!$H$106*'DIA_Giả Định'!$H$107+'DIA_Giả Định'!$H$108*'DIA_Giả Định'!$H$109+'DIA_Giả Định'!$H$110*'DIA_Giả Định'!$H$111+'DIA_Giả Định'!$H$112*'DIA_Giả Định'!$H$113+'DIA_Giả Định'!$H$114*'DIA_Giả Định'!$H$115+'DIA_Giả Định'!$H$116*'DIA_Giả Định'!$H$117+'DIA_Giả Định'!$H$118*'DIA_Giả Định'!$H$119 -> 880400000 | F22: 0 | G22: 0 | H22: ='DIA_Giả Định'!$K$90*'DIA_Giả Định'!$K$91+'DIA_Giả Định'!$K$92*'DIA_Giả Định'!$K$93+'DIA_Giả Định'!$K$94*'DIA_Giả Định'!$K$95+'DIA_Giả Định'!$K$96*'DIA_Giả Định'!$K$97+'DIA_Giả Định'!$K$98*'DIA_Giả Định'!$K$99+'DIA_Giả Định'!$K$100*'DIA_Giả Định'!$K$101+'DIA_Giả Định'!$K$102*'DIA_Giả Định'!$K$103+'DIA_Giả Định'!$K$104*'DIA_Giả Định'!$K$105+'DIA_Giả Định'!$K$106*'DIA_Giả Định'!$K$107+'DIA_Giả Định'!$K$108*'DIA_Giả Định'!$K$109+'DIA_Giả Định'!$K$110*'DIA_Giả Định'!$K$111+'DIA_Giả Định'!$K$112*'DIA_Giả Định'!$K$113+'DIA_Giả Định'!$K$114*'DIA_Giả Định'!$K$115+'DIA_Giả Định'!$K$116*'DIA_Giả Định'!$K$117+'DIA_Giả Định'!$K$118*'DIA_Giả Định'!$K$119 -> 1086050000 | I22: 0 | J22: 0
A23: Tổng người dùng | B23: ='DIA_Giả Định'!$E$6 -> 20000 | C23: ='DIA_Giả Định'!$F$6 -> 30000 | D23: ='DIA_Giả Định'!$G$6 -> 37500 | E23: ='DIA_Giả Định'!$H$6 -> 70000 | F23: ='DIA_Giả Định'!$I$6 -> 190000 | G23: ='DIA_Giả Định'!$J$6 -> 70000 | H23: ='DIA_Giả Định'!$K$6 -> 50000 | I23: ='DIA_Giả Định'!$L$6 -> 70000 | J23: ='DIA_Giả Định'!$M$6 -> 100000
A24: MAU | B24: =('DIA_Giả Định'!$E$6*'DIA_Giả Định'!$E$7) -> 6000 | C24: =('DIA_Giả Định'!$F$6*'DIA_Giả Định'!$F$7) -> 12000 | D24: =('DIA_Giả Định'!$G$6*'DIA_Giả Định'!$G$7) -> 18750 | E24: =('DIA_Giả Định'!$H$6*'DIA_Giả Định'!$H$7) -> 24500 | F24: =('DIA_Giả Định'!$I$6*'DIA_Giả Định'!$I$7) -> 85500 | G24: =('DIA_Giả Định'!$J$6*'DIA_Giả Định'!$J$7) -> 38500 | H24: =('DIA_Giả Định'!$K$6*'DIA_Giả Định'!$K$7) -> 20000 | I24: =('DIA_Giả Định'!$L$6*'DIA_Giả Định'!$L$7) -> 35000 | J24: =('DIA_Giả Định'!$M$6*'DIA_Giả Định'!$M$7) -> 60000
A25: Người dùng Pro | B25: =('DIA_Giả Định'!$E$6*'DIA_Giả Định'!$E$8) -> 600 | C25: =('DIA_Giả Định'!$F$6*'DIA_Giả Định'!$F$8) -> 1200 | D25: =('DIA_Giả Định'!$G$6*'DIA_Giả Định'!$G$8) -> 1875 | E25: =('DIA_Giả Định'!$H$6*'DIA_Giả Định'!$H$8) -> 2800 | F25: =('DIA_Giả Định'!$I$6*'DIA_Giả Định'!$I$8) -> 9500 | G25: =('DIA_Giả Định'!$J$6*'DIA_Giả Định'!$J$8) -> 4200 | H25: =('DIA_Giả Định'!$K$6*'DIA_Giả Định'!$K$8) -> 2500 | I25: =('DIA_Giả Định'!$L$6*'DIA_Giả Định'!$L$8) -> 4200 | J25: =('DIA_Giả Định'!$M$6*'DIA_Giả Định'!$M$8) -> 7000
A26: Cơ sở B2B cuối năm | B26: ='DIA_Giả Định'!$E$25+'DIA_Giả Định'!$E$26 -> 4 | C26: ='DIA_Giả Định'!$F$25+'DIA_Giả Định'!$F$26 -> 13 | D26: ='DIA_Giả Định'!$G$25+'DIA_Giả Định'!$G$26 -> 25 | E26: ='DIA_Giả Định'!$H$25+'DIA_Giả Định'!$H$26 -> 60 | F26: ='DIA_Giả Định'!$I$25+'DIA_Giả Định'!$I$26 -> 180 | G26: ='DIA_Giả Định'!$J$25+'DIA_Giả Định'!$J$26 -> 40 | H26: ='DIA_Giả Định'!$K$25+'DIA_Giả Định'!$K$26 -> 11 | I26: ='DIA_Giả Định'!$L$25+'DIA_Giả Định'!$L$26 -> 30 | J26: ='DIA_Giả Định'!$M$25+'DIA_Giả Định'!$M$26 -> 55
A27: Cơ sở B2B bình quân | B27: =(('DIA_Giả Định'!$E$25*'DIA_Giả Định'!$E$30)*'DIA_Giả Định'!$E$37*'DIA_Giả Định'!$E$5+('DIA_Giả Định'!$E$26*'DIA_Giả Định'!$E$30)*'DIA_Giả Định'!$E$37*'DIA_Giả Định'!$E$5) -> 19176000 | C27: =(('DIA_Giả Định'!$F$25*'DIA_Giả Định'!$F$30)*'DIA_Giả Định'!$F$37*'DIA_Giả Định'!$F$5+('DIA_Giả Định'!$F$26*'DIA_Giả Định'!$F$30)*'DIA_Giả Định'!$F$37*'DIA_Giả Định'!$F$5) -> 2.0586079e+08 | D27: =(('DIA_Giả Định'!$G$25*'DIA_Giả Định'!$G$30)*'DIA_Giả Định'!$G$37*'DIA_Giả Định'!$G$5+('DIA_Giả Định'!$G$26*'DIA_Giả Định'!$G$30)*'DIA_Giả Định'!$G$37*'DIA_Giả Định'!$G$5) -> 1.3076832e+09 | E27: =(('DIA_Giả Định'!$H$25*'DIA_Giả Định'!$H$30)*'DIA_Giả Định'!$H$37*'DIA_Giả Định'!$H$5+('DIA_Giả Định'!$H$26*'DIA_Giả Định'!$H$30)*'DIA_Giả Định'!$H$37*'DIA_Giả Định'!$H$5) -> 323640000 | F27: =(('DIA_Giả Định'!$I$25*'DIA_Giả Định'!$I$30)*'DIA_Giả Định'!$I$37*'DIA_Giả Định'!$I$5+('DIA_Giả Định'!$I$26*'DIA_Giả Định'!$I$30)*'DIA_Giả Định'!$I$37*'DIA_Giả Định'!$I$5) -> 1072575324 | G27: =(('DIA_Giả Định'!$J$25*'DIA_Giả Định'!$J$30)*'DIA_Giả Định'!$J$37*'DIA_Giả Định'!$J$5+('DIA_Giả Định'!$J$26*'DIA_Giả Định'!$J$30)*'DIA_Giả Định'!$J$37*'DIA_Giả Định'!$J$5) -> 2.6330532e+08 | H27: =(('DIA_Giả Định'!$K$25*'DIA_Giả Định'!$K$30)*'DIA_Giả Định'!$K$37*'DIA_Giả Định'!$K$5+('DIA_Giả Định'!$K$26*'DIA_Giả Định'!$K$30)*'DIA_Giả Định'!$K$37*'DIA_Giả Định'!$K$5) -> 65934000 | I27: =(('DIA_Giả Định'!$L$25*'DIA_Giả Định'!$L$30)*'DIA_Giả Định'!$L$37*'DIA_Giả Định'!$L$5+('DIA_Giả Định'!$L$26*'DIA_Giả Định'!$L$30)*'DIA_Giả Định'!$L$37*'DIA_Giả Định'!$L$5) -> 1.9864715e+08 | J27: =(('DIA_Giả Định'!$M$25*'DIA_Giả Định'!$M$30)*'DIA_Giả Định'!$M$37*'DIA_Giả Định'!$M$5+('DIA_Giả Định'!$M$26*'DIA_Giả Định'!$M$30)*'DIA_Giả Định'!$M$37*'DIA_Giả Định'!$M$5) -> 4.0231677e+08
A28: Doanh thu B2C | B28: =(('DIA_Giả Định'!$E$6*'DIA_Giả Định'!$E$8)*'DIA_Giả Định'!$E$9*'DIA_Giả Định'!$E$35*'DIA_Giả Định'!$E$5+('DIA_Giả Định'!$E$6*'DIA_Giả Định'!$E$8)*'DIA_Giả Định'!$E$10*'DIA_Giả Định'!$E$36) -> 201450000 | C28: =(('DIA_Giả Định'!$F$6*'DIA_Giả Định'!$F$8)*'DIA_Giả Định'!$F$9*'DIA_Giả Định'!$F$35*'DIA_Giả Định'!$F$5+('DIA_Giả Định'!$F$6*'DIA_Giả Định'!$F$8)*'DIA_Giả Định'!$F$10*'DIA_Giả Định'!$F$36) -> 441329904 | D28: =(('DIA_Giả Định'!$G$6*'DIA_Giả Định'!$G$8)*'DIA_Giả Định'!$G$9*'DIA_Giả Định'!$G$35*'DIA_Giả Định'!$G$5+('DIA_Giả Định'!$G$6*'DIA_Giả Định'!$G$8)*'DIA_Giả Định'!$G$10*'DIA_Giả Định'!$G$36) -> 705955575 | E28: =(('DIA_Giả Định'!$H$6*'DIA_Giả Định'!$H$8)*'DIA_Giả Định'!$H$9*'DIA_Giả Định'!$H$35*'DIA_Giả Định'!$H$5+('DIA_Giả Định'!$H$6*'DIA_Giả Định'!$H$8)*'DIA_Giả Định'!$H$10*'DIA_Giả Định'!$H$36) -> 1.25244e+09 | F28: =(('DIA_Giả Định'!$I$6*'DIA_Giả Định'!$I$8)*'DIA_Giả Định'!$I$9*'DIA_Giả Định'!$I$35*'DIA_Giả Định'!$I$5+('DIA_Giả Định'!$I$6*'DIA_Giả Định'!$I$8)*'DIA_Giả Định'!$I$10*'DIA_Giả Định'!$I$36) -> 4.651815e+09 | G28: =(('DIA_Giả Định'!$J$6*'DIA_Giả Định'!$J$8)*'DIA_Giả Định'!$J$9*'DIA_Giả Định'!$J$35*'DIA_Giả Định'!$J$5+('DIA_Giả Định'!$J$6*'DIA_Giả Định'!$J$8)*'DIA_Giả Định'!$J$10*'DIA_Giả Định'!$J$36) -> 2.2503334e+09 | H28: =(('DIA_Giả Định'!$K$6*'DIA_Giả Định'!$K$8)*'DIA_Giả Định'!$K$9*'DIA_Giả Định'!$K$35*'DIA_Giả Định'!$K$5+('DIA_Giả Định'!$K$6*'DIA_Giả Định'!$K$8)*'DIA_Giả Định'!$K$10*'DIA_Giả Định'!$K$36) -> 1392125000 | I28: =(('DIA_Giả Định'!$L$6*'DIA_Giả Định'!$L$8)*'DIA_Giả Định'!$L$9*'DIA_Giả Định'!$L$35*'DIA_Giả Định'!$L$5+('DIA_Giả Định'!$L$6*'DIA_Giả Định'!$L$8)*'DIA_Giả Định'!$L$10*'DIA_Giả Định'!$L$36) -> 2559052272 | J28: =(('DIA_Giả Định'!$M$6*'DIA_Giả Định'!$M$8)*'DIA_Giả Định'!$M$9*'DIA_Giả Định'!$M$35*'DIA_Giả Định'!$M$5+('DIA_Giả Định'!$M$6*'DIA_Giả Định'!$M$8)*'DIA_Giả Định'!$M$10*'DIA_Giả Định'!$M$36) -> 4.6645942e+09
A29: Doanh thu B2B | B29: =(('DIA_Giả Định'!$E$25*'DIA_Giả Định'!$E$30)*'DIA_Giả Định'!$E$37*'DIA_Giả Định'!$E$5+('DIA_Giả Định'!$E$26*'DIA_Giả Định'!$E$30)*'DIA_Giả Định'!$E$37*'DIA_Giả Định'!$E$5) -> 19176000 | C29: =(('DIA_Giả Định'!$F$25*'DIA_Giả Định'!$F$30)*'DIA_Giả Định'!$F$37*'DIA_Giả Định'!$F$5+('DIA_Giả Định'!$F$26*'DIA_Giả Định'!$F$30)*'DIA_Giả Định'!$F$37*'DIA_Giả Định'!$F$5) -> 2.0586079e+08 | D29: =(('DIA_Giả Định'!$G$25*'DIA_Giả Định'!$G$30)*'DIA_Giả Định'!$G$37*'DIA_Giả Định'!$G$5+('DIA_Giả Định'!$G$26*'DIA_Giả Định'!$G$30)*'DIA_Giả Định'!$G$37*'DIA_Giả Định'!$G$5) -> 1.3076832e+09 | E29: =(('DIA_Giả Định'!$H$25*'DIA_Giả Định'!$H$30)*'DIA_Giả Định'!$H$37*'DIA_Giả Định'!$H$5+('DIA_Giả Định'!$H$26*'DIA_Giả Định'!$H$30)*'DIA_Giả Định'!$H$37*'DIA_Giả Định'!$H$5) -> 323640000 | F29: =(('DIA_Giả Định'!$I$25*'DIA_Giả Định'!$I$30)*'DIA_Giả Định'!$I$37*'DIA_Giả Định'!$I$5+('DIA_Giả Định'!$I$26*'DIA_Giả Định'!$I$30)*'DIA_Giả Định'!$I$37*'DIA_Giả Định'!$I$5) -> 1072575324 | G29: =(('DIA_Giả Định'!$J$25*'DIA_Giả Định'!$J$30)*'DIA_Giả Định'!$J$37*'DIA_Giả Định'!$J$5+('DIA_Giả Định'!$J$26*'DIA_Giả Định'!$J$30)*'DIA_Giả Định'!$J$37*'DIA_Giả Định'!$J$5) -> 2.6330532e+08 | H29: =(('DIA_Giả Định'!$K$25*'DIA_Giả Định'!$K$30)*'DIA_Giả Định'!$K$37*'DIA_Giả Định'!$K$5+('DIA_Giả Định'!$K$26*'DIA_Giả Định'!$K$30)*'DIA_Giả Định'!$K$37*'DIA_Giả Định'!$K$5) -> 65934000 | I29: =(('DIA_Giả Định'!$L$25*'DIA_Giả Định'!$L$30)*'DIA_Giả Định'!$L$37*'DIA_Giả Định'!$L$5+('DIA_Giả Định'!$L$26*'DIA_Giả Định'!$L$30)*'DIA_Giả Định'!$L$37*'DIA_Giả Định'!$L$5) -> 1.9864715e+08 | J29: =(('DIA_Giả Định'!$M$25*'DIA_Giả Định'!$M$30)*'DIA_Giả Định'!$M$37*'DIA_Giả Định'!$M$5+('DIA_Giả Định'!$M$26*'DIA_Giả Định'!$M$30)*'DIA_Giả Định'!$M$37*'DIA_Giả Định'!$M$5) -> 4.0231677e+08
A30: Doanh thu triển khai | B30: ='DIA_Giả Định'!$E$27*'DIA_Giả Định'!$E$39+'DIA_Giả Định'!$E$28*'DIA_Giả Định'!$E$40 -> 54000000 | C30: =('DIA_Giả Định'!$F$27*'DIA_Giả Định'!$F$39+'DIA_Giả Định'!$F$28*'DIA_Giả Định'!$F$40) -> 117000000 | D30: =('DIA_Giả Định'!$G$27*'DIA_Giả Định'!$G$39+'DIA_Giả Định'!$G$28*'DIA_Giả Định'!$G$40) -> 189000000 | E30: ='DIA_Giả Định'!$H$27*'DIA_Giả Định'!$H$39+'DIA_Giả Định'!$H$28*'DIA_Giả Định'!$H$40 -> 110000000 | F30: =('DIA_Giả Định'!$I$27*'DIA_Giả Định'!$I$39+'DIA_Giả Định'!$I$28*'DIA_Giả Định'!$I$40) -> 190000000 | G30: =('DIA_Giả Định'!$J$27*'DIA_Giả Định'!$J$39+'DIA_Giả Định'!$J$28*'DIA_Giả Định'!$J$40) -> 350000000 | H30: ='DIA_Giả Định'!$K$27*'DIA_Giả Định'!$K$39+'DIA_Giả Định'!$K$28*'DIA_Giả Định'!$K$40 -> 187000000 | I30: =('DIA_Giả Định'!$L$27*'DIA_Giả Định'!$L$39+'DIA_Giả Định'!$L$28*'DIA_Giả Định'!$L$40) -> 319000000 | J30: =('DIA_Giả Định'!$M$27*'DIA_Giả Định'!$M$39+'DIA_Giả Định'!$M$28*'DIA_Giả Định'!$M$40) -> 539000000
A31: Doanh thu dịch vụ | B31: =('DIA_Giả Định'!$E$29*'DIA_Giả Định'!$E$41+'DIA_Giả Định'!$E$29*'DIA_Giả Định'!$E$43*'DIA_Giả Định'!$E$42) -> 15300000 | C31: =('DIA_Giả Định'!$F$29*'DIA_Giả Định'!$F$41+'DIA_Giả Định'!$F$29*'DIA_Giả Định'!$F$43*'DIA_Giả Định'!$F$42) -> 40500000 | D31: =('DIA_Giả Định'!$G$29*'DIA_Giả Định'!$G$41+'DIA_Giả Định'!$G$29*'DIA_Giả Định'!$G$43*'DIA_Giả Định'!$G$42) -> 77625000 | E31: =('DIA_Giả Định'!$H$29*'DIA_Giả Định'!$H$41+'DIA_Giả Định'!$H$29*'DIA_Giả Định'!$H$43*'DIA_Giả Định'!$H$42) -> 35000000 | F31: =('DIA_Giả Định'!$I$29*'DIA_Giả Định'!$I$41+'DIA_Giả Định'!$I$29*'DIA_Giả Định'!$I$43*'DIA_Giả Định'!$I$42) -> 74750000 | G31: =('DIA_Giả Định'!$J$29*'DIA_Giả Định'!$J$41+'DIA_Giả Định'!$J$29*'DIA_Giả Định'!$J$43*'DIA_Giả Định'!$J$42) -> 162500000 | H31: =('DIA_Giả Định'!$K$29*'DIA_Giả Định'!$K$41+'DIA_Giả Định'!$K$29*'DIA_Giả Định'!$K$43*'DIA_Giả Định'!$K$42) -> 73700000 | I31: =('DIA_Giả Định'!$L$29*'DIA_Giả Định'!$L$41+'DIA_Giả Định'!$L$29*'DIA_Giả Định'!$L$43*'DIA_Giả Định'!$L$42) -> 161500000 | J31: =('DIA_Giả Định'!$M$29*'DIA_Giả Định'!$M$41+'DIA_Giả Định'!$M$29*'DIA_Giả Định'!$M$43*'DIA_Giả Định'!$M$42) -> 360500000
A32: Tổng doanh thu | B32: =SUM(B28:B31) -> 289926000 | C32: =SUM(C28:C31) -> 8.0469069e+08 | D32: =SUM(D28:D31) -> 2.2802637e+09 | E32: =SUM(E28:E31) -> 1.72108e+09 | F32: =SUM(F28:F31) -> 5.9891404e+09 | G32: =SUM(G28:G31) -> 3.0261388e+09 | H32: =SUM(H28:H31) -> 1718759000 | I32: =SUM(I28:I31) -> 3238199426 | J32: =SUM(J28:J31) -> 5.966411e+09
A33: Chi phí biến đổi | B33: ='DIA_Giả Định'!$E$35*40%*'DIA_Giả Định'!$E$13 -> 69600000 | C33: ='DIA_Giả Định'!$F$35*40%*'DIA_Giả Định'!$F$13 -> 153774240 | D33: ='DIA_Giả Định'!$G$35*40%*'DIA_Giả Định'!$G$13 -> 240272250 | E33: ='DIA_Giả Định'!$H$35*40%*'DIA_Giả Định'!$H$13 -> 382200000 | F33: ='DIA_Giả Định'!$I$35*40%*'DIA_Giả Định'!$I$13 -> 1.4734489e+09 | G33: ='DIA_Giả Định'!$J$35*40%*'DIA_Giả Định'!$J$13 -> 7.3294947e+08 | H33: ='DIA_Giả Định'!$K$35*40%*'DIA_Giả Định'!$K$13 -> 392000000 | I33: ='DIA_Giả Định'!$L$35*40%*'DIA_Giả Định'!$L$13 -> 7.578242e+08 | J33: ='DIA_Giả Định'!$M$35*40%*'DIA_Giả Định'!$M$13 -> 1.4351458e+09
A34: Chi phí cố định | B34: =SUM('DIA_Giả Định'!E75:E88)*12 -> 1767750000 | C34: =SUM('DIA_Giả Định'!F75:F88)*12 -> 2403750000 | D34: =SUM('DIA_Giả Định'!G75:G88)*12 -> 3123750000 | E34: =SUM('DIA_Giả Định'!H75:H88)*12 -> 2241750000 | F34: =SUM('DIA_Giả Định'!I75:I88)*12 -> 2979750000 | G34: =SUM('DIA_Giả Định'!J75:J88)*12 -> 3609750000 | H34: =SUM('DIA_Giả Định'!K75:K88)*12 -> 3117750000 | I34: =SUM('DIA_Giả Định'!L75:L88)*12 -> 4251750000 | J34: =SUM('DIA_Giả Định'!M75:M88)*12 -> 5427750000
A35: EBITDA | B35: =B32-B33-B34 -> -1547424000 | C35: =C32-C33-C34 -> -1.7528335e+09 | D35: =D32-D33-D34 -> -1.0837585e+09 | E35: =E32-E33-E34 -> -9.0287e+08 | F35: =F32-F33-F34 -> 1.5359415e+09 | G35: =G32-G33-G34 -> -1.3165607e+09 | H35: =H32-H33-H34 -> -1790991000 | I35: =I32-I33-I34 -> -1771374774 | J35: =J32-J33-J34 -> -8.9648485e+08
A36: Khấu hao & phân bổ | B36: =((('DIA_Giả Định'!$E$92*'DIA_Giả Định'!$E$93)+('DIA_Giả Định'!$E$94*'DIA_Giả Định'!$E$95)+('DIA_Giả Định'!$E$104*'DIA_Giả Định'!$E$105)+('DIA_Giả Định'!$E$96*'DIA_Giả Định'!$E$97)+('DIA_Giả Định'!$E$98*'DIA_Giả Định'!$E$99)+('DIA_Giả Định'!$E$100*'DIA_Giả Định'!$E$101))/'DIA_Giả Định'!$E$64+(('DIA_Giả Định'!$E$114*'DIA_Giả Định'!$E$115)+('DIA_Giả Định'!$E$116*'DIA_Giả Định'!$E$117))/'DIA_Giả Định'!$E$65) -> 3.6626667e+08 | C36: =((('DIA_Giả Định'!$E$92*'DIA_Giả Định'!$E$93)+('DIA_Giả Định'!$E$94*'DIA_Giả Định'!$E$95)+('DIA_Giả Định'!$E$104*'DIA_Giả Định'!$E$105)+('DIA_Giả Định'!$E$96*'DIA_Giả Định'!$E$97)+('DIA_Giả Định'!$E$98*'DIA_Giả Định'!$E$99)+('DIA_Giả Định'!$E$100*'DIA_Giả Định'!$E$101))/'DIA_Giả Định'!$E$64+(('DIA_Giả Định'!$E$114*'DIA_Giả Định'!$E$115)+('DIA_Giả Định'!$E$116*'DIA_Giả Định'!$E$117))/'DIA_Giả Định'!$E$65) -> 3.6626667e+08 | D36: =((('DIA_Giả Định'!$E$92*'DIA_Giả Định'!$E$93)+('DIA_Giả Định'!$E$94*'DIA_Giả Định'!$E$95)+('DIA_Giả Định'!$E$104*'DIA_Giả Định'!$E$105)+('DIA_Giả Định'!$E$96*'DIA_Giả Định'!$E$97)+('DIA_Giả Định'!$E$98*'DIA_Giả Định'!$E$99)+('DIA_Giả Định'!$E$100*'DIA_Giả Định'!$E$101))/'DIA_Giả Định'!$E$64+(('DIA_Giả Định'!$E$114*'DIA_Giả Định'!$E$115)+('DIA_Giả Định'!$E$116*'DIA_Giả Định'!$E$117))/'DIA_Giả Định'!$E$65) -> 3.6626667e+08 | E36: =((('DIA_Giả Định'!$H$92*'DIA_Giả Định'!$H$93)+('DIA_Giả Định'!$H$94*'DIA_Giả Định'!$H$95)+('DIA_Giả Định'!$H$104*'DIA_Giả Định'!$H$105)+('DIA_Giả Định'!$H$96*'DIA_Giả Định'!$H$97)+('DIA_Giả Định'!$H$98*'DIA_Giả Định'!$H$99)+('DIA_Giả Định'!$H$100*'DIA_Giả Định'!$H$101))/'DIA_Giả Định'!$H$64+(('DIA_Giả Định'!$H$114*'DIA_Giả Định'!$H$115)+('DIA_Giả Định'!$H$116*'DIA_Giả Định'!$H$117))/'DIA_Giả Định'!$H$65) -> 389550000 | F36: =((('DIA_Giả Định'!$H$92*'DIA_Giả Định'!$H$93)+('DIA_Giả Định'!$H$94*'DIA_Giả Định'!$H$95)+('DIA_Giả Định'!$H$104*'DIA_Giả Định'!$H$105)+('DIA_Giả Định'!$H$96*'DIA_Giả Định'!$H$97)+('DIA_Giả Định'!$H$98*'DIA_Giả Định'!$H$99)+('DIA_Giả Định'!$H$100*'DIA_Giả Định'!$H$101))/'DIA_Giả Định'!$H$64+(('DIA_Giả Định'!$H$114*'DIA_Giả Định'!$H$115)+('DIA_Giả Định'!$H$116*'DIA_Giả Định'!$H$117))/'DIA_Giả Định'!$H$65) -> 389550000 | G36: =((('DIA_Giả Định'!$H$92*'DIA_Giả Định'!$H$93)+('DIA_Giả Định'!$H$94*'DIA_Giả Định'!$H$95)+('DIA_Giả Định'!$H$104*'DIA_Giả Định'!$H$105)+('DIA_Giả Định'!$H$96*'DIA_Giả Định'!$H$97)+('DIA_Giả Định'!$H$98*'DIA_Giả Định'!$H$99)+('DIA_Giả Định'!$H$100*'DIA_Giả Định'!$H$101))/'DIA_Giả Định'!$H$64+(('DIA_Giả Định'!$H$114*'DIA_Giả Định'!$H$115)+('DIA_Giả Định'!$H$116*'DIA_Giả Định'!$H$117))/'DIA_Giả Định'!$H$65) -> 389550000 | H36: =((('DIA_Giả Định'!$K$92*'DIA_Giả Định'!$K$93)+('DIA_Giả Định'!$K$94*'DIA_Giả Định'!$K$95)+('DIA_Giả Định'!$K$104*'DIA_Giả Định'!$K$105)+('DIA_Giả Định'!$K$96*'DIA_Giả Định'!$K$97)+('DIA_Giả Định'!$K$98*'DIA_Giả Định'!$K$99)+('DIA_Giả Định'!$K$100*'DIA_Giả Định'!$K$101))/'DIA_Giả Định'!$K$64+(('DIA_Giả Định'!$K$114*'DIA_Giả Định'!$K$115)+('DIA_Giả Định'!$K$116*'DIA_Giả Định'!$K$117))/'DIA_Giả Định'!$K$65) -> 422650000 | I36: =((('DIA_Giả Định'!$K$92*'DIA_Giả Định'!$K$93)+('DIA_Giả Định'!$K$94*'DIA_Giả Định'!$K$95)+('DIA_Giả Định'!$K$104*'DIA_Giả Định'!$K$105)+('DIA_Giả Định'!$K$96*'DIA_Giả Định'!$K$97)+('DIA_Giả Định'!$K$98*'DIA_Giả Định'!$K$99)+('DIA_Giả Định'!$K$100*'DIA_Giả Định'!$K$101))/'DIA_Giả Định'!$K$64+(('DIA_Giả Định'!$K$114*'DIA_Giả Định'!$K$115)+('DIA_Giả Định'!$K$116*'DIA_Giả Định'!$K$117))/'DIA_Giả Định'!$K$65) -> 422650000 | J36: =((('DIA_Giả Định'!$K$92*'DIA_Giả Định'!$K$93)+('DIA_Giả Định'!$K$94*'DIA_Giả Định'!$K$95)+('DIA_Giả Định'!$K$104*'DIA_Giả Định'!$K$105)+('DIA_Giả Định'!$K$96*'DIA_Giả Định'!$K$97)+('DIA_Giả Định'!$K$98*'DIA_Giả Định'!$K$99)+('DIA_Giả Định'!$K$100*'DIA_Giả Định'!$K$101))/'DIA_Giả Định'!$K$64+(('DIA_Giả Định'!$K$114*'DIA_Giả Định'!$K$115)+('DIA_Giả Định'!$K$116*'DIA_Giả Định'!$K$117))/'DIA_Giả Định'!$K$65) -> 422650000
A37: EBIT | B37: =B35-B36 -> -1.9136907e+09 | C37: =C35-C36 -> -2.1191002e+09 | D37: =D35-D36 -> -1.4500252e+09 | E37: =E35-E36 -> -1.29242e+09 | F37: =F35-F36 -> 1.1463915e+09 | G37: =G35-G36 -> -1.7061107e+09 | H37: =H35-H36 -> -2213641000 | I37: =I35-I36 -> -2194024774 | J37: =J35-J36 -> -1.3191348e+09
A38: Thuế | B38: =MAX(0,B37*'DIA_Giả Định'!$E$59) -> 0 | C38: =MAX(0,C37*'DIA_Giả Định'!$F$59) -> 0 | D38: =MAX(0,D37*'DIA_Giả Định'!$G$59) -> 0 | E38: =MAX(0,E37*'DIA_Giả Định'!$H$59) -> 0 | F38: =MAX(0,F37*'DIA_Giả Định'!$I$59) -> 2.292783e+08 | G38: =MAX(0,G37*'DIA_Giả Định'!$J$59) -> 0 | H38: =MAX(0,H37*'DIA_Giả Định'!$K$59) -> 0 | I38: =MAX(0,I37*'DIA_Giả Định'!$L$59) -> 0 | J38: =MAX(0,J37*'DIA_Giả Định'!$M$59) -> 0
A39: Lợi nhuận sau thuế | B39: =B37-B38 -> -1.9136907e+09 | C39: =C37-C38 -> -2.1191002e+09 | D39: =D37-D38 -> -1.4500252e+09 | E39: =E37-E38 -> -1.29242e+09 | F39: =F37-F38 -> 9.171132e+08 | G39: =G37-G38 -> -1.7061107e+09 | H39: =H37-H38 -> -2213641000 | I39: =I37-I38 -> -2194024774 | J39: =J37-J38 -> -1.3191348e+09
A40: Chi đầu tư bổ sung | B40: =-'DIA_Giả Định'!$E$73 -> 0 | C40: =-'DIA_Giả Định'!$F$73 -> -50000000 | D40: =-'DIA_Giả Định'!$G$73 -> -80000000 | E40: =-'DIA_Giả Định'!$H$73 -> 0 | F40: =-'DIA_Giả Định'!$I$73 -> -100000000 | G40: =-'DIA_Giả Định'!$J$73 -> -150000000 | H40: =-'DIA_Giả Định'!$K$73 -> 0 | I40: =-'DIA_Giả Định'!$L$73 -> -200000000 | J40: =-'DIA_Giả Định'!$M$73 -> -300000000
A41: Thay đổi vốn lưu động | B41: =-MAX(0,(B34/'DIA_Giả Định'!$E$5*'DIA_Giả Định'!$E$67)-('DIA_Giả Định'!$E$124*'DIA_Giả Định'!$E$125)) -> -39625000 | C41: =-MAX(0,(C34/'DIA_Giả Định'!$F$5*'DIA_Giả Định'!$F$67)-(B34/'DIA_Giả Định'!$E$5*'DIA_Giả Định'!$E$67)) -> -106000000 | D41: =-MAX(0,(D34/'DIA_Giả Định'!$G$5*'DIA_Giả Định'!$G$67)-(C34/'DIA_Giả Định'!$F$5*'DIA_Giả Định'!$F$67)) -> -120000000 | E41: =-MAX(0,(E34/'DIA_Giả Định'!$H$5*'DIA_Giả Định'!$H$67)-('DIA_Giả Định'!$H$124*'DIA_Giả Định'!$H$125)) -> -73625000 | F41: =-MAX(0,(F34/'DIA_Giả Định'!$I$5*'DIA_Giả Định'!$I$67)-(E34/'DIA_Giả Định'!$H$5*'DIA_Giả Định'!$H$67)) -> -123000000 | G41: =-MAX(0,(G34/'DIA_Giả Định'!$J$5*'DIA_Giả Định'!$J$67)-(F34/'DIA_Giả Định'!$I$5*'DIA_Giả Định'!$I$67)) -> -105000000 | H41: =-MAX(0,(H34/'DIA_Giả Định'!$K$5*'DIA_Giả Định'!$K$67)-('DIA_Giả Định'!$K$124*'DIA_Giả Định'!$K$125)) -> -159625000 | I41: =-MAX(0,(I34/'DIA_Giả Định'!$L$5*'DIA_Giả Định'!$L$67)-(H34/'DIA_Giả Định'!$K$5*'DIA_Giả Định'!$K$67)) -> -189000000 | J41: =-MAX(0,(J34/'DIA_Giả Định'!$M$5*'DIA_Giả Định'!$M$67)-(I34/'DIA_Giả Định'!$L$5*'DIA_Giả Định'!$L$67)) -> -196000000
A42: FCF | B42: =B37*(1-'DIA_Giả Định'!$E$59)+B36+B40+B41 -> -1.2043109e+09 | C42: =C37*(1-'DIA_Giả Định'!$F$59)+C36+C40+C41 -> -1.4850135e+09 | D42: =D37*(1-'DIA_Giả Định'!$G$59)+D36+D40+D41 -> -9.9375347e+08 | E42: =E37*(1-'DIA_Giả Định'!$H$59)+E36+E40+E41 -> -7.18011e+08 | F42: =F37*(1-'DIA_Giả Định'!$I$59)+F36+F40+F41 -> 1.0836632e+09 | G42: =G37*(1-'DIA_Giả Định'!$J$59)+G36+G40+G41 -> -1.2303386e+09 | H42: =H37*(1-'DIA_Giả Định'!$K$59)+H36+H40+H41 -> -1507887800 | I42: =I37*(1-'DIA_Giả Định'!$L$59)+I36+I40+I41 -> -1.7215698e+09 | J42: =J37*(1-'DIA_Giả Định'!$M$59)+J36+J40+J41 -> -1.1286579e+09
A43: FCF chiết khấu | B43: =B42/POWER(1+'DIA_Giả Định'!$E$60,1) -> -1.0035924e+09 | C43: =C42/POWER(1+'DIA_Giả Định'!$E$60,2) -> -1.0312594e+09 | D43: =D42/POWER(1+'DIA_Giả Định'!$E$60,3) -> -5.7508881e+08 | E43: =E42/POWER(1+'DIA_Giả Định'!$H$60,1) -> -6.084839e+08 | F43: =F42/POWER(1+'DIA_Giả Định'!$H$60,2) -> 7.7827003e+08 | G43: =G42/POWER(1+'DIA_Giả Định'!$H$60,3) -> -7.4882204e+08 | H43: =H42/POWER(1+'DIA_Giả Định'!$K$60,1) -> -1.3112068e+09 | I43: =I42/POWER(1+'DIA_Giả Định'!$K$60,2) -> -1.3017541e+09 | J43: =J42/POWER(1+'DIA_Giả Định'!$K$60,3) -> -7.4211088e+08
A44: FCF lũy kế | B44: =-B22+B42 -> -1.8889109e+09 | C44: =B44+C42 -> -3.3739244e+09 | D44: =C44+D42 -> -4.3676778e+09 | E44: =-E22+E42 -> -1.598411e+09 | F44: =E44+F42 -> -5.147478e+08 | G44: =F44+G42 -> -1.7450864e+09 | H44: =-H22+H42 -> -2593937800 | I44: =H44+I42 -> -4.3155076e+09 | J44: =I44+J42 -> -5.4441655e+09
A45: FCF chiết khấu lũy kế | B45: =-B22+B43 -> -1.6881924e+09 | C45: =B45+C43 -> -2.7194518e+09 | D45: =C45+D43 -> -3.2945406e+09 | E45: =-E22+E43 -> -1.4888839e+09 | F45: =E45+F43 -> -7.1061386e+08 | G45: =F45+G43 -> -1.4594359e+09 | H45: =-H22+H43 -> -2.3972568e+09 | I45: =H45+I43 -> -3.6990109e+09 | J45: =I45+J43 -> -4.4411218e+09
A46: NPV | B46: =SUM(B43:D43)-B22 -> -3.2945406e+09 | E46: =SUM(E43:G43)-E22 -> -1.4594359e+09 | H46: =SUM(H43:J43)-H22 -> -4.4411218e+09
A47: IRR | B47: =IF(D44<0,0,IFERROR(IRR(A51:D51),0)) -> 0 | E47: =IF(G44<0,0,IFERROR(IRR(L51:O51),0)) -> 0 | H47: =IF(J44<0,0,IFERROR(IRR(Q51:T51),0)) -> 0
A48: Thời gian hoàn vốn | B48: =IF(D44<0,">3 năm",IF(B44>=0,IFERROR(B22/B42,0),IF(C44>=0,1+IFERROR(ABS(B44)/C42,0),2+IFERROR(ABS(C44)/D42,0)))) -> >3 năm | E48: =IF(G44<0,">3 năm",IF(E44>=0,IFERROR(E22/E42,0),IF(F44>=0,1+IFERROR(ABS(E44)/F42,0),2+IFERROR(ABS(F44)/G42,0)))) -> >3 năm | H48: =IF(J44<0,">3 năm",IF(H44>=0,IFERROR(H22/H42,0),IF(I44>=0,1+IFERROR(ABS(H44)/I42,0),2+IFERROR(ABS(I44)/J42,0)))) -> >3 năm
A49: Nhu cầu vốn | B49: =MAX(0,-MIN(-B22,B44:D44)) -> 4.3676778e+09 | E49: =MAX(0,-MIN(-E22,E44:G44)) -> 1.7450864e+09 | H49: =MAX(0,-MIN(-H22,H44:J44)) -> 5.4441655e+09
A51: =-B22 -> -684600000 | B51: =B42 -> -1.2043109e+09 | C51: =C42 -> -1.4850135e+09 | D51: =D42 -> -9.9375347e+08 | E51: =E42 -> -7.18011e+08 | F51: =F42 -> 1.0836632e+09 | G51: =G42 -> -1.2303386e+09 | H51: =H42 -> -1507887800 | I51: =I42 -> -1.7215698e+09 | J51: =J42 -> -1.1286579e+09 | L51: =-E22 -> -880400000 | M51: =E42 -> -7.18011e+08 | N51: =F42 -> 1.0836632e+09 | O51: =G42 -> -1.2303386e+09 | Q51: =-H22 -> -1086050000 | R51: =H42 -> -1507887800 | S51: =I42 -> -1.7215698e+09 | T51: =J42 -> -1.1286579e+09
A57: BẢNG ĐỘ NHẠY 2 CHIỀU — KỊCH BẢN CƠ SỞ
A59: 1. Giá Premium × Chuyển đổi - Doanh thu B2C Năm 3 | G59: 2. Phí B2B × Số cơ sở - B2B ARR Năm 3
A60: Giá PrO/tháng \ Tỷ lệ chuyển đổi | B60: ='DIA_Giả Định'!$J$35*'DIA_Giả Định'!$N$145 -> 42834.709 | C60: ='DIA_Giả Định'!$J$35*'DIA_Giả Định'!$N$146 -> 47594.122 | D60: ='DIA_Giả Định'!$J$35*'DIA_Giả Định'!$N$147 -> 52353.534 | E60: ='DIA_Giả Định'!$J$35*'DIA_Giả Định'!$N$148 -> 57112.946 | G60: Phí B2B bình quân/tháng \ Số cơ sở | H60: =('DIA_Giả Định'!$J$25+'DIA_Giả Định'!$J$26)*'DIA_Giả Định'!$N$145 -> 36 | I60: =('DIA_Giả Định'!$J$25+'DIA_Giả Định'!$J$26)*'DIA_Giả Định'!$N$146 -> 40 | J60: =('DIA_Giả Định'!$J$25+'DIA_Giả Định'!$J$26)*'DIA_Giả Định'!$N$147 -> 44 | K60: =('DIA_Giả Định'!$J$25+'DIA_Giả Định'!$J$26)*'DIA_Giả Định'!$N$148 -> 48
A61: ='DIA_Giả Định'!$J$35*'DIA_Giả Định'!$N$144 -> 38075.297 | B61: ='DIA_Giả Định'!$J$6*B$60*('DIA_Giả Định'!$J$9*$A$61*'DIA_Giả Định'!$J$5+'DIA_Giả Định'!$J$10*$A$61*'DIA_Giả Định'!$J$5*(1-(1-'DIA_Giả Định'!$J$36/('DIA_Giả Định'!$J$35*'DIA_Giả Định'!$J$5)))) -> 1.2852317e+15 | C61: ='DIA_Giả Định'!$J$6*C$60*('DIA_Giả Định'!$J$9*$A$61*'DIA_Giả Định'!$J$5+'DIA_Giả Định'!$J$10*$A$61*'DIA_Giả Định'!$J$5*(1-(1-'DIA_Giả Định'!$J$36/('DIA_Giả Định'!$J$35*'DIA_Giả Định'!$J$5)))) -> 1.4280352e+15 | D61: ='DIA_Giả Định'!$J$6*D$60*('DIA_Giả Định'!$J$9*$A$61*'DIA_Giả Định'!$J$5+'DIA_Giả Định'!$J$10*$A$61*'DIA_Giả Định'!$J$5*(1-(1-'DIA_Giả Định'!$J$36/('DIA_Giả Định'!$J$35*'DIA_Giả Định'!$J$5)))) -> 1.5708388e+15 | E61: ='DIA_Giả Định'!$J$6*E$60*('DIA_Giả Định'!$J$9*$A$61*'DIA_Giả Định'!$J$5+'DIA_Giả Định'!$J$10*$A$61*'DIA_Giả Định'!$J$5*(1-(1-'DIA_Giả Định'!$J$36/('DIA_Giả Định'!$J$35*'DIA_Giả Định'!$J$5)))) -> 1.7136423e+15 | G61: =(('DIA_Giả Định'!$J$25*'DIA_Giả Định'!$J$38+'DIA_Giả Định'!$J$26*'DIA_Giả Định'!$J$37)/('DIA_Giả Định'!$J$25+'DIA_Giả Định'!$J$26))*'DIA_Giả Định'!$N$144 -> 2812063.3 | H61: =$G$61*H$60*'DIA_Giả Định'!$J$5 -> 1.2148114e+09 | I61: =$G$61*I$60*'DIA_Giả Định'!$J$5 -> 1.3497904e+09 | J61: =$G$61*J$60*'DIA_Giả Định'!$J$5 -> 1.4847694e+09 | K61: =$G$61*K$60*'DIA_Giả Định'!$J$5 -> 1.6197485e+09
A62: ='DIA_Giả Định'!$J$35*'DIA_Giả Định'!$N$145 -> 42834.709 | B62: ='DIA_Giả Định'!$J$6*B$60*('DIA_Giả Định'!$J$9*$A$62*'DIA_Giả Định'!$J$5+'DIA_Giả Định'!$J$10*$A$62*'DIA_Giả Định'!$J$5*(1-(1-'DIA_Giả Định'!$J$36/('DIA_Giả Định'!$J$35*'DIA_Giả Định'!$J$5)))) -> 1.4458857e+15 | C62: ='DIA_Giả Định'!$J$6*C$60*('DIA_Giả Định'!$J$9*$A$62*'DIA_Giả Định'!$J$5+'DIA_Giả Định'!$J$10*$A$62*'DIA_Giả Định'!$J$5*(1-(1-'DIA_Giả Định'!$J$36/('DIA_Giả Định'!$J$35*'DIA_Giả Định'!$J$5)))) -> 1.6065396e+15 | D62: ='DIA_Giả Định'!$J$6*D$60*('DIA_Giả Định'!$J$9*$A$62*'DIA_Giả Định'!$J$5+'DIA_Giả Định'!$J$10*$A$62*'DIA_Giả Định'!$J$5*(1-(1-'DIA_Giả Định'!$J$36/('DIA_Giả Định'!$J$35*'DIA_Giả Định'!$J$5)))) -> 1.7671936e+15 | E62: ='DIA_Giả Định'!$J$6*E$60*('DIA_Giả Định'!$J$9*$A$62*'DIA_Giả Định'!$J$5+'DIA_Giả Định'!$J$10*$A$62*'DIA_Giả Định'!$J$5*(1-(1-'DIA_Giả Định'!$J$36/('DIA_Giả Định'!$J$35*'DIA_Giả Định'!$J$5)))) -> 1.9278476e+15 | G62: =(('DIA_Giả Định'!$J$25*'DIA_Giả Định'!$J$38+'DIA_Giả Định'!$J$26*'DIA_Giả Định'!$J$37)/('DIA_Giả Định'!$J$25+'DIA_Giả Định'!$J$26))*'DIA_Giả Định'!$N$145 -> 3163571.2 | H62: =$G$62*H$60*'DIA_Giả Định'!$J$5 -> 1.3666628e+09 | I62: =$G$62*I$60*'DIA_Giả Định'!$J$5 -> 1.5185142e+09 | J62: =$G$62*J$60*'DIA_Giả Định'!$J$5 -> 1.6703656e+09 | K62: =$G$62*K$60*'DIA_Giả Định'!$J$5 -> 1.822217e+09
A63: ='DIA_Giả Định'!$J$35*'DIA_Giả Định'!$N$146 -> 47594.122 | B63: ='DIA_Giả Định'!$J$6*B$60*('DIA_Giả Định'!$J$9*$A$63*'DIA_Giả Định'!$J$5+'DIA_Giả Định'!$J$10*$A$63*'DIA_Giả Định'!$J$5*(1-(1-'DIA_Giả Định'!$J$36/('DIA_Giả Định'!$J$35*'DIA_Giả Định'!$J$5)))) -> 1.6065396e+15 | C63: ='DIA_Giả Định'!$J$6*C$60*('DIA_Giả Định'!$J$9*$A$63*'DIA_Giả Định'!$J$5+'DIA_Giả Định'!$J$10*$A$63*'DIA_Giả Định'!$J$5*(1-(1-'DIA_Giả Định'!$J$36/('DIA_Giả Định'!$J$35*'DIA_Giả Định'!$J$5)))) -> 1.785044e+15 | D63: ='DIA_Giả Định'!$J$6*D$60*('DIA_Giả Định'!$J$9*$A$63*'DIA_Giả Định'!$J$5+'DIA_Giả Định'!$J$10*$A$63*'DIA_Giả Định'!$J$5*(1-(1-'DIA_Giả Định'!$J$36/('DIA_Giả Định'!$J$35*'DIA_Giả Định'!$J$5)))) -> 1.9635485e+15 | E63: ='DIA_Giả Định'!$J$6*E$60*('DIA_Giả Định'!$J$9*$A$63*'DIA_Giả Định'!$J$5+'DIA_Giả Định'!$J$10*$A$63*'DIA_Giả Định'!$J$5*(1-(1-'DIA_Giả Định'!$J$36/('DIA_Giả Định'!$J$35*'DIA_Giả Định'!$J$5)))) -> 2.1420529e+15 | G63: =(('DIA_Giả Định'!$J$25*'DIA_Giả Định'!$J$38+'DIA_Giả Định'!$J$26*'DIA_Giả Định'!$J$37)/('DIA_Giả Định'!$J$25+'DIA_Giả Định'!$J$26))*'DIA_Giả Định'!$N$146 -> 3515079.1 | H63: =$G$63*H$60*'DIA_Giả Định'!$J$5 -> 1.5185142e+09 | I63: =$G$63*I$60*'DIA_Giả Định'!$J$5 -> 1.687238e+09 | J63: =$G$63*J$60*'DIA_Giả Định'!$J$5 -> 1.8559618e+09 | K63: =$G$63*K$60*'DIA_Giả Định'!$J$5 -> 2.0246856e+09
A64: ='DIA_Giả Định'!$J$35*'DIA_Giả Định'!$N$147 -> 52353.534 | B64: ='DIA_Giả Định'!$J$6*B$60*('DIA_Giả Định'!$J$9*$A$64*'DIA_Giả Định'!$J$5+'DIA_Giả Định'!$J$10*$A$64*'DIA_Giả Định'!$J$5*(1-(1-'DIA_Giả Định'!$J$36/('DIA_Giả Định'!$J$35*'DIA_Giả Định'!$J$5)))) -> 1.7671936e+15 | C64: ='DIA_Giả Định'!$J$6*C$60*('DIA_Giả Định'!$J$9*$A$64*'DIA_Giả Định'!$J$5+'DIA_Giả Định'!$J$10*$A$64*'DIA_Giả Định'!$J$5*(1-(1-'DIA_Giả Định'!$J$36/('DIA_Giả Định'!$J$35*'DIA_Giả Định'!$J$5)))) -> 1.9635485e+15 | D64: ='DIA_Giả Định'!$J$6*D$60*('DIA_Giả Định'!$J$9*$A$64*'DIA_Giả Định'!$J$5+'DIA_Giả Định'!$J$10*$A$64*'DIA_Giả Định'!$J$5*(1-(1-'DIA_Giả Định'!$J$36/('DIA_Giả Định'!$J$35*'DIA_Giả Định'!$J$5)))) -> 2.1599033e+15 | E64: ='DIA_Giả Định'!$J$6*E$60*('DIA_Giả Định'!$J$9*$A$64*'DIA_Giả Định'!$J$5+'DIA_Giả Định'!$J$10*$A$64*'DIA_Giả Định'!$J$5*(1-(1-'DIA_Giả Định'!$J$36/('DIA_Giả Định'!$J$35*'DIA_Giả Định'!$J$5)))) -> 2.3562581e+15 | G64: =(('DIA_Giả Định'!$J$25*'DIA_Giả Định'!$J$38+'DIA_Giả Định'!$J$26*'DIA_Giả Định'!$J$37)/('DIA_Giả Định'!$J$25+'DIA_Giả Định'!$J$26))*'DIA_Giả Định'!$N$147 -> 3866587.1 | H64: =$G$64*H$60*'DIA_Giả Định'!$J$5 -> 1.6703656e+09 | I64: =$G$64*I$60*'DIA_Giả Định'!$J$5 -> 1.8559618e+09 | J64: =$G$64*J$60*'DIA_Giả Định'!$J$5 -> 2.041558e+09 | K64: =$G$64*K$60*'DIA_Giả Định'!$J$5 -> 2.2271541e+09
A65: ='DIA_Giả Định'!$J$35*'DIA_Giả Định'!$N$148 -> 57112.946 | B65: ='DIA_Giả Định'!$J$6*B$60*('DIA_Giả Định'!$J$9*$A$65*'DIA_Giả Định'!$J$5+'DIA_Giả Định'!$J$10*$A$65*'DIA_Giả Định'!$J$5*(1-(1-'DIA_Giả Định'!$J$36/('DIA_Giả Định'!$J$35*'DIA_Giả Định'!$J$5)))) -> 1.9278476e+15 | C65: ='DIA_Giả Định'!$J$6*C$60*('DIA_Giả Định'!$J$9*$A$65*'DIA_Giả Định'!$J$5+'DIA_Giả Định'!$J$10*$A$65*'DIA_Giả Định'!$J$5*(1-(1-'DIA_Giả Định'!$J$36/('DIA_Giả Định'!$J$35*'DIA_Giả Định'!$J$5)))) -> 2.1420529e+15 | D65: ='DIA_Giả Định'!$J$6*D$60*('DIA_Giả Định'!$J$9*$A$65*'DIA_Giả Định'!$J$5+'DIA_Giả Định'!$J$10*$A$65*'DIA_Giả Định'!$J$5*(1-(1-'DIA_Giả Định'!$J$36/('DIA_Giả Định'!$J$35*'DIA_Giả Định'!$J$5)))) -> 2.3562581e+15 | E65: ='DIA_Giả Định'!$J$6*E$60*('DIA_Giả Định'!$J$9*$A$65*'DIA_Giả Định'!$J$5+'DIA_Giả Định'!$J$10*$A$65*'DIA_Giả Định'!$J$5*(1-(1-'DIA_Giả Định'!$J$36/('DIA_Giả Định'!$J$35*'DIA_Giả Định'!$J$5)))) -> 2.5704634e+15 | G65: =(('DIA_Giả Định'!$J$25*'DIA_Giả Định'!$J$38+'DIA_Giả Định'!$J$26*'DIA_Giả Định'!$J$37)/('DIA_Giả Định'!$J$25+'DIA_Giả Định'!$J$26))*'DIA_Giả Định'!$N$148 -> 4218095 | H65: =$G$65*H$60*'DIA_Giả Định'!$J$5 -> 1.822217e+09 | I65: =$G$65*I$60*'DIA_Giả Định'!$J$5 -> 2.0246856e+09 | J65: =$G$65*J$60*'DIA_Giả Định'!$J$5 -> 2.2271541e+09 | K65: =$G$65*K$60*'DIA_Giả Định'!$J$5 -> 2.4296227e+09
A69: 3. Chi phí AI/lượt × Lượt quét — Tổng chi phí AI Năm 3 | G69: 4. CAC × Churn — LTV/CAC B2C Năm 3
A70: Chi phí AI/lượt \ Lượt quét/MAU/tháng | B70: ='DIA_Giả Định'!$J$23*'DIA_Giả Định'!$N$144 -> 1.2 | C70: ='DIA_Giả Định'!$J$23*'DIA_Giả Định'!$N$145 -> 1.35 | D70: ='DIA_Giả Định'!$J$23*'DIA_Giả Định'!$N$146 -> 1.5 | E70: ='DIA_Giả Định'!$J$23*'DIA_Giả Định'!$N$148 -> 1.8 | G70: CAC B2C \ Churn/tháng | H70: ='DIA_Giả Định'!$J$17*'DIA_Giả Định'!$N$145 -> 0.045 | I70: ='DIA_Giả Định'!$J$17*'DIA_Giả Định'!$N$146 -> 0.05 | J70: ='DIA_Giả Định'!$J$17*'DIA_Giả Định'!$N$147 -> 0.055 | K70: ='DIA_Giả Định'!$J$17*'DIA_Giả Định'!$N$148 -> 0.06
A71: ='DIA_Giả Định'!$J$45*'DIA_Giả Định'!$N$144 -> 112 | B71: ='DIA_Giả Định'!$J$6*'DIA_Giả Định'!$J$7*$A$71*B$70*'DIA_Giả Định'!$J$5 -> 62092800 | C71: ='DIA_Giả Định'!$J$6*'DIA_Giả Định'!$J$7*$A$71*C$70*'DIA_Giả Định'!$J$5 -> 69854400 | D71: ='DIA_Giả Định'!$J$6*'DIA_Giả Định'!$J$7*$A$71*D$70*'DIA_Giả Định'!$J$5 -> 77616000 | E71: ='DIA_Giả Định'!$J$6*'DIA_Giả Định'!$J$7*$A$71*E$70*'DIA_Giả Định'!$J$5 -> 93139200 | G71: ='DIA_Hiệu Quả TC'!$D$87*'DIA_Giả Định'!$N$144 -> 0 | H71: =IFERROR(('DIA_Giá và Doanh Thu'!$H$21*'DIA_Hiệu Quả TC'!$D$35/H$70)/$G$71,0) -> 0 | I71: =IFERROR(('DIA_Giá và Doanh Thu'!$H$21*'DIA_Hiệu Quả TC'!$D$35/I$70)/$G$71,0) -> 0 | J71: =IFERROR(('DIA_Giá và Doanh Thu'!$H$21*'DIA_Hiệu Quả TC'!$D$35/J$70)/$G$71,0) -> 0 | K71: =IFERROR(('DIA_Giá và Doanh Thu'!$H$21*'DIA_Hiệu Quả TC'!$D$35/K$70)/$G$71,0) -> 0
A72: ='DIA_Giả Định'!$J$45*'DIA_Giả Định'!$N$145 -> 126 | B72: ='DIA_Giả Định'!$J$6*'DIA_Giả Định'!$J$7*$A$72*B$70*'DIA_Giả Định'!$J$5 -> 69854400 | C72: ='DIA_Giả Định'!$J$6*'DIA_Giả Định'!$J$7*$A$72*C$70*'DIA_Giả Định'!$J$5 -> 78586200 | D72: ='DIA_Giả Định'!$J$6*'DIA_Giả Định'!$J$7*$A$72*D$70*'DIA_Giả Định'!$J$5 -> 87318000 | E72: ='DIA_Giả Định'!$J$6*'DIA_Giả Định'!$J$7*$A$72*E$70*'DIA_Giả Định'!$J$5 -> 104781600 | G72: ='DIA_Hiệu Quả TC'!$D$87*'DIA_Giả Định'!$N$145 -> 0 | H72: =IFERROR(('DIA_Giá và Doanh Thu'!$H$21*'DIA_Hiệu Quả TC'!$D$35/H$70)/$G$72,0) -> 0 | I72: =IFERROR(('DIA_Giá và Doanh Thu'!$H$21*'DIA_Hiệu Quả TC'!$D$35/I$70)/$G$72,0) -> 0 | J72: =IFERROR(('DIA_Giá và Doanh Thu'!$H$21*'DIA_Hiệu Quả TC'!$D$35/J$70)/$G$72,0) -> 0 | K72: =IFERROR(('DIA_Giá và Doanh Thu'!$H$21*'DIA_Hiệu Quả TC'!$D$35/K$70)/$G$72,0) -> 0
A73: ='DIA_Giả Định'!$J$45*'DIA_Giả Định'!$N$146 -> 140 | B73: ='DIA_Giả Định'!$J$6*'DIA_Giả Định'!$J$7*$A$73*B$70*'DIA_Giả Định'!$J$5 -> 77616000 | C73: ='DIA_Giả Định'!$J$6*'DIA_Giả Định'!$J$7*$A$73*C$70*'DIA_Giả Định'!$J$5 -> 87318000 | D73: ='DIA_Giả Định'!$J$6*'DIA_Giả Định'!$J$7*$A$73*D$70*'DIA_Giả Định'!$J$5 -> 97020000 | E73: ='DIA_Giả Định'!$J$6*'DIA_Giả Định'!$J$7*$A$73*E$70*'DIA_Giả Định'!$J$5 -> 1.16424e+08 | G73: ='DIA_Hiệu Quả TC'!$D$87*'DIA_Giả Định'!$N$146 -> 0 | H73: =IFERROR(('DIA_Giá và Doanh Thu'!$H$21*'DIA_Hiệu Quả TC'!$D$35/H$70)/$G$73,0) -> 0 | I73: =IFERROR(('DIA_Giá và Doanh Thu'!$H$21*'DIA_Hiệu Quả TC'!$D$35/I$70)/$G$73,0) -> 0 | J73: =IFERROR(('DIA_Giá và Doanh Thu'!$H$21*'DIA_Hiệu Quả TC'!$D$35/J$70)/$G$73,0) -> 0 | K73: =IFERROR(('DIA_Giá và Doanh Thu'!$H$21*'DIA_Hiệu Quả TC'!$D$35/K$70)/$G$73,0) -> 0
A74: ='DIA_Giả Định'!$J$45*'DIA_Giả Định'!$N$147 -> 154 | B74: ='DIA_Giả Định'!$J$6*'DIA_Giả Định'!$J$7*$A$74*B$70*'DIA_Giả Định'!$J$5 -> 85377600 | C74: ='DIA_Giả Định'!$J$6*'DIA_Giả Định'!$J$7*$A$74*C$70*'DIA_Giả Định'!$J$5 -> 96049800 | D74: ='DIA_Giả Định'!$J$6*'DIA_Giả Định'!$J$7*$A$74*D$70*'DIA_Giả Định'!$J$5 -> 106722000 | E74: ='DIA_Giả Định'!$J$6*'DIA_Giả Định'!$J$7*$A$74*E$70*'DIA_Giả Định'!$J$5 -> 1.280664e+08 | G74: ='DIA_Hiệu Quả TC'!$D$87*'DIA_Giả Định'!$N$147 -> 0 | H74: =IFERROR(('DIA_Giá và Doanh Thu'!$H$21*'DIA_Hiệu Quả TC'!$D$35/H$70)/$G$74,0) -> 0 | I74: =IFERROR(('DIA_Giá và Doanh Thu'!$H$21*'DIA_Hiệu Quả TC'!$D$35/I$70)/$G$74,0) -> 0 | J74: =IFERROR(('DIA_Giá và Doanh Thu'!$H$21*'DIA_Hiệu Quả TC'!$D$35/J$70)/$G$74,0) -> 0 | K74: =IFERROR(('DIA_Giá và Doanh Thu'!$H$21*'DIA_Hiệu Quả TC'!$D$35/K$70)/$G$74,0) -> 0
A75: ='DIA_Giả Định'!$J$45*'DIA_Giả Định'!$N$148 -> 168 | B75: ='DIA_Giả Định'!$J$6*'DIA_Giả Định'!$J$7*$A$75*B$70*'DIA_Giả Định'!$J$5 -> 93139200 | C75: ='DIA_Giả Định'!$J$6*'DIA_Giả Định'!$J$7*$A$75*C$70*'DIA_Giả Định'!$J$5 -> 104781600 | D75: ='DIA_Giả Định'!$J$6*'DIA_Giả Định'!$J$7*$A$75*D$70*'DIA_Giả Định'!$J$5 -> 116424000 | E75: ='DIA_Giả Định'!$J$6*'DIA_Giả Định'!$J$7*$A$75*E$70*'DIA_Giả Định'!$J$5 -> 1.397088e+08 | G75: ='DIA_Hiệu Quả TC'!$D$87*'DIA_Giả Định'!$N$148 -> 0 | H75: =IFERROR(('DIA_Giá và Doanh Thu'!$H$21*'DIA_Hiệu Quả TC'!$D$35/H$70)/$G$75,0) -> 0 | I75: =IFERROR(('DIA_Giá và Doanh Thu'!$H$21*'DIA_Hiệu Quả TC'!$D$35/I$70)/$G$75,0) -> 0 | J75: =IFERROR(('DIA_Giá và Doanh Thu'!$H$21*'DIA_Hiệu Quả TC'!$D$35/J$70)/$G$75,0) -> 0 | K75: =IFERROR(('DIA_Giá và Doanh Thu'!$H$21*'DIA_Hiệu Quả TC'!$D$35/K$70)/$G$75,0) -> 0

Sheet DIA_Hiệu Quả TC
A1: DIA+ - HIỆU QUẢ TÀI CHÍNH 3 NĂM
A3: 1. THÔNG SỐ
A4: Chỉ tiêu | B4: Giá trị | C4: Ghi chú
A5: Tổng đầu tư ban đầu | B5: ='DIA_Chi Phí'!$D$21 -> 1755250000 | C5: Liên kết DIA_Chi Phí / DIA_Giả Định
A6: Tài sản hữu hình | B6: =SUMIF('DIA_Chi Phí'!$I$6:$I$20,"Tài sản hữu hình",'DIA_Chi Phí'!$D$6:$D$20) -> 139800000 | C6: Liên kết DIA_Chi Phí / DIA_Giả Định
A7: Chi phí phát triển phần mềm được phân bổ | B7: =SUMIF('DIA_Chi Phí'!$I$6:$I$20,"Phần mềm",'DIA_Chi Phí'!$D$6:$D$20) -> 454450000 | C7: Liên kết DIA_Chi Phí / DIA_Giả Định
A8: Vốn lưu động | B8: ='DIA_Chi Phí'!$D$19 -> 300000000 | C8: Liên kết DIA_Chi Phí / DIA_Giả Định
A9: Vốn vay | B9: =B5*'DIA_Giả Định'!$N$61 -> 0 | C9: Liên kết DIA_Chi Phí / DIA_Giả Định
A10: Vốn chủ sở hữu | B10: =B5-B9 -> 1755250000 | C10: Liên kết DIA_Chi Phí / DIA_Giả Định
A11: Lãi suất | B11: ='DIA_Giả Định'!$N$62 -> 0.1 | C11: Liên kết DIA_Chi Phí / DIA_Giả Định
A12: Suất chiết khấu | B12: ='DIA_Giả Định'!$N$60 -> 0.18 | C12: Liên kết DIA_Chi Phí / DIA_Giả Định
A13: Thuế TNDN | B13: ='DIA_Giả Định'!$N$59 -> 0.2 | C13: Liên kết DIA_Chi Phí / DIA_Giả Định
A14: Thời gian phân bổ phần mềm | B14: ='DIA_Giả Định'!$N$64 -> 1 | C14: Liên kết DIA_Chi Phí / DIA_Giả Định
A15: Vòng đời dự án | B15: ='DIA_Giả Định'!$N$66 -> 3 | C15: Liên kết DIA_Chi Phí / DIA_Giả Định
A17: 2. KẾ HOẠCH TÀI CHÍNH
A18: 2.1. Kế hoạch vay và trả nợ hàng năm
A19: Chỉ tiêu | B19: Năm 1 | C19: Năm 2 | D19: Năm 3
A20: Nợ đầu kỳ | B20: =IF('DIA_Giả Định'!$N$61=0,0,B9) -> 0 | C20: =B24 -> 0 | D20: =C24 -> 0
A21: Lãi phát sinh | B21: =IF('DIA_Giả Định'!$N$61=0,0,B20*'DIA_Giả Định'!$N$62) -> 0 | C21: =IF('DIA_Giả Định'!$N$61=0,0,C20*'DIA_Giả Định'!$O$62) -> 0 | D21: =IF('DIA_Giả Định'!$N$61=0,0,D20*'DIA_Giả Định'!$P$62) -> 0
A22: Trả lãi | B22: =B21 -> 0 | C22: =C21 -> 0 | D22: =D21 -> 0
A23: Trả gốc | B23: =IF('DIA_Giả Định'!$N$61=0,0,MIN(B20,B9/'DIA_Giả Định'!$N$71)) -> 0 | C23: =IF('DIA_Giả Định'!$N$61=0,0,MIN(C20,B9/'DIA_Giả Định'!$N$71)) -> 0 | D23: =IF('DIA_Giả Định'!$N$61=0,0,MIN(D20,B9/'DIA_Giả Định'!$N$71)) -> 0
A24: Nợ cuối kỳ | B24: =MAX(0,B20-B23) -> 0 | C24: =MAX(0,C20-C23) -> 0 | D24: =MAX(0,D20-D23) -> 0
A27: 2.2. Kế hoạch thu nhập hàng năm
A28: Chỉ tiêu | B28: Năm 1 | C28: Năm 2 | D28: Năm 3
A29: Tổng doanh thu | B29: ='DIA_Giá và Doanh Thu'!$F$20 -> 2201140000 | C29: ='DIA_Giá và Doanh Thu'!$G$20 -> 6.9230477e+09 | D29: ='DIA_Giá và Doanh Thu'!$H$20 -> 9.069186e+09
A30: Doanh thu B2C | B30: ='DIA_Giá và Doanh Thu'!$F$15 -> 1.25244e+09 | C30: ='DIA_Giá và Doanh Thu'!$G$15 -> 4.651815e+09 | D30: ='DIA_Giá và Doanh Thu'!$H$15 -> 2.2503334e+09
A31: Doanh thu B2B | B31: ='DIA_Giá và Doanh Thu'!$F$16 -> 803700000 | C31: ='DIA_Giá và Doanh Thu'!$G$16 -> 2006482698 | D31: ='DIA_Giá và Doanh Thu'!$H$16 -> 6.3063526e+09
A32: Doanh thu triển khai & dịch vụ | B32: ='DIA_Giá và Doanh Thu'!$F$18+'DIA_Giá và Doanh Thu'!$F$19 -> 85000000 | C32: ='DIA_Giá và Doanh Thu'!$G$18+'DIA_Giá và Doanh Thu'!$G$19 -> 174750000 | D32: ='DIA_Giá và Doanh Thu'!$H$18+'DIA_Giá và Doanh Thu'!$H$19 -> 362500000
A33: Chi phí biến đổi | B33: ='DIA_Chi Phí'!$D$58 -> 974263100 | C33: ='DIA_Chi Phí'!$E$58 -> 3.3824947e+09 | D33: ='DIA_Chi Phí'!$F$58 -> 2.7890188e+09
A34: Lợi nhuận gộp | B34: =B29-B33 -> 1226876900 | C34: =C29-C33 -> 3.540553e+09 | D34: =D29-D33 -> 6.2801673e+09
A35: Gross Margin | B35: =IFERROR(B34/B29,0) -> 0.55738249 | C35: =IFERROR(C34/C29,0) -> 0.51141537 | D35: =IFERROR(D34/D29,0) -> 0.69247309
A36: Chi phí nhân sự | B36: =SUMIF('DIA_Chi Phí'!$I$26:$I$41,"Nhân sự",'DIA_Chi Phí'!$C$26:$C$41) -> 588000000 | C36: =SUMIF('DIA_Chi Phí'!$I$26:$I$41,"Nhân sự",'DIA_Chi Phí'!$E$26:$E$41) -> 720000000 | D36: =SUMIF('DIA_Chi Phí'!$I$26:$I$41,"Nhân sự",'DIA_Chi Phí'!$G$26:$G$41) -> 864000000
A37: Chi phí marketing | B37: =SUMIF('DIA_Chi Phí'!$I$26:$I$41,"Marketing",'DIA_Chi Phí'!$C$26:$C$41) -> 180000000 | C37: =SUMIF('DIA_Chi Phí'!$I$26:$I$41,"Marketing",'DIA_Chi Phí'!$E$26:$E$41) -> 240000000 | D37: =SUMIF('DIA_Chi Phí'!$I$26:$I$41,"Marketing",'DIA_Chi Phí'!$G$26:$G$41) -> 300000000
A38: Chi phí công nghệ | B38: =SUMIF('DIA_Chi Phí'!$I$26:$I$41,"Công nghệ",'DIA_Chi Phí'!$C$26:$C$41) -> 345750000 | C38: =SUMIF('DIA_Chi Phí'!$I$26:$I$41,"Công nghệ",'DIA_Chi Phí'!$E$26:$E$41) -> 441750000 | D38: =SUMIF('DIA_Chi Phí'!$I$26:$I$41,"Công nghệ",'DIA_Chi Phí'!$G$26:$G$41) -> 573750000
A39: Chi phí bán hàng & quản lý | B39: =SUMIF('DIA_Chi Phí'!$I$26:$I$41,"Bán hàng & QLDN",'DIA_Chi Phí'!$C$26:$C$41) -> 528000000 | C39: =SUMIF('DIA_Chi Phí'!$I$26:$I$41,"Bán hàng & QLDN",'DIA_Chi Phí'!$E$26:$E$41) -> 834000000 | D39: =SUMIF('DIA_Chi Phí'!$I$26:$I$41,"Bán hàng & QLDN",'DIA_Chi Phí'!$G$26:$G$41) -> 1104000000
A40: EBITDA | B40: =B34-SUM(B36:B39) -> -414873100 | C40: =C34-SUM(C36:C39) -> 1.304803e+09 | D40: =D34-SUM(D36:D39) -> 3.4384173e+09
A41: Biên EBITDA | B41: =IFERROR(B40/B29,0) -> -0.18848101 | C41: =IFERROR(C40/C29,0) -> 0.18847234 | D41: =IFERROR(D40/D29,0) -> 0.37913185
A42: Khấu hao / phân bổ phần mềm | B42: =B6/'DIA_Giả Định'!$N$65+B7/'DIA_Giả Định'!$N$64 -> 489400000 | C42: =IF(2<='DIA_Giả Định'!$N$65,B6/'DIA_Giả Định'!$N$65,0)+IF(2<='DIA_Giả Định'!$N$64,B7/'DIA_Giả Định'!$N$64,0) -> 34950000 | D42: =IF(3<='DIA_Giả Định'!$N$65,B6/'DIA_Giả Định'!$N$65,0)+IF(3<='DIA_Giả Định'!$N$64,B7/'DIA_Giả Định'!$N$64,0) -> 34950000
A43: EBIT | B43: =B40-B42 -> -904273100 | C43: =C40-C42 -> 1.269853e+09 | D43: =D40-D42 -> 3.4034673e+09
A44: Chi phí lãi vay | B44: =B22 -> 0 | C44: =C22 -> 0 | D44: =D22 -> 0
A45: Lợi nhuận trước thuế | B45: =B43-B44 -> -904273100 | C45: =C43-C44 -> 1.269853e+09 | D45: =D43-D44 -> 3.4034673e+09
A46: Thuế | B46: =MAX(0,B45*'DIA_Giả Định'!$N$59) -> 0 | C46: =MAX(0,C45*'DIA_Giả Định'!$O$59) -> 2.539706e+08 | D46: =MAX(0,D45*'DIA_Giả Định'!$P$59) -> 6.8069345e+08
A47: Lợi nhuận sau thuế | B47: =B45-B46 -> -904273100 | C47: =C45-C46 -> 1.0158824e+09 | D47: =D45-D46 -> 2.7227738e+09
A48: Net Profit Margin | B48: =IFERROR(B47/B29,0) -> -0.41082035 | C48: =IFERROR(C47/C29,0) -> 0.14673919 | D48: =IFERROR(D47/D29,0) -> 0.30022251
A51: 2.3. Dòng tiền
A52: Chỉ tiêu | B52: Năm 0 | C52: Năm 1 | D52: Năm 2 | E52: Năm 3
A53: Dòng tiền đầu tư ban đầu | B53: =-B5 -> -1755250000 | C53: 0 | D53: 0 | E53: 0
A54: Dòng tiền từ hoạt động kinh doanh | B54: 0 | C54: =B47+B42 -> -414873100 | D54: =C47+C42 -> 1.0508324e+09 | E54: =D47+D42 -> 2.7577238e+09
A55: Dòng tiền vay | B55: =B9 -> 0 | C55: 0 | D55: 0 | E55: 0
A56: Vốn chủ sở hữu góp | B56: =B10 -> 1755250000 | C56: 0 | D56: 0 | E56: 0
A57: Trả nợ gốc | B57: 0 | C57: =-B23 -> 0 | D57: =-C23 -> 0 | E57: =-D23 -> 0
A58: Chi đầu tư bổ sung | B58: 0 | C58: =-'DIA_Giả Định'!$N$73 -> 0 | D58: =-'DIA_Giả Định'!$O$73 -> -100000000 | E58: =-'DIA_Giả Định'!$P$73 -> -150000000
A59: Thay đổi vốn lưu động | B59: 0 | C59: =-MAX(0,('DIA_Chi Phí'!$C$42/'DIA_Giả Định'!$N$5*'DIA_Giả Định'!$N$67)-B8) -> 0 | D59: =-MAX(0,('DIA_Chi Phí'!$E$42/'DIA_Giả Định'!$O$5*'DIA_Giả Định'!$O$67)-('DIA_Chi Phí'!$C$42/'DIA_Giả Định'!$N$5*'DIA_Giả Định'!$N$67)) -> -99000000 | E59: =-MAX(0,('DIA_Chi Phí'!$G$42/'DIA_Giả Định'!$P$5*'DIA_Giả Định'!$P$67)-('DIA_Chi Phí'!$E$42/'DIA_Giả Định'!$O$5*'DIA_Giả Định'!$O$67)) -> -101000000
A60: Dòng tiền ròng | B60: =SUM(B53:B56) -> 0 | C60: =SUM(C53:C59) -> -414873100 | D60: =SUM(D53:D59) -> 8.518324e+08 | E60: =SUM(E53:E59) -> 2.5067238e+09
A61: Dòng tiền lũy kế | B61: =B60 -> 0 | C61: =B61+C60 -> -414873100 | D61: =C61+D60 -> 4.369593e+08 | E61: =D61+E60 -> 2.9436831e+09
A62: Dòng tiền dự án (FCF) | B62: =-B5 -> -1755250000 | C62: =B43*(1-'DIA_Giả Định'!$N$59)+B42+C58+C59 -> -234018480 | D62: =C43*(1-'DIA_Giả Định'!$O$59)+C42+D58+D59 -> 8.518324e+08 | E62: =D43*(1-'DIA_Giả Định'!$P$59)+D42+E58+E59 -> 2.5067238e+09
A63: FCF chiết khấu | B63: =B62 -> -1755250000 | C63: =C62/POWER(1+'DIA_Giả Định'!$N$60,1) -> -1.9832075e+08 | D63: =D62/POWER(1+'DIA_Giả Định'!$N$60,2) -> 6.1177277e+08 | E63: =E62/POWER(1+'DIA_Giả Định'!$N$60,3) -> 1.5256695e+09
A64: FCF lũy kế | B64: =B62 -> -1755250000 | C64: =B64+C62 -> -1989268480 | D64: =C64+D62 -> -1.1374361e+09 | E64: =D64+E62 -> 1.3692877e+09
A65: FCF chiết khấu lũy kế | B65: =B63 -> -1755250000 | C65: =B65+C63 -> -1.9535707e+09 | D65: =C65+D63 -> -1.341798e+09 | E65: =D65+E63 -> 1.8387153e+08
A67: 3. HIỆU QUẢ TÀI CHÍNH
A68: 3.1. NPV, IRR, hoàn vốn và điểm hòa vốn
A69: Chỉ tiêu | B69: Giá trị | C69: Diễn giải | D69: Đánh giá | E69: Kết luận
A70: NPV | B70: {=NPV('DIA_Giả Định'!$N$60,C62:E62)+B62} -> 1.8387153e+08 | C70: Kết quả thay đổi theo kịch bản và giả định. | D70: NPV | E70: =IF(B70>0,"CÓ — NPV>0, dự án có hiệu quả tài chính","CHƯA — NPV≤0, cần điều chỉnh giả định") -> CÓ — NPV>0, dự án có hiệu quả tài chính
A71: IRR | B71: =IF(E64<0,0,IFERROR(IRR(B62:E62),0)) -> 0.22137183 | C71: Kết quả thay đổi theo kịch bản và giả định. | D71: IRR | E71: =IF(B71>B12,"CÓ — IRR>r, dự án có hiệu quả tài chính","CHƯA — IRR≤r, cần điều chỉnh giả định") -> CÓ — IRR>r, dự án có hiệu quả tài chính
A72: Thời gian hoàn vốn chưa chiết khấu | B72: =IF(E64<0,">3 năm",IF(C64>=0,IFERROR(ABS(B64)/C62,0),IF(D64>=0,1+IFERROR(ABS(C64)/D62,0),2+IFERROR(ABS(D64)/E62,0)))) -> 2.453754 | C72: Kết quả thay đổi theo kịch bản và giả định. | D72: Hoàn vốn | E72: =IF(B72=">3 năm","CHƯA — Chưa hoàn vốn trong 3 năm","CÓ — Hoàn vốn trong vòng đời dự án") -> CÓ — Hoàn vốn trong vòng đời dự án
A73: Thời gian hoàn vốn có chiết khấu | B73: =IF(E65<0,">3 năm",IF(C65>=0,IFERROR(ABS(B65)/C63,0),IF(D65>=0,1+IFERROR(ABS(C65)/D63,0),2+IFERROR(ABS(D65)/E63,0)))) -> 2.8794814 | C73: Kết quả thay đổi theo kịch bản và giả định. | D73: Dòng tiền | E73: =IF(E65<0,"CẢNH BÁO — Dòng tiền chiết khấu lũy kế còn âm","TỐT — Dòng tiền chiết khấu lũy kế dương") -> TỐT — Dòng tiền chiết khấu lũy kế dương
A74: ROI | B74: =IFERROR(SUM(B47:D47)/B5,0) -> 1.6148031 | C74: Kết quả thay đổi theo kịch bản và giả định.
A75: Biên lợi nhuận gộp | B75: =D35 -> 0.69247309 | C75: Kết quả thay đổi theo kịch bản và giả định.
A76: Biên EBITDA | B76: =D41 -> 0.37913185 | C76: Kết quả thay đổi theo kịch bản và giả định.
A77: Biên lợi nhuận ròng | B77: =D48 -> 0.30022251 | C77: Kết quả thay đổi theo kịch bản và giả định.
A78: Burn Rate bình quân / tháng | B78: =IFERROR(-SUMIF(C60:E60,"<0",C60:E60)/(COUNTIF(C60:E60,"<0")*'DIA_Giả Định'!$N$5),0) -> 34572758 | C78: Kết quả thay đổi theo kịch bản và giả định.
A79: Runway | B79: =IFERROR(B8/B78,0) -> 8.6773522 | C79: Kết quả thay đổi theo kịch bản và giả định.
A80: Điểm hòa vốn doanh thu | B80: =IFERROR(SUM(D36:D39)/(IFERROR((D29-D33)/D29,0)),0) -> 4.1037696e+09 | C80: Kết quả thay đổi theo kịch bản và giả định.
A81: Điểm hòa vốn số người dùng Premium | B81: =MAX(0,IFERROR((SUM(D36:D39)-(D31-'DIA_Chi Phí'!$F$54-'DIA_Chi Phí'!$F$56))/('DIA_Giá và Doanh Thu'!$H$21*'DIA_Giả Định'!$P$5-'DIA_Giả Định'!$P$23*'DIA_Giả Định'!$P$45*'DIA_Giả Định'!$P$5-('DIA_Giả Định'!$P$46+'DIA_Giả Định'!$P$47+'DIA_Giả Định'!$P$48)*'DIA_Giả Định'!$P$5-'DIA_Giá và Doanh Thu'!$H$21*'DIA_Giả Định'!$P$5*'DIA_Giả Định'!$P$49-'DIA_Giả Định'!$P$50*'DIA_Giả Định'!$P$5-'DIA_Giả Định'!$P$56*'DIA_Giả Định'!$P$57),0)) -> 0 | C81: Kết quả thay đổi theo kịch bản và giả định.
A82: Điểm hòa vốn số cơ sở B2B | B82: =MAX(0,IFERROR((SUM(D36:D39)-(D30-'DIA_Chi Phí'!$F$50-'DIA_Chi Phí'!$F$52))/(IFERROR((D31-'DIA_Chi Phí'!$F$54-'DIA_Chi Phí'!$F$56)/('DIA_Giá và Doanh Thu'!$I$8+'DIA_Giá và Doanh Thu'!$I$7),0)),0)) -> 37.483193 | C82: Kết quả thay đổi theo kịch bản và giả định.
A85: 3.2. Unit Economics
A86: Chỉ tiêu | B86: Năm 1 | C86: Năm 2 | D86: Năm 3
A87: CAC người dùng Premium | B87: =IFERROR('DIA_Chi Phí'!$C$30*'DIA_Giả Định'!$N$72/(('DIA_Giả Định'!$N$6*'DIA_Giả Định'!$N$8)),0) -> 45000 | C87: =IFERROR('DIA_Chi Phí'!$E$30*'DIA_Giả Định'!$O$72/(MAX(0,('DIA_Giả Định'!$O$6*'DIA_Giả Định'!$O$8)-('DIA_Giả Định'!$N$6*'DIA_Giả Định'!$N$8)*POWER(1-'DIA_Giả Định'!$O$17,'DIA_Giả Định'!$O$5))),0) -> 20656.587 | D87: =IFERROR('DIA_Chi Phí'!$G$30*'DIA_Giả Định'!$P$72/(MAX(0,('DIA_Giả Định'!$P$6*'DIA_Giả Định'!$P$8)-('DIA_Giả Định'!$O$6*'DIA_Giả Định'!$O$8)*POWER(1-'DIA_Giả Định'!$P$17,'DIA_Giả Định'!$P$5))),0) -> 0
A88: CAC khách hàng B2B | B88: =IFERROR(('DIA_Chi Phí'!$C$29+'DIA_Chi Phí'!$C$30*(1-'DIA_Giả Định'!$N$72)+'DIA_Chi Phí'!$C$40)/'DIA_Giả Định'!$N$29,0) -> 26571429 | C88: =IFERROR(('DIA_Chi Phí'!$E$29+'DIA_Chi Phí'!$E$30*(1-'DIA_Giả Định'!$O$72)+'DIA_Chi Phí'!$E$40)/'DIA_Giả Định'!$O$29,0) -> 19846154 | D88: =IFERROR(('DIA_Chi Phí'!$G$29+'DIA_Chi Phí'!$G$30*(1-'DIA_Giả Định'!$P$72)+'DIA_Chi Phí'!$G$40)/'DIA_Giả Định'!$P$29,0) -> 15120000
A89: LTV người dùng Premium (12 tháng) | B89: ='DIA_Giá và Doanh Thu'!$F$21*12*B35 -> 249317.19 | C89: ='DIA_Giá và Doanh Thu'!$G$21*12*C35 -> 250422.07 | D89: ='DIA_Giá và Doanh Thu'!$H$21*12*D35 -> 371022.7
A90: LTV khách hàng B2B (24 tháng) | B90: ='DIA_Giá và Doanh Thu'!$F$22*24*B35 -> 35837465 | C90: ='DIA_Giá và Doanh Thu'!$G$22*24*C35 -> 37314403 | D90: ='DIA_Giá và Doanh Thu'!$H$22*24*D35 -> 54587243
A91: LTV/CAC B2C | B91: =IFERROR(B89/B87,0) -> 5.540382 | C91: =IFERROR(C89/C87,0) -> 12.12311 | D91: =IFERROR(D89/D87,0) -> 0
A92: LTV/CAC B2B | B92: =IFERROR(B90/B88,0) -> 1.3487218 | C92: =IFERROR(C90/C88,0) -> 1.8801831 | D92: =IFERROR(D90/D88,0) -> 3.6102674
A93: Contribution Margin / người dùng Premium | B93: =('DIA_Giá và Doanh Thu'!$F$21*'DIA_Giả Định'!$N$5-'DIA_Giả Định'!$N$23*'DIA_Giả Định'!$N$45*'DIA_Giả Định'!$N$5-('DIA_Giả Định'!$N$46+'DIA_Giả Định'!$N$47+'DIA_Giả Định'!$N$48)*'DIA_Giả Định'!$N$5-'DIA_Giá và Doanh Thu'!$F$21*'DIA_Giả Định'!$N$5*'DIA_Giả Định'!$N$49-'DIA_Giả Định'!$N$50*'DIA_Giả Định'!$N$5-'DIA_Giả Định'!$N$56*'DIA_Giả Định'!$N$57) -> 324717.5 | C93: =('DIA_Giá và Doanh Thu'!$G$21*'DIA_Giả Định'!$O$5-'DIA_Giả Định'!$O$23*'DIA_Giả Định'!$O$45*'DIA_Giả Định'!$O$5-('DIA_Giả Định'!$O$46+'DIA_Giả Định'!$O$47+'DIA_Giả Định'!$O$48)*'DIA_Giả Định'!$O$5-'DIA_Giá và Doanh Thu'!$G$21*'DIA_Giả Định'!$O$5*'DIA_Giả Định'!$O$49-'DIA_Giả Định'!$O$50*'DIA_Giả Định'!$O$5-'DIA_Giả Định'!$O$56*'DIA_Giả Định'!$O$57) -> 351719.12 | D93: =('DIA_Giá và Doanh Thu'!$H$21*'DIA_Giả Định'!$P$5-'DIA_Giả Định'!$P$23*'DIA_Giả Định'!$P$45*'DIA_Giả Định'!$P$5-('DIA_Giả Định'!$P$46+'DIA_Giả Định'!$P$47+'DIA_Giả Định'!$P$48)*'DIA_Giả Định'!$P$5-'DIA_Giá và Doanh Thu'!$H$21*'DIA_Giả Định'!$P$5*'DIA_Giả Định'!$P$49-'DIA_Giả Định'!$P$50*'DIA_Giả Định'!$P$5-'DIA_Giả Định'!$P$56*'DIA_Giả Định'!$P$57) -> 384318.83
A94: Contribution Margin / cơ sở y tế | B94: =IFERROR((B31-'DIA_Chi Phí'!$D$54-'DIA_Chi Phí'!$D$56)/('DIA_Giá và Doanh Thu'!$G$8+'DIA_Giá và Doanh Thu'!$G$7),0) -> 23108833 | C94: =IFERROR((C31-'DIA_Chi Phí'!$E$54-'DIA_Chi Phí'!$E$56)/('DIA_Giá và Doanh Thu'!$H$8+'DIA_Giá và Doanh Thu'!$H$7),0) -> 25952196 | D94: =IFERROR((D31-'DIA_Chi Phí'!$F$54-'DIA_Chi Phí'!$F$56)/('DIA_Giá và Doanh Thu'!$I$8+'DIA_Giá và Doanh Thu'!$I$7),0) -> 28035896
A95: Thời gian hoàn vốn CAC B2C | B95: =IFERROR(B87/(B93/'DIA_Giả Định'!$N$5),0) -> 1.662984 | C95: =IFERROR(C87/(C93/'DIA_Giả Định'!$O$5),0) -> 0.7047642 | D95: =IFERROR(D87/(D93/'DIA_Giả Định'!$P$5),0) -> 0
A96: Thời gian hoàn vốn CAC B2B | B96: =IFERROR(B88/(B94/'DIA_Giả Định'!$N$5),0) -> 13.798063 | C96: =IFERROR(C88/(C94/'DIA_Giả Định'!$O$5),0) -> 9.1766355 | D96: =IFERROR(D88/(D94/'DIA_Giả Định'!$P$5),0) -> 6.4717033
B252: Dòng tiền ròng tổng hợp (IRR) | C252: =C249 -> 0 | D252: =D249+D250 -> 0 | E252: =E249+E250 -> 0 | F252: =F249+F250 -> 0 | G252: =IRR(C252:F252) -> #NUM!
B253: Giá trị thanh lý (Terminal Value) | F253: =MAX(0, F238 * 8) -> 0
B254: Dòng tiền ròng tổng hợp (chạy IRR) | C254: =C249+C250 -> 0 | D254: =D249+D250 -> 0 | E254: =E249+E250 -> 0 | F254: =F249+F250+F253 -> 0 | G254: =IRR(C254:F254, 0.1) -> #NUM!
B255: Dòng tiền lũy kế (Funding) | C255: =C254 -> 0 | D255: =C255+D254 -> 0 | E255: =D255+E254 -> 0 | F255: =E255+F254 -> 0

Sheet DIA_Giá và Doanh Thu
A2: Kịch bản
A3: Tên gói | B3: Đối tượng khách hàng | C3: Giá niêm yết Năm 1 | D3: Chu kỳ thanh toán | E3: Chiết khấu | F3: Giá thực thu Năm 1 | G3: Khách hàng Năm 1 | H3: Khách hàng Năm 2 | I3: Khách hàng Năm 3 | J3: Doanh thu Năm 1 | K3: Doanh thu Năm 2 | L3: Doanh thu Năm 3 | M3: Tỷ trọng DT Năm 1 | N3: Tỷ trọng DT Năm 2 | O3: Tỷ trọng DT Năm 3 | P3: Ghi chú
A4: DIA+ Free | B4: Người dùng cá nhân | C4: 0 | D4: Miễn phí | E4: 0 | F4: 0 | G4: =MAX(0,'DIA_Giả Định'!$N$6-('DIA_Giả Định'!$N$6*'DIA_Giả Định'!$N$8)) -> 67200 | H4: =MAX(0,'DIA_Giả Định'!$O$6-('DIA_Giả Định'!$O$6*'DIA_Giả Định'!$O$8)) -> 180500 | I4: =MAX(0,'DIA_Giả Định'!$P$6-('DIA_Giả Định'!$P$6*'DIA_Giả Định'!$P$8)) -> 65800 | J4: 0 | K4: 0 | L4: 0 | M4: =IFERROR(J4/$F$20,0) -> 0 | N4: =IFERROR(K4/$G$20,0) -> 0 | O4: =IFERROR(L4/$H$20,0) -> 0 | P4: Phễu thu hút người dùng; không tạo doanh thu trực tiếp. Tính năng cơ bản gồm ghi nhận glucose và nhắc thuốc.
A5: DIA+ Pro/Tháng | B5: Người dùng cá nhân | C5: ='DIA_Giả Định'!$N$35 -> 39000 | D5: Tháng | E5: 0 | F5: ='DIA_Giả Định'!$N$35 -> 39000 | G5: =('DIA_Giả Định'!$N$6*'DIA_Giả Định'!$N$8)*'DIA_Giả Định'!$N$9 -> 1960 | H5: =('DIA_Giả Định'!$O$6*'DIA_Giả Định'!$O$8)*'DIA_Giả Định'!$O$9 -> 6175 | I5: =('DIA_Giả Định'!$P$6*'DIA_Giả Định'!$P$8)*'DIA_Giả Định'!$P$9 -> 2520 | J5: =G5*'DIA_Giả Định'!$N$35*'DIA_Giả Định'!$N$5 -> 9.1728e+08 | K5: =H5*'DIA_Giả Định'!$O$35*'DIA_Giả Định'!$O$5 -> 3.1924725e+09 | L5: =I5*'DIA_Giả Định'!$P$35*'DIA_Giả Định'!$P$5 -> 1.4392462e+09 | M5: =IFERROR(J5/$F$20,0) -> 0.41672951 | N5: =IFERROR(K5/$G$20,0) -> 0.46113687 | O5: =IFERROR(L5/$H$20,0) -> 0.1586963 | P5: Doanh thu định kỳ B2C theo tháng; số khách hàng = người dùng Premium × tỷ trọng trả tháng.
A6: DIA+ Pro/Năm | B6: Người dùng cá nhân | C6: ='DIA_Giả Định'!$N$36 -> 399000 | D6: Năm | E6: =IFERROR(1-'DIA_Giả Định'!$N$36/('DIA_Giả Định'!$N$35*'DIA_Giả Định'!$N$5),0) -> 0.1474359 | F6: ='DIA_Giả Định'!$N$36 -> 399000 | G6: =('DIA_Giả Định'!$N$6*'DIA_Giả Định'!$N$8)*'DIA_Giả Định'!$N$10 -> 840 | H6: =('DIA_Giả Định'!$O$6*'DIA_Giả Định'!$O$8)*'DIA_Giả Định'!$O$10 -> 3325 | I6: =('DIA_Giả Định'!$P$6*'DIA_Giả Định'!$P$8)*'DIA_Giả Định'!$P$10 -> 1680 | J6: =G6*'DIA_Giả Định'!$N$36 -> 335160000 | K6: =H6*'DIA_Giả Định'!$O$36 -> 1.4593425e+09 | L6: =I6*'DIA_Giả Định'!$P$36 -> 8.110872e+08 | M6: =IFERROR(J6/$F$20,0) -> 0.15226655 | N6: =IFERROR(K6/$G$20,0) -> 0.21079481 | O6: =IFERROR(L6/$H$20,0) -> 0.089433296 | P6: Doanh thu định kỳ B2C theo năm; mức chiết khấu được tính từ giá tháng và giá năm trong sheet giả định.
A7: DIA+ Clinic/Tháng | B7: Phòng khám, Bệnh viện, Trung tâm y tế | C7: 990000 | D7: Tháng | E7: 0 | F7: 990000 | G7: ='DIA_Giả Định'!$N$26*'DIA_Giả Định'!$N$30 -> 25 | H7: ='DIA_Giả Định'!$N$26+'DIA_Giả Định'!$O$28*'DIA_Giả Định'!$O$30 -> 55 | I7: ='DIA_Giả Định'!$O$26+'DIA_Giả Định'!$P$28*'DIA_Giả Định'!$P$30 -> 160 | J7: =G7*'DIA_Giả Định'!$N$37*'DIA_Giả Định'!$N$5 -> 269700000 | K7: =H7*'DIA_Giả Định'!$O$37*'DIA_Giả Định'!$O$5 -> 655462698 | L7: =I7*'DIA_Giả Định'!$P$37*'DIA_Giả Định'!$P$5 -> 2.1064426e+09 | M7: =IFERROR(J7/$F$20,0) -> 0.12252742 | N7: =IFERROR(K7/$G$20,0) -> 0.094678345 | O7: =IFERROR(L7/$H$20,0) -> 0.23226369 | P7: Thuê bao SaaS cho phòng khám; số cơ sở hoạt động bình quân phản ánh thời điểm ký mới trong năm.
A8: DIA+ Clinic/Năm | B8: Phòng khám, Bệnh viện, Trung tâm y tế | C8: 9900000 | D8: Tháng | E8: 0 | F8: 9900000 | G8: ='DIA_Giả Định'!$N$25*'DIA_Giả Định'!$N$30 -> 5 | H8: ='DIA_Giả Định'!$N$25+'DIA_Giả Định'!$O$27*'DIA_Giả Định'!$O$30 -> 11.5 | I8: ='DIA_Giả Định'!$O$25+'DIA_Giả Định'!$P$27*'DIA_Giả Định'!$P$30 -> 32.5 | J8: =G8*'DIA_Giả Định'!$N$38*'DIA_Giả Định'!$N$5 -> 534000000 | K8: =H8*'DIA_Giả Định'!$O$38*'DIA_Giả Định'!$O$5 -> 1351020000 | L8: =I8*'DIA_Giả Định'!$P$38*'DIA_Giả Định'!$P$5 -> 4.19991e+09 | M8: =IFERROR(J8/$F$20,0) -> 0.24260156 | N8: =IFERROR(K8/$G$20,0) -> 0.19514816 | O8: =IFERROR(L8/$H$20,0) -> 0.46309669 | P8: Thuê bao SaaS cho bệnh viện; gồm quản lý bệnh nhân từ xa, cảnh báo và chia sẻ dữ liệu với bác sĩ.
A9: Phí triển khai/bệnh viện | B9: Cơ sở ký mới | C9: =IFERROR(('DIA_Giả Định'!$N$27*'DIA_Giả Định'!$N$39)/'DIA_Giả Định'!$N$29,0) -> 8571428.6 | D9: Một lần | E9: 0 | F9: =C9 -> 8571428.6 | G9: ='DIA_Giả Định'!$N$27 -> 2 | H9: ='DIA_Giả Định'!$O$27 -> 3 | I9: ='DIA_Giả Định'!$P$27 -> 5 | J9: ='DIA_Giả Định'!$N$27*'DIA_Giả Định'!$N$39 -> 60000000 | K9: ='DIA_Giả Định'!$O$27*'DIA_Giả Định'!$O$39 -> 90000000 | L9: ='DIA_Giả Định'!$P$27*'DIA_Giả Định'!$P$39 -> 150000000 | M9: =IFERROR(J9/$F$20,0) -> 0.027258602 | N9: =IFERROR(K9/$G$20,0) -> 0.013000055 | O9: =IFERROR(L9/$H$20,0) -> 0.016539522 | P9: Doanh thu một lần = số cơ sở ký mới × phí triển khai theo từng loại cơ sở.
A10: Phí triển khai/phòng khám | B10: Cơ sở ký mới | C10: =IFERROR(('DIA_Giả Định'!$N$28*'DIA_Giả Định'!$N$40)/'DIA_Giả Định'!$N$29,0) -> 7142857.1 | D10: Một lần | E10: 0 | F10: =C10 -> 7142857.1 | G10: ='DIA_Giả Định'!$N$28 -> 5 | H10: ='DIA_Giả Định'!$O$28 -> 10 | I10: ='DIA_Giả Định'!$P$28 -> 20 | J10: ='DIA_Giả Định'!$N$28*'DIA_Giả Định'!$N$40 -> 50000000 | K10: ='DIA_Giả Định'!$O$28*'DIA_Giả Định'!$O$40 -> 100000000 | L10: ='DIA_Giả Định'!$P$28*'DIA_Giả Định'!$P$40 -> 200000000 | M10: =IFERROR(J10/$F$20,0) -> 0.022715502 | N10: =IFERROR(K10/$G$20,0) -> 0.014444505 | O10: =IFERROR(L10/$H$20,0) -> 0.022052696 | P10: Doanh thu một lần = số cơ sở ký mới × phí triển khai theo từng loại cơ sở.
A11: Phí đào tạo | B11: Cơ sở ký mới | C11: ='DIA_Giả Định'!$N$41 -> 2000000 | D11: Một lần | E11: 0 | F11: ='DIA_Giả Định'!$N$41 -> 2000000 | G11: ='DIA_Giả Định'!$N$29 -> 7 | H11: ='DIA_Giả Định'!$O$29 -> 13 | I11: ='DIA_Giả Định'!$P$29 -> 25 | J11: =G11*'DIA_Giả Định'!$N$41 -> 14000000 | K11: =H11*'DIA_Giả Định'!$O$41 -> 26000000 | L11: =I11*'DIA_Giả Định'!$P$41 -> 50000000 | M11: =IFERROR(J11/$F$20,0) -> 0.0063603406 | N11: =IFERROR(K11/$G$20,0) -> 0.0037555714 | O11: =IFERROR(L11/$H$20,0) -> 0.0055131739 | P11: Doanh thu dịch vụ một lần = số cơ sở ký mới × phí đào tạo.
A12: Phí tích hợp hệ thống/API | B12: Cơ sở mua tích hợp | C12: ='DIA_Giả Định'!$N$42 -> 15000000 | D12: Một lần | E12: 0 | F12: ='DIA_Giả Định'!$N$42 -> 15000000 | G12: ='DIA_Giả Định'!$N$29*'DIA_Giả Định'!$N$43 -> 1.4 | H12: ='DIA_Giả Định'!$O$29*'DIA_Giả Định'!$O$43 -> 3.25 | I12: ='DIA_Giả Định'!$P$29*'DIA_Giả Định'!$P$43 -> 7.5 | J12: =G12*'DIA_Giả Định'!$N$42 -> 21000000 | K12: =H12*'DIA_Giả Định'!$O$42 -> 48750000 | L12: =I12*'DIA_Giả Định'!$P$42 -> 112500000 | M12: =IFERROR(J12/$F$20,0) -> 0.0095405108 | N12: =IFERROR(K12/$G$20,0) -> 0.0070416964 | O12: =IFERROR(L12/$H$20,0) -> 0.012404641 | P12: Doanh thu tích hợp = số cơ sở ký mới × tỷ lệ mua API × phí tích hợp hệ thống.
A14: TỔNG HỢP DOANH THU & CHỈ SỐ SaaS | F14: Năm 1 | G14: Năm 2 | H14: Năm 3
A15: Doanh thu định kỳ B2C | F15: =SUM(J5:J6) -> 1.25244e+09 | G15: =SUM(K5:K6) -> 4.651815e+09 | H15: =SUM(L5:L6) -> 2.2503334e+09
A16: Doanh thu định kỳ B2B | F16: =SUM(J7:J8) -> 803700000 | G16: =SUM(K7:K8) -> 2006482698 | H16: =SUM(L7:L8) -> 6.3063526e+09
A17: Doanh thu triển khai một lần/bệnh viện | F17: =J9 -> 60000000 | G17: =K9 -> 90000000 | H17: =L9 -> 150000000
A18: Doanh thu triển khai một lần/phòng khám | F18: =J10 -> 50000000 | G18: =K10 -> 100000000 | H18: =L10 -> 200000000
A19: Doanh thu dịch vụ khác | F19: =SUM(J11:J12) -> 35000000 | G19: =SUM(K11:K12) -> 74750000 | H19: =SUM(L11:L12) -> 162500000
A20: Tổng doanh thu | F20: =SUM(F15:F19) -> 2201140000 | G20: =SUM(G15:G19) -> 6.9230477e+09 | H20: =SUM(H15:H19) -> 9.069186e+09
A21: ARPU B2C / tháng - Doanh thu trung bình trên 1 người dùng mỗi tháng | F21: =IFERROR(F15/('DIA_Giả Định'!$N$6*'DIA_Giả Định'!$N$8*'DIA_Giả Định'!$N$5),0) -> 37275 | G21: =IFERROR(G15/('DIA_Giả Định'!$O$6*'DIA_Giả Định'!$O$8*'DIA_Giả Định'!$O$5),0) -> 40805.395 | H21: =IFERROR(H15/('DIA_Giả Định'!$P$6*'DIA_Giả Định'!$P$8*'DIA_Giả Định'!$P$5),0) -> 44649.473
A22: ARPU B2B / tháng - Doanh thu trung bình trên một khách hàng doanh nghiệp mỗi tháng | F22: =IFERROR(F16/((G7)*'DIA_Giả Định'!$N$5),0) -> 2679000 | G22: =IFERROR(G16/((H7)*'DIA_Giả Định'!$O$5),0) -> 3040125.3 | H22: =IFERROR(H16/((I7)*'DIA_Giả Định'!$P$5),0) -> 3284558.6
A23: MRR (Monthly Recurring Revenue - Doanh thu định kỳ hàng tháng) | F23: =IFERROR((F15+F16)/'DIA_Giả Định'!$N$5,0) -> 1.71345e+08 | G23: =IFERROR((G15+G16)/'DIA_Giả Định'!$O$5,0) -> 5.5485814e+08 | H23: =IFERROR((H15+H16)/'DIA_Giả Định'!$P$5,0) -> 7.1305717e+08
A24: ARR (Annual Recurring Revenue - Doanh thu định kỳ hàng năm) | F24: =F15+F16 -> 2.05614e+09 | G24: =G15+G16 -> 6.6582977e+09 | H24: =H15+H16 -> 8.556686e+09
A25: Tăng trưởng doanh thu | F25: 0 | G25: =IFERROR(G20/F20-1,0) -> 2.1452101 | H25: =IFERROR(H20/G20-1,0) -> 0.30999906
A26: Tỷ lệ doanh thu định kỳ | F26: =IFERROR(F24/F20,0) -> 0.93412504 | G26: =IFERROR(G24/G20,0) -> 0.96175817 | H26: =IFERROR(H24/H20,0) -> 0.94348997
A27: Doanh thu / MAU | F27: =IFERROR(F20/('DIA_Giả Định'!$N$6*'DIA_Giả Định'!$N$7),0) -> 89842.449 | G27: =IFERROR(G20/('DIA_Giả Định'!$O$6*'DIA_Giả Định'!$O$7),0) -> 80971.318 | H27: =IFERROR(H20/('DIA_Giả Định'!$P$6*'DIA_Giả Định'!$P$7),0) -> 235563.27

Sheet DIA_Tóm Tắt
A1: DIA+ - DASHBOARD TÀI CHÍNH 3 NĂM
A2: Kịch bản thi khởi nghiệp: Lean MVP → Pilot y tế → Mở rộng B2B2C
A3: Kịch bản | B3: ='DIA_Giả Định'!$B$2 -> Cơ sở
A5: KPI VẬN HÀNH & TÀI CHÍNH | F5: CHỈ SỐ NHÀ ĐẦU TƯ
A6: Chỉ tiêu | B6: Năm 1 | C6: Năm 2 | D6: Năm 3 | F6: Chỉ tiêu | G6: Giá trị | H6: Chỉ tiêu | I6: Giá trị
A7: Tổng người dùng | B7: ='DIA_Giả Định'!$N$6 -> 70000 | C7: ='DIA_Giả Định'!$O$6 -> 190000 | D7: ='DIA_Giả Định'!$P$6 -> 70000 | F7: NPV | G7: ='DIA_Hiệu Quả TC'!B70 -> 1.8387153e+08 | H7: IRR | I7: =IFERROR('DIA_Hiệu Quả TC'!B71, "Âm") -> 0.22137183
A8: Người dùng hoạt động | B8: ='DIA_Giả Định'!$N$6*'DIA_Giả Định'!$N$7 -> 24500 | C8: ='DIA_Giả Định'!$O$6*'DIA_Giả Định'!$O$7 -> 85500 | D8: ='DIA_Giả Định'!$P$6*'DIA_Giả Định'!$P$7 -> 38500 | F8: Hoàn vốn | G8: ='DIA_Hiệu Quả TC'!B72 -> 2.453754 | H8: Doanh thu hòa vốn | I8: ='DIA_Hiệu Quả TC'!B80 -> 4.1037696e+09
A9: Người dùng Pro | B9: ='DIA_Giả Định'!$N$6*'DIA_Giả Định'!$N$8 -> 2800 | C9: ='DIA_Giả Định'!$O$6*'DIA_Giả Định'!$O$8 -> 9500 | D9: ='DIA_Giả Định'!$P$6*'DIA_Giả Định'!$P$8 -> 4200 | F9: CAC B2C Năm 3 | G9: ='DIA_Hiệu Quả TC'!$D$87 -> 0 | H9: LTV B2C 12T Năm 3 | I9: ='DIA_Hiệu Quả TC'!$D$89 -> 371022.7
A10: Số cơ sở y tế | B10: ='DIA_Giả Định'!$N$25+'DIA_Giả Định'!$N$26 -> 60 | C10: ='DIA_Giả Định'!$O$25+'DIA_Giả Định'!$O$26 -> 180 | D10: ='DIA_Giả Định'!$P$25+'DIA_Giả Định'!$P$26 -> 40 | F10: LTV/CAC B2C | G10: ='DIA_Hiệu Quả TC'!$D$91 -> 0 | H10: Burn Rate | I10: ='DIA_Hiệu Quả TC'!$B$78 -> 34572758
A11: Doanh thu | B11: ='DIA_Hiệu Quả TC'!$B$29 -> 2201140000 | C11: ='DIA_Hiệu Quả TC'!$C$29 -> 6.9230477e+09 | D11: ='DIA_Hiệu Quả TC'!$D$29 -> 9.069186e+09 | F11: Runway | G11: ='DIA_Hiệu Quả TC'!$B$79 -> 8.6773522 | H11: CAC B2B Năm 3 | I11: ='DIA_Hiệu Quả TC'!$D$88 -> 15120000
A12: ARR | B12: ='DIA_Giá và Doanh Thu'!$F$24 -> 2.05614e+09 | C12: ='DIA_Giá và Doanh Thu'!$G$24 -> 6.6582977e+09 | D12: ='DIA_Giá và Doanh Thu'!$H$24 -> 8.556686e+09 | F12: LTV B2B 24T Năm 3 | G12: ='DIA_Hiệu Quả TC'!$D$90 -> 54587243 | H12: LTV/CAC B2B | I12: ='DIA_Hiệu Quả TC'!$D$92 -> 3.6102674
A13: Tổng chi phí | B13: ='DIA_Chi Phí'!$D$65 -> 2616013100 | C13: ='DIA_Chi Phí'!$E$65 -> 5.6182447e+09 | D13: ='DIA_Chi Phí'!$F$65 -> 5.6307688e+09 | F13: Nhu cầu vốn | G13: =MAX(0, -MIN('DIA_Hiệu Quả TC'!C64:E64)) -> 1989268480 | H13: =-MIN('DIA_Hiệu Quả TC'!C64:E64) -> 1989268480 | I13: =ROUNDUP(G13 / 100000000, 0) * 100000000 -> 2000000000
A14: Lợi nhuận gộp | B14: ='DIA_Hiệu Quả TC'!$B$34 -> 1226876900 | C14: ='DIA_Hiệu Quả TC'!$C$34 -> 3.540553e+09 | D14: ='DIA_Hiệu Quả TC'!$D$34 -> 6.2801673e+09
A15: EBITDA | B15: ='DIA_Hiệu Quả TC'!$B$40 -> -414873100 | C15: ='DIA_Hiệu Quả TC'!$C$40 -> 1.304803e+09 | D15: ='DIA_Hiệu Quả TC'!$D$40 -> 3.4384173e+09
A16: Lợi nhuận sau thuế | B16: ='DIA_Hiệu Quả TC'!$B$47 -> -904273100 | C16: ='DIA_Hiệu Quả TC'!$C$47 -> 1.0158824e+09 | D16: ='DIA_Hiệu Quả TC'!$D$47 -> 2.7227738e+09
A17: Dòng tiền ròng | B17: ='DIA_Hiệu Quả TC'!$C$60 -> -414873100 | C17: ='DIA_Hiệu Quả TC'!$D$60 -> 8.518324e+08 | D17: ='DIA_Hiệu Quả TC'!$E$60 -> 2.5067238e+09
A18: Dòng tiền lũy kế | B18: ='DIA_Hiệu Quả TC'!$C$61 -> -414873100 | C18: ='DIA_Hiệu Quả TC'!$D$61 -> 4.369593e+08 | D18: ='DIA_Hiệu Quả TC'!$E$61 -> 2.9436831e+09
A21: KẾT LUẬN TỰ ĐỘNG
A22: Hiệu quả tài chính | D22: =IF(AND('DIA_Hiệu Quả TC'!$B$70>0,'DIA_Hiệu Quả TC'!$B$71>'DIA_Giả Định'!$N$60),"Đạt yêu cầu tài chính","Cần điều chỉnh giả định") -> Đạt yêu cầu tài chính
A23: Hòa vốn | D23: =IF(AND('DIA_Hiệu Quả TC'!$D$40>0,'DIA_Hiệu Quả TC'!$E$64>=0),"Hoàn vốn trong năm 3","Chưa hoàn vốn trong 3 năm") -> Hoàn vốn trong năm 3
A24: Dòng tiền | D24: =IF('DIA_Hiệu Quả TC'!$E$61<0,"Dòng tiền chưa cân bằng",IF(MIN('DIA_Hiệu Quả TC'!$C$61:$E$61)<0,"Cần bố trí vốn lưu động giai đoạn đầu","Dòng tiền được kiểm soát")) -> Cần bố trí vốn lưu động giai đoạn đầu
A25: Khuyến nghị tổng hợp | D25: =IF(AND(D22="Đạt yêu cầu tài chính",D23="Hoàn vốn trong năm 3",'DIA_Hiệu Quả TC'!$E$61>=0),"Khả thi có điều kiện – đề xuất gọi vốn "&TEXT(I13/1000000000,"0.0")&" tỷ đồng","Cần điều chỉnh giả định") -> Khả thi có điều kiện – đề xuất gọi vốn 2.0 tỷ đồng
A29: Năm | B29: Doanh thu | C29: Tổng chi phí
A30: Năm 1 | B30: =B11 -> 2201140000 | C30: =B13 -> 2616013100
A31: Năm 2 | B31: =C11 -> 6.9230477e+09 | C31: =C13 -> 5.6182447e+09
A32: Năm 3 | B32: =D11 -> 9.069186e+09 | C32: =D13 -> 5.6307688e+09
A35: Cơ cấu doanh thu Năm 3 | B35: Giá trị
A36: B2C | B36: ='DIA_Hiệu Quả TC'!$D$30 -> 2.2503334e+09
A37: B2B | B37: ='DIA_Hiệu Quả TC'!$D$31 -> 6.3063526e+09
A38: Triển khai & dịch vụ | B38: ='DIA_Hiệu Quả TC'!$D$32 -> 362500000
B40: Thời gian hoàn vốn (DPP) | D40: > 3 | E40: năm (Chưa thu hồi vốn)
A41: Năm | B41: Tổng người dùng | C41: Pro
A42: Năm 1 | B42: =B7 -> 70000 | C42: =B9 -> 2800
A43: Năm 2 | B43: =C7 -> 190000 | C43: =C9 -> 9500
A44: Năm 3 | B44: =D7 -> 70000 | C44: =D9 -> 4200
A47: Năm | B47: Dòng tiền ròng | C47: Dòng tiền lũy kế
A48: Năm 1 | B48: =B17 -> -414873100 | C48: =B18 -> -414873100
A49: Năm 2 | B49: =C17 -> 8.518324e+08 | C49: =C18 -> 4.369593e+08
A50: Năm 3 | B50: =D17 -> 2.5067238e+09 | C50: =D18 -> 2.9436831e+09
